Workbook

Sheet BASE
B2: CNPJ | C2: EMPRESAS | D2: CÓDIGO SISTEMA | E2: INTEGRAÇÃO FINANCEIRA | F2: ATIVIDADE OPERACIONAL | G2: REGIME TRIBUTÁRIO | H2: INFORMAÇÃO DE FOLHA DE PAGAMENTO | I2: STATUS DE FECHAMENTO | J2: RESPONSÁVEL | K2: COMPETÊNCIA DE FECHAMENTO | L2: FECHAMENTOS EM 10.2025 | M2: FECHAMENTOS EM 11.2025 | N2: FECHAMENTOS EM 12.2025 | O2: FECHAMENTOS EM 01.2026 | P2: FECHAMENTOS EM 02.2026 | Q2: FECHAMENTOS EM 03.2026
A3: 1 | B3: 28523040000137 | C3: 180X NEGOCIOS DIGITAIS LTDA | D3: 555 | E3: CAIXA | F3: SERVIÇO | G3: LUCRO PRESUMIDO | H3: SEM FOLHA | I3: =APOIO!L3 -> EM DIA | J3: INGRID | K3: 46023 | L3: 45931 | M3: 45962 | N3: 45992 | Q3: 46082
A4: =A3+1 -> 2 | B4: 63849413000165 | C4: 2RV ADMINISTRACAO E CONSULTORIA LTDA | D4: 259 | E4: ACOMPANHAR | F4: SERVIÇO/COMÉRCIO | G4: SIMPLES NACIONAL | H4: SEM FOLHA | I4: =APOIO!L4 -> EM ATRASO | J4: KELVIN | K4: 45931 | O4: 46023 | Q4: 46082
A5: =A4+1 -> 3 | B5: 52613816000194 | C5: 3.5 ESPORTE E SAÚDE LTDA (TAGUATINGA) | D5: 183 | E5: BANCO | F5: SERVIÇO | G5: SIMPLES NACIONAL | H5: FOLHA | I5: =APOIO!L5 -> EM DIA | J5: INGRID | K5: 46023 | L5: 45931 | Q5: 46082
A6: =A5+1 -> 4 | B6: 53114412000119 | C6: 3.6 ESPORTE E SAÚDE LTDA | D6: 130 | E6: BPO | F6: SERVIÇO | G6: LUCRO PRESUMIDO | H6: FOLHA | I6: =APOIO!L6 -> EM ATRASO | J6: KELVIN | K6: 45931 | M6: 45962 | N6: 45992
A7: =A6+1 -> 5 | B7: 65173227000184 | C7: ACADEMIA CEILANDIA DUE LTDA | D7: 272 | E7: ACOMPANHAR | F7: SERVIÇO | G7: SIMPLES NACIONAL | H7: SEM FOLHA | I7: =APOIO!L7 -> EM DIA | J7: KELVIN | K7: 46054
A8: =A7+1 -> 6 | B8: 57407089000122 | C8: ACADEMIA CEILANDIA ESPORTE SAUDE LTDA | D8: 195 | E8: CAIXA | F8: SERVIÇO | G8: LUCRO PRESUMIDO | H8: SEM FOLHA | I8: =APOIO!L8 -> EM ATRASO | J8: KELVIN | K8: 45931 | M8: 45962 | N8: 45992
A9: =A8+1 -> 7 | B9: 9404697000130 | C9: ACADEMIA PERSONAL FITNESS LTDA (LIVE 3.3) | D9: 134 | E9: CAIXA | F9: SERVIÇO/COMÉRCIO | G9: SIMPLES NACIONAL | H9: FOLHA | I9: =APOIO!L9 -> EM ATRASO | J9: KELVIN | K9: 45931 | M9: 45962 | N9: 45992
A10: =A9+1 -> 8 | B10: 43798918000130 | C10: AG COMERCIO E MERCEARIA LTDA | D10: 408 | E10: BANCO | F10: COMÉRCIO | G10: LUCRO REAL | H10: SEM FOLHA | I10: =APOIO!L10 -> EM ATRASO | J10: KELVIN | K10: 45931 | L10: 45931
A11: =A10+1 -> 9 | B11: 54711482000117 | C11: AGENCIA 33 MARKETING E NEGOCIOS DIGITAIS LTDA | D11: 148 | E11: CAIXA | F11: SERVIÇO | G11: SIMPLES NACIONAL | H11: SEM FOLHA | I11: =APOIO!L11 -> EM ATRASO | J11: KELVIN | K11: 45931 | M11: 45962 | N11: 45992
A12: =A11+1 -> 10 | B12: 42730764000182 | C12: AGRO VIRA LATA COMÉRCIO DE ARTIGOS PARA ANIMAIS E SERVIÇOES LTDA | D12: 389 | E12: CAIXA | F12: SERVIÇO/COMÉRCIO | G12: SIMPLES NACIONAL | H12: FOLHA | I12: =APOIO!L12 -> EM ATRASO | J12: INGRID | K12: 45931 | M12: 45962 | N12: 45992
A13: =A12+1 -> 11 | B13: 64899759000130 | C13: AHAVA ENERGIA SOLAR | D13: 270 | E13: NIBO | F13: SERVIÇO/COMÉRCIO | G13: LUCRO PRESUMIDO | H13: SEM FOLHA | I13: =APOIO!L13 -> EM DIA | J13: KELVIN | K13: 46054 | P13: 46054
A14: =A13+1 -> 12 | B14: 24924847000120 | C14: ALDEMIR CANDIDO DE RESENDE ME | D14: 263 | E14: ACOMPANHAR | F14: SERVIÇO/COMÉRCIO | G14: SIMPLES NACIONAL | H14: SEM FOLHA | I14: =APOIO!L14 -> EM DIA | J14: INGRID | K14: 46023 | O14: 46023 | P14: 46054
A15: =A14+1 -> 13 | B15: 35965694000186 | C15: ALLEGRO COMÉRCIO DE ROUPAS | D15: 232 | E15: NIBO | F15: COMÉRCIO | G15: SIMPLES NACIONAL | H15: FOLHA | I15: =APOIO!L15 -> EM ATRASO | J15: KELVIN | K15: 45778
A16: =A15+1 -> 14 | B16: 28251192000128 | C16: ALMED SERVICOS MEDICOS LTDA | D16: 154 | E16: CAIXA | F16: SERVIÇO | G16: SIMPLES NACIONAL | H16: FATOR R | I16: =APOIO!L16 -> EM ATRASO | J16: INGRID | K16: 45901 | L16: 45931 | M16: 45962
A17: =A16+1 -> 15 | B17: 30826817000184 | C17: ALS SOLUÇÕES ESTRUTURAIS LTDA | D17: 268 | E17: ACOMPANHAR | F17: SERVIÇO | G17: LUCRO PRESUMIDO | H17: PRO LABORE | I17: =APOIO!L17 -> EM DIA | J17: INGRID | K17: 46054 | O17: 46054 | P17: 46054
A18: =A17+1 -> 16 | B18: 43106777000148 | C18: ANDRE DA SILVA FERRAZ SOCIEDADE INVIDIDUAL DE ADVOCACIA | D18: 391 | E18: CAIXA | F18: SERVIÇO | G18: SIMPLES NACIONAL | H18: SEM FOLHA | I18: =APOIO!L18 -> EM ATRASO | J18: INGRID | K18: 45901 | L18: 45931 | M18: 45962
A19: =A18+1 -> 17 | B19: 33154864000117 | C19: AO QUADRADO FABRICAÇAO PROPRIA DE PRODUTOS ALIMENTICIOS LTDA | D19: 425 | E19: BANCO | F19: COMÉRCIO | G19: LUCRO REAL | H19: FOLHA | I19: =APOIO!L19 -> EM ATRASO | J19: KELVIN | K19: 45992 | M19: 45962 | O19: 46023
A20: =A19+1 -> 18 | B20: 51055596000168 | C20: APS CONSULTORIA EM VENDAS E CRESCIMENTO LTDA | D20: 82 | E20: CAIXA | F20: SERVIÇO | G20: SIMPLES NACIONAL | H20: PRO LABORE | I20: =APOIO!L20 -> EM ATRASO | J20: INGRID | K20: 45930 | L20: 45931 | M20: 45962
A21: =A20+1 -> 19 | B21: 40192892000194 | C21: ARQ ENG CONSTRUCOES E COMERCIO LTDA | D21: 37 | E21: CAIXA | F21: SERVIÇO | G21: SIMPLES NACIONAL | H21: SEM FOLHA | I21: =APOIO!L21 -> EM ATRASO | J21: KELVIN | K21: 45931 | M21: 45962 | N21: 45992
A22: =A21+1 -> 20 | B22: 686261000107 | C22: ASMRE ASSOC DOS SERV DO MIN DAS REL EXTERIORES | D22: 409 | E22: NIBO | F22: SERVIÇO | G22: LUCRO PRESUMIDO | H22: FOLHA | I22: =APOIO!L22 -> EM ATRASO | J22: KELVIN | K22: 45992 | N22: 45992 | P22: 46054
A23: =A22+1 -> 21 | B23: 32474592000170 | C23: AUDIOFISA GAMA COMÉRCIO DE APARELHOS AUDITIVOS LTDA ME | D23: 114 | E23: CAIXA | F23: SERVIÇO/COMÉRCIO | G23: SIMPLES NACIONAL | H23: SEM FOLHA | I23: =APOIO!L23 -> EM ATRASO | J23: INGRID | K23: 45931 | M23: 45962
A24: =A23+1 -> 22 | B24: 49890800000114 | C24: B2JF COMÉRCIO DE ALIMENTOS LTDA | D24: 10 | E24: CAIXA | F24: COMÉRCIO | G24: LUCRO PRESUMIDO | H24: SEM FOLHA | I24: =APOIO!L24 -> EM ATRASO | J24: KELVIN | K24: 45931 | M24: 45962 | N24: 45992
A25: =A24+1 -> 23 | B25: 62733499000101 | C25: BAHEA COZINHA BAIANA ASA NORTE LTDA | D25: 246 | E25: BANCO | F25: COMÉRCIO | G25: SIMPLES NACIONAL | H25: FOLHA | I25: =APOIO!L25 -> EM ATRASO | J25: KELVIN | K25: 45901 | L25: 45931
A26: =A25+1 -> 24 | B26: 33464640000101 | C26: BAHEA COZINHA BAIANA LTDA | D26: 382 | E26: VOXEL | F26: COMÉRCIO | G26: LUCRO PRESUMIDO | H26: FOLHA | I26: =APOIO!L26 -> EM ATRASO | J26: KELVIN | K26: 45931
A27: =A26+1 -> 25 | B27: 21090763000140 | C27: BANCA CREPE TO GO COMERCIO LTDA | D27: 13 | E27: CAIXA | F27: COMÉRCIO | G27: LUCRO PRESUMIDO | H27: FOLHA | I27: =APOIO!L27 -> EM DIA | J27: INGRID | K27: 46023 | Q27: 46082
A28: =A27+1 -> 26 | B28: 24711074000102 | C28: BARDO REPRESENTACAO E TRANSPORTES EIRELI | D28: 38 | E28: CAIXA | F28: SERVIÇO | G28: LUCRO PRESUMIDO | H28: SEM FOLHA | I28: =APOIO!L28 -> EM DIA | J28: INGRID | K28: 46023 | L28: 45931 | M28: 45962 | Q28: 46082
A29: =A28+1 -> 27 | B29: 58952972000166 | C29: BARUK COMERCIO E DISTRIBUIÇÃO DE ALIMENTOS LTDA | D29: 207 | E29: BANCO | F29: COMÉRCIO | G29: SIMPLES NACIONAL | H29: FOLHA | I29: =APOIO!L29 -> EM ATRASO | J29: INGRID | K29: 45992 | L29: 45931 | P29: 46054
A30: =A29+1 -> 28 | B30: 50605321000198 | C30: BILLY BYTE SOLUÇÕES LTDA | D30: 76 | E30: NIBO | F30: SERVIÇO | G30: LUCRO PRESUMIDO | H30: SEM FOLHA | I30: =APOIO!L30 -> EM ATRASO | J30: KELVIN | K30: 45992 | L30: 45931 | N30: 45992 | O30: 46023
A31: =A30+1 -> 29 | B31: 48484094000148 | C31: BRASIL VERDE COMÉRCIO VAREJISTA E ATACADISTA DE PAMONHAS LTDA | D31: 188 | E31: BPO | F31: COMÉRCIO | G31: SIMPLES NACIONAL | H31: FOLHA | I31: =APOIO!L31 -> EM ATRASO | J31: KELVIN | K31: 45931 | M31: 45962 | N31: 45992
A32: =A31+1 -> 30 | B32: 5317981000119 | C32: BRASILIA TONER LTDA | D32: 87 | E32: CAIXA | F32: SERVIÇO | G32: SIMPLES NACIONAL | H32: FOLHA | I32: =APOIO!L32 -> EM ATRASO | J32: INGRID | K32: 45931 | M32: 45962
A33: =A32+1 -> 31 | B33: 55038535000143 | C33: BRM ENGENHARIA E TECNOLOGIA LTDA | D33: 160 | E33: CAIXA | F33: SERVIÇO | G33: SIMPLES NACIONAL | H33: SEM FOLHA | I33: =APOIO!L33 -> EM ATRASO | J33: KELVIN | K33: 45962 | M33: 45962 | N33: 45992 | O33: 46023
A34: =A33+1 -> 32 | B34: 38141002000173 | C34: BROTHES BURGER COMERCIO DE ALIMENTOS LTDA | D34: 529 | E34: CAIXA | F34: COMÉRCIO | G34: SIMPLES NACIONAL | H34: SEM FOLHA | I34: =APOIO!L34 -> EM ATRASO | J34: INGRID | K34: 45901 | M34: 45962
A35: =A34+1 -> 33 | B35: 47500142000181 | C35: BRUMIX TREINAMENTO, DESENVOLVIMENTO E SERVICOS LTDA | D35: 564 | E35: CAIXA | F35: SERVIÇO | G35: SIMPLES NACIONAL | H35: FOLHA | I35: =APOIO!L35 -> EM ATRASO | J35: KELVIN | K35: 45962 | M35: 45962 | N35: 45992 | O35: 46023
A36: =A35+1 -> 34 | B36: 22614874000333 | C36: CADEIRAS DESIGN LTDA (FILIAL) | D36: 211 | E36: BPO | F36: COMÉRCIO | G36: SIMPLES NACIONAL | H36: FOLHA | I36: =APOIO!L36 -> EM ATRASO | J36: KELVIN | K36: 45931 | M36: 45962 | N36: 45992
A37: =A36+1 -> 35 | B37: 22614874000171 | C37: CADEIRAS DESIGN LTDA (MATRIZ) | D37: 210 | E37: BPO | F37: COMÉRCIO | G37: SIMPLES NACIONAL | H37: FOLHA | I37: =APOIO!L37 -> EM ATRASO | J37: KELVIN | K37: 45931 | M37: 45962 | N37: 45992
A38: =A37+1 -> 36 | B38: 29682133000177 | C38: CADEIRAS DESIGN SHOPPING ID LTDA | D38: 215 | E38: BPO | F38: COMÉRCIO | G38: SIMPLES NACIONAL | H38: FOLHA | I38: =APOIO!L38 -> EM ATRASO | J38: KELVIN | K38: 45931 | M38: 45962 | N38: 45992
A39: =A38+1 -> 37 | B39: 28527486000130 | C39: CADEIRAS DESIGN.COM LTDA | D39: 214 | E39: BPO | F39: COMÉRCIO | G39: SIMPLES NACIONAL | H39: SEM FOLHA | I39: =APOIO!L39 -> EM ATRASO | J39: KELVIN | K39: 45931 | L39: 45931 | N39: 45992
A40: =A39+1 -> 38 | B40: 11111157000100 | C40: CASA DE FRUTAS A & E LTDA | D40: 241 | E40: CAIXA | F40: COMÉRCIO | G40: SIMPLES NACIONAL | H40: FOLHA | I40: =APOIO!L40 -> EM ATRASO | J40: INGRID | K40: 45901 | L40: 45931
A41: =A40+1 -> 39 | B41: 63653031000161 | C41: CASA QUADRADA PARTICIPACOES | D41: 255 | E41: ACOMPANHAR | F41: HOLDING | G41: LUCRO PRESUMIDO | H41: SEM FOLHA | I41: =APOIO!L41 -> EM ATRASO | J41: KELVIN | K41: 45962 | O41: 46023
A42: =A41+1 -> 40 | B42: 34698196000151 | C42: CENTRO DE MEDICINA DE FAMILIA DE BRASILIA LTDA | D42: 135 | E42: BANCO | F42: SERVIÇO | G42: LUCRO PRESUMIDO | H42: FOLHA | I42: =APOIO!L42 -> EM ATRASO | J42: INGRID | K42: 45992 | M42: 45962
A43: =A42+1 -> 41 | B43: 22855971000156 | C43: CENTRO DE NEFROLOGIA DO DISTRITO FEDERAL LTDA | D43: 104 | E43: NIBO | F43: SERVIÇO | G43: LUCRO PRESUMIDO | H43: SEM FOLHA | I43: =APOIO!L43 -> EM DIA | J43: INGRID | K43: 46023 | L43: 45931 | M43: 45962 | O43: 46023 | Q43: 46082
A44: =A43+1 -> 42 | B44: 33612605000192 | C44: CLIMA GESTAO DE PESSOAS LTDA | D44: 401 | E44: BANCO | F44: SERVIÇO | G44: SIMPLES NACIONAL | H44: PRO LABORE | I44: =APOIO!L44 -> EM DIA | J44: INGRID | K44: 46023 | M44: 45962 | Q44: 45717
A45: =A44+1 -> 43 | B45: 55824679000125 | C45: CLINICA BIOPELLE SERVIÇOS MÉDICOS LTDA | D45: 170 | E45: CAIXA | F45: SERVIÇO | G45: SIMPLES NACIONAL | H45: FATOR R | I45: =APOIO!L45 -> EM ATRASO | J45: INGRID | K45: 45931 | M45: 45962
A46: =A45+1 -> 44 | B46: 41631955000124 | C46: CLINICA ODONTOLOGICA ALMEIDA LTDA (OPTIMA) | D46: 67 | E46: BANCO | F46: SERVIÇO | G46: LUCRO PRESUMIDO | H46: SEM FOLHA | I46: =APOIO!L46 -> EM ATRASO | J46: KELVIN | K46: 45931 | M46: 45962 | N46: 45992
A47: =A46+1 -> 45 | B47: 39682852000141 | C47: COB OPTOMETRIA E SAUDE DOS OLHOS LTDA | D47: 27 | E47: CAIXA | F47: SERVIÇO | G47: SIMPLES NACIONAL | H47: SEM FOLHA | I47: =APOIO!L47 -> EM ATRASO | J47: INGRID | K47: 45931 | L47: 45931 | M47: 45962
A48: =A47+1 -> 46 | B48: 59212038000170 | C48: CONGLOMERADO MACEDO COMERCIO DE ALIMENTOS IV LTDA | D48: 229 | E48: CAIXA | F48: COMÉRCIO | G48: SIMPLES NACIONAL | H48: SEM FOLHA | I48: =APOIO!L48 -> EM ATRASO | J48: INGRID | K48: 45809
A49: =A48+1 -> 47 | B49: 38212384000189 | C49: CONSULTORIA A LTDA | D49: 396 | E49: CAIXA | F49: SERVIÇO/COMÉRCIO | G49: SIMPLES NACIONAL | H49: FATOR R | I49: =APOIO!L49 -> EM ATRASO | J49: INGRID | K49: 45901 | L49: 45931 | M49: 45962
A50: =A49+1 -> 48 | B50: 46905278000109 | C50: CRIS QUIRINO STUDIO ODONTOLOGICO LTDA | D50: 536 | E50: NIBO | F50: SERVIÇO | G50: SIMPLES NACIONAL | H50: FATOR R | I50: =APOIO!L50 -> EM ATRASO | J50: INGRID | K50: 45992 | M50: 45962
A51: =A50+1 -> 49 | B51: 34488093000167 | C51: CWJR REPRESENTACOES LTDA | D51: 216 | E51: ACOMPANHAR | F51: SERVIÇO | G51: SIMPLES NACIONAL | H51: FATOR R | I51: =APOIO!L51 -> EM ATRASO | J51: KELVIN | K51: 45931 | M51: 45962 | N51: 46023
A52: =A51+1 -> 50 | B52: 47667895000186 | C52: DF HAMBURGUERIA CASTELO LTDA | D52: 582 | E52: CAIXA | F52: COMÉRCIO | G52: SIMPLES NACIONAL | H52: SEM FOLHA | I52: =APOIO!L52 -> EM ATRASO | J52: KELVIN | K52: 45992 | M52: 45962 | N52: 45992
A53: =A52+1 -> 51 | B53: 29525176000149 | C53: DF HAMBURGUERIA LTDA | D53: 581 | E53: CAIXA | F53: COMÉRCIO | G53: SIMPLES NACIONAL | H53: FOLHA | I53: =APOIO!L53 -> EM ATRASO | J53: KELVIN | K53: 45931 | M53: 45962 | N53: 45992
A54: =A53+1 -> 52 | B54: 30666082000179 | C54: DJ RESTAURANTE E RECEPCOES LTDA | D54: 99 | E54: CAIXA | F54: SERVIÇO/COMÉRCIO | G54: LUCRO PRESUMIDO | H54: PRO LABORE | I54: =APOIO!L54 -> EM DIA | J54: INGRID | K54: 46023 | M54: 45962 | N54: 45992 | Q54: 46082
A55: =A54+1 -> 53 | B55: 40385101000142 | C55: DL ESPETINHOS COMERCIO DE ALIMENTOS LTDA | D55: 406 | E55: CAIXA | F55: COMÉRCIO | G55: SIMPLES NACIONAL | H55: FOLHA | I55: =APOIO!L55 -> EM ATRASO | J55: INGRID | K55: 45901 | M55: 45962
A56: =A55+1 -> 54 | B56: 62686180000164 | C56: DOUGLAS & MARIO SOLUCOES EM ALUGUEL LTDA | D56: 245 | E56: ACOMPANHAR | F56: SERVIÇO | G56: LUCRO PRESUMIDO | H56: SEM FOLHA | I56: =APOIO!L56 -> EM ATRASO | J56: KELVIN | K56: 45931 | L56: 45931 | N56: 46023
A57: =A56+1 -> 55 | B57: 43192522000145 | C57: DOUGLAS MATOS SOCIEDADE INDIVIDUAL DE ADVOCACIA | D57: 525 | E57: CAIXA | F57: SERVIÇO | G57: SIMPLES NACIONAL | H57: SEM FOLHA | I57: =APOIO!L57 -> EM ATRASO | J57: KELVIN | K57: 45931 | M57: 45962 | N57: 45992
A58: =A57+1 -> 56 | B58: 63652658000106 | C58: DUODECIMA PARTICIPACOES LTDA | D58: 256 | E58: ACOMPANHAR | F58: HOLDING | G58: LUCRO PRESUMIDO | H58: SEM FOLHA | I58: =APOIO!L58 -> EM ATRASO | J58: INGRID | K58: 45962
A59: =A58+1 -> 57 | B59: 32474729000196 | C59: EAPL AGUAS CLARAS COMERCIO DE APARELHOS (AUDIOFISA COMERCIO) | D59: 115 | E59: CAIXA | F59: SERVIÇO/COMÉRCIO | G59: SIMPLES NACIONAL | H59: FOLHA | I59: =APOIO!L59 -> EM ATRASO | J59: KELVIN | K59: 45931 | O59: 46023
A60: =A59+1 -> 58 | B60: 19662855000106 | C60: EAPL COMERCIO DE APARELHOS AUDITIVOS (CENTRO AUDITIVO AUDIOFISA) | D60: 54 | E60: BPO | F60: SERVIÇO/COMÉRCIO | G60: LUCRO PRESUMIDO | H60: SEM FOLHA | I60: =APOIO!L60 -> EM ATRASO | J60: KELVIN | K60: 45627
A61: =A60+1 -> 59 | B61: 19662855000459 | C61: EAPL COMERCIO DE APARELHOS AUDITIVOS LTDA (GAMA) (AUDIOFISA) | D61: 236 | E61: CAIXA | F61: SERVIÇO/COMÉRCIO | G61: LUCRO PRESUMIDO | H61: SEM FOLHA | I61: =APOIO!L61 -> EM DIA | J61: INGRID | K61: 46023 | Q61: 46082
A62: =A61+1 -> 60 | B62: 19662855000530 | C62: EAPL COMERCIO DE APARELHOS AUDITIVOS LTDA(ASA NORTE)(AUDIOFISA) | D62: 235 | E62: CAIXA | F62: SERVIÇO/COMÉRCIO | G62: LUCRO PRESUMIDO | H62: SEM FOLHA | I62: =APOIO!L62 -> EM ATRASO | J62: KELVIN | K62: 45627
A63: =A62+1 -> 61 | B63: 62760002000136 | C63: EDUARDO CARDOSO SERVICOS MEDICOS LTD | D63: 249 | E63: NIBO | F63: SERVIÇO | G63: SIMPLES NACIONAL | H63: FATOR R | I63: =APOIO!L63 -> EM ATRASO | J63: KELVIN | K63: 45992 | L63: 45931 | N63: 45992 | Q63: 46082
A64: =A63+1 -> 62 | B64: 63.542.784/0001-08 | C64: ELPORTO PIZZA 206 SUL LTDA | D64: 279 | E64: ACOMPANHAR | F64: COMÉRCIO | G64: SIMPLES NACIONAL | H64: FOLHA | I64: =APOIO!L64 -> EM DIA | J64: KELVIN | K64: 46082 | Q64: 46082
A65: =A64+1 -> 63 | B65: 13345041000161 | C65: EME - COMERCIO DE MOVEIS LTDA | D65: 209 | E65: BPO | F65: COMÉRCIO | G65: SIMPLES NACIONAL | H65: FOLHA | I65: =APOIO!L65 -> EM ATRASO | J65: KELVIN | K65: 45931 | L65: 45931 | M65: 45962 | N65: 45992
A66: =A65+1 -> 64 | B66: 13345041000242 | C66: EME - COMERCIO DE MOVEIS LTDA (FILIAL) | D66: 212 | E66: BPO | F66: COMÉRCIO | G66: SIMPLES NACIONAL | H66: SEM FOLHA | I66: =APOIO!L66 -> EM ATRASO | J66: KELVIN | K66: 45931 | L66: 45931 | M66: 45962 | N66: 45992
A67: =A66+1 -> 65 | B67: 36599674000100 | C67: EMPORIO DIVA COMERCIO DE PRODUTOS DE BELEZA EIRELI | D67: 11 | E67: CAIXA | F67: COMÉRCIO | G67: LUCRO PRESUMIDO | H67: FOLHA | I67: =APOIO!L67 -> EM DIA | J67: INGRID | K67: 46023 | Q67: 46082
A68: =A67+1 -> 66 | B68: 48439778000128 | C68: ESCOLA E CRECHE GERAÇÃO APRENDER LTDA | D68: 35 | E68: CAIXA | F68: SERVIÇO | G68: SIMPLES NACIONAL | H68: FOLHA | I68: =APOIO!L68 -> EM ATRASO | J68: INGRID | K68: 45931 | M68: 45962
A69: =A68+1 -> 67 | B69: 63274325000182 | C69: ESFERA CORRETORA DE SEGUROS LTDA | D69: 250 | E69: ACOMPANHAR | F69: SERVIÇO | G69: LUCRO PRESUMIDO | H69: SEM FOLHA | I69: =APOIO!L69 -> EM ATRASO | J69: INGRID | K69: 45950
A70: =A69+1 -> 68 | B70: 61963820000173 | C70: F. B. FREITAS DE SOUZA LTDA | D70: 239 | E70: ACOMPANHAR | F70: SERVIÇO | G70: SIMPLES NACIONAL | H70: SEM FOLHA | I70: =APOIO!L70 -> EM ATRASO | J70: INGRID | K70: 45839
A71: =A70+1 -> 69 | B71: 35725797000179 | C71: F.B. SANTOS GESTAO E ADMINISTRAÇÃO IMOBILIARIA | D71: 22 | E71: CAIXA | F71: SERVIÇO | G71: LUCRO PRESUMIDO | H71: SEM FOLHA | I71: =APOIO!L71 -> EM DIA | J71: INGRID | K71: 46023 | M71: 45962 | Q71: 46082
A72: =A71+1 -> 70 | B72: 18252709000140 | C72: FARIA COMERCIO DE BEBIDAS,CONVENIENCIA,EVENTOS E LOCACOES LTDA | D72: 25 | E72: CAIXA | F72: COMÉRCIO | G72: SIMPLES NACIONAL | H72: FOLHA | I72: =APOIO!L72 -> EM ATRASO | J72: KELVIN | K72: 45931 | M72: 45962 | N72: 45992
A73: =A72+1 -> 71 | B73: 36768275000117 | C73: FARIA DUE COMERCIO DE BEBIDAS E ALIMENTOS LTDA | D73: 21 | E73: CAIXA | F73: COMÉRCIO | G73: SIMPLES NACIONAL | H73: FOLHA | I73: =APOIO!L73 -> EM ATRASO | J73: KELVIN | K73: 45931 | M73: 45962 | N73: 45992
A74: =A73+1 -> 72 | B74: 53808182000198 | C74: FENESTRA INDUSTRIA, COMERCIO, FABRICACAO E INSTALACAO DE METAISE VIDROS LTDA | D74: 133 | E74: BANCO | F74: SERVIÇO/COMÉRCIO | G74: SIMPLES NACIONAL | H74: FOLHA | I74: =APOIO!L74 -> EM ATRASO | J74: KELVIN | K74: 45931 | M74: 45962 | N74: 45992
A75: =A74+1 -> 73 | B75: 56932805000128 | C75: FEO TECNOLOGIA LTDA | D75: 185 | E75: NIBO | F75: SERVIÇO | G75: LUCRO PRESUMIDO | H75: SEM FOLHA | I75: =APOIO!L75 -> EM ATRASO | J75: KELVIN | K75: 45932 | L75: 45931 | N75: 46023 | O75: 46023 | Q75: 46082
A76: =A75+1 -> 74 | B76: 28460728000115 | C76: FERNANDO NAVES SOCIEDADE INDIVIDUAL DE ADVOCACIA | D76: 343 | E76: CAIXA | F76: SERVIÇO | G76: SIMPLES NACIONAL | H76: SEM FOLHA | I76: =APOIO!L76 -> EM ATRASO | J76: KELVIN | K76: 45931 | M76: 45962 | N76: 45992
A77: =A76+1 -> 75 | B77: 65258029000113 | C77: FILO BEAUTY STUDIO | D77: 273 | E77: ACOMPANHAR | F77: SERVIÇO | G77: SIMPLES NACIONAL | H77: SEM FOLHA | I77: =APOIO!L77 -> EM DIA | J77: KELVIN | K77: 46054
A78: =A77+1 -> 76 | B78: 49779103000190 | C78: FINANCIAL CONSULTORES ASSOCIADOS LTDA | D78: 24 | E78: CAIXA | F78: SERVIÇO | G78: SIMPLES NACIONAL | H78: SEM FOLHA | I78: =APOIO!L78 -> EM ATRASO | J78: INGRID | K78: 45931 | M78: 45962
A79: =A78+1 -> 77 | B79: 20282860000172 | C79: FORNO MASTER INDUSTRIA E COMERCIO DE BISCOITOS LTDA | D79: 23 | E79: CAIXA | F79: COMÉRCIO | G79: SIMPLES NACIONAL | H79: SEM FOLHA | I79: =APOIO!L79 -> EM ATRASO | J79: INGRID | K79: 45627
A80: =A79+1 -> 78 | B80: 22109712000186 | C80: FORTALEZA COMERCIO E DISTRIBUICAO DE ALIMENTOS LTDA | D80: 30 | E80: BANCO | F80: COMÉRCIO | G80: LUCRO PRESUMIDO | H80: SEM FOLHA | I80: =APOIO!L80 -> EM ATRASO | J80: KELVIN | K80: 45627
A81: =A80+1 -> 79 | B81: 28234202000117 | C81: FRIO TECNICO'S - PRESTACAO DE SERVICOS DE INSTALACAO DE AR CONDICIONADO LTDA | D81: 102 | E81: CAIXA | F81: SERVIÇO | G81: SIMPLES NACIONAL | H81: FOLHA | I81: =APOIO!L81 -> EM ATRASO | J81: KELVIN | K81: 45992 | L81: 45931 | M81: 45962 | N81: 45992
A82: =A81+1 -> 80 | B82: 34974447000183 | C82: GARCIA KPP COMERCIO DE ALIMENTOS EIRELI (DONA MARICOTA) | D82: 336 | E82: CAIXA | F82: COMÉRCIO | G82: LUCRO PRESUMIDO | H82: FOLHA | I82: =APOIO!L82 -> EM ATRASO | J82: INGRID | K82: 45627
A83: =A82+1 -> 81 | B83: 28071236000138 | C83: GC SILVA COMERCIO DE BEBIDAS 191DF EIRELI - MATRIZ | D83: 75 | E83: CAIXA | F83: COMÉRCIO | G83: LUCRO REAL | H83: SEM FOLHA | I83: =APOIO!L83 -> EM ATRASO | J83: INGRID | K83: 45627
A84: =A83+1 -> 82 | B84: 28071236000219 | C84: GC SILVA COMERCIO DE BEBIDAS 191DF EIRELI - GO | D84: 149 | E84: CAIXA | F84: COMÉRCIO | G84: LUCRO REAL | H84: SEM FOLHA | I84: =APOIO!L84 -> EM ATRASO | J84: INGRID | K84: 45627
A85: =A84+1 -> 83 | B85: 63315107000149 | C85: GEOINFRA ENGENHARIA LTDA | D85: 251 | E85: ACOMPANHAR | F85: SERVIÇOS | G85: SIMPLES NACIONAL | H85: SEM FOLHA | I85: =APOIO!L85 -> EM ATRASO | J85: INGRID | K85: 45952
A86: =A85+1 -> 84 | B86: 52584427000188 | C86: GEOLINK TRANSFORMACAO DIGITAL LTDA | D86: 253 | E86: ACOMPANHAR | F86: SERVIÇO | G86: SIMPLES NACIONAL | H86: SEM FOLHA | I86: =APOIO!L86 -> EM ATRASO | J86: INGRID | K86: 45962 | M86: 45962
A87: =A86+1 -> 85 | B87: 17063002000122 | C87: GESTAO CONTADORES LTDA | D87: 1 | E87: CAIXA | F87: SERVIÇO | G87: SIMPLES NACIONAL | H87: FOLHA | I87: =APOIO!L87 -> EM ATRASO | J87: KELVIN | K87: 45627
A88: =A87+1 -> 86 | B88: 64.464.630/0001-08 | C88: GESTAO ONLINE OUTSOURCING LTDA | D88: 260 | E88: CAIXA | F88: SERVIÇOS | G88: SIMPLES NACIONAL | H88: FOLHA | I88: =APOIO!L88 -> EM DIA | J88: INGRID | K88: 46023 | O88: 46023
A89: =A88+1 -> 87 | B89: 27072709000159 | C89: GK MEDICINE SERVICOS MEDICOS LTDA | D89: 513 | E89: CAIXA | F89: SERVIÇO | G89: SIMPLES NACIONAL | H89: PRO LABORE | I89: =APOIO!L89 -> EM ATRASO | J89: INGRID | K89: 45931 | M89: 45962 | N89: 45992
A90: =A89+1 -> 88 | B90: 53726610000133 | C90: GM BRASIL COMERCIO DE PRODUTOS OPTICOS LTDA | D90: 129 | E90: CAIXA | F90: COMÉRCIO | G90: SIMPLES NACIONAL | H90: SEM FOLHA | I90: =APOIO!L90 -> EM ATRASO | J90: INGRID | K90: 45627
A91: =A90+1 -> 89 | B91: 57670435000160 | C91: GPR SOFTWARE LTDA | D91: 196 | E91: BANCO | F91: SERVIÇO | G91: LUCRO PRESUMIDO | H91: SEM FOLHA | I91: =APOIO!L91 -> EM DIA | J91: KELVIN | K91: 46023 | L91: 45931 | O91: 46023 | Q91: 46082
A92: =A91+1 -> 90 | B92: 61166521000108 | C92: GRUPO IMS COMERCIO DE ALIMENTOS I LTDA (TEXAS BURGER) | D92: 233 | E92: CAIXA | F92: COMÉRCIO | G92: SIMPLES NACIONAL | H92: SEM FOLHA | I92: =APOIO!L92 -> EM ATRASO | J92: KELVIN | K92: 45901
A93: =A92+1 -> 91 | B93: 61166503000126 | C93: GRUPO IMS COMERCIO DE ALIMENTOS II LTDA (TEXAS BURGER) | D93: 234 | E93: CAIXA | F93: COMÉRCIO | G93: SIMPLES NACIONAL | H93: SEM FOLHA | I93: =APOIO!L93 -> EM ATRASO | J93: INGRID | K93: 45809
A94: =A93+1 -> 92 | B94: 54447300000142 | C94: GRUPO MACEDO (TEXAS BURGER) | D94: 144 | E94: CAIXA | F94: COMÉRCIO | G94: SIMPLES NACIONAL | H94: SEM FOLHA | I94: =APOIO!L94 -> EM ATRASO | J94: KELVIN | K94: 45931 | M94: 45962 | N94: 45992
A95: =A94+1 -> 93 | B95: 54447287000121 | C95: GRUPO MACEDO II (BEST BEEF) | D95: 146 | E95: CAIXA | F95: COMÉRCIO | G95: SIMPLES NACIONAL | H95: SEM FOLHA | I95: =APOIO!L95 -> EM ATRASO | J95: KELVIN | K95: 45931 | M95: 45962 | N95: 45992 | O95: 46023
A96: =A95+1 -> 94 | B96: 54447285000132 | C96: GRUPO MACEDO III (BURGER MANIA) | D96: 147 | E96: CAIXA | F96: COMÉRCIO | G96: SIMPLES NACIONAL | H96: SEM FOLHA | I96: =APOIO!L96 -> EM ATRASO | J96: KELVIN | K96: 45931 | M96: 45962 | N96: 45992
A97: =A96+1 -> 95 | B97: 50900559000146 | C97: GS SCHILLING CONSULTORIA EM TECNOLOGIA LTDA | D97: 63 | E97: CAIXA | F97: SERVIÇO | G97: SIMPLES NACIONAL | H97: SEM FOLHA | I97: =APOIO!L97 -> EM ATRASO | J97: INGRID | K97: 45931 | M97: 45962 | N97: 45992
A98: =A97+1 -> 96 | B98: 64880825000120 | C98: IA TECH TECNOLOGIA DA INFORMACAO LTDA | D98: 269 | E98: ACOMPANHAR | F98: SERVIÇO | G98: SIMPLES NACIONAL | H98: SEM FOLHA | I98: =APOIO!L98 -> EM DIA | J98: INGRID | K98: 46054 | P98: 46054
A99: =A98+1 -> 97 | B99: 36631894000165 | C99: IGREJA MINISTÉRIO NOVA VIDA | D99: 152 | E99: CAIXA | F99: SERVIÇO | G99: LUCRO PRESUMIDO | H99: SEM FOLHA | I99: =APOIO!L99 -> EM DIA | J99: INGRID | K99: 46023 | M99: 45962 | N99: 45992 | Q99: 46082
A100: =A99+1 -> 98 | B100: 55038481000116 | C100: IMPACT ENGENHARIA E ENERGIA SOLAR LTDA | D100: 159 | E100: CAIXA | F100: SERVIÇO/COMÉRCIO | G100: SIMPLES NACIONAL | H100: SEM FOLHA | I100: =APOIO!L100 -> EM ATRASO | J100: INGRID | K100: 45931 | N100: 45992
A101: =A100+1 -> 99 | B101: 59084161000153 | C101: IMS COMÉRCIO DE ALIMENTOS III LTDA (CONGLOMERADO) | D101: 230 | E101: CAIXA | F101: COMÉRCIO | G101: SIMPLES NACIONAL | H101: SEM FOLHA | I101: =APOIO!L101 -> EM ATRASO | J101: INGRID | K101: 45930 | L101: 45931
...

Sheet APOIO
G1: =BASE!K1
B2: DATA DE HOJE: | C2: MÊS: | D2: ANO | G2: =BASE!K2 -> COMPETÊNCIA DE FECHAMENTO | H2: MÊS | I2: ANO | J2: AVALIAÇÃO ANO | K2: AVALIAÇÃO MÊS | N2: VALIDAÇÃO
B3: =TODAY() -> 46099 | C3: 3 | D3: 2026 | E3: =IF(C3=1,11,(C3-2)) -> 1 | F3: =BASE!B3 -> 28523040000137 | G3: =BASE!K3 -> 46023 | H3: =MONTH(G3) -> 1 | I3: =YEAR(G3) -> 2026 | J3: =IF(I3<$D$3,"EM ATRASO","PENSAR") -> PENSAR | K3: =IF(H3<$E$3,"EM ATRASO","EM DIA") -> EM DIA | L3: =IF(J3="EM ATRASO","EM ATRASO",K3) -> EM DIA | N3: =F3=BASE!B3 -> TRUE
F4: =BASE!B4 -> 63849413000165 | G4: =BASE!K4 -> 45931 | H4: =MONTH(G4) -> 10 | I4: =YEAR(G4) -> 2025 | J4: =IF(I4<$D$3,"EM ATRASO","PENSAR") -> EM ATRASO | K4: =IF(H4<$E$3,"EM ATRASO","EM DIA") -> EM DIA | L4: =IF(J4="EM ATRASO","EM ATRASO",K4) -> EM ATRASO | N4: =F4=BASE!B4 -> TRUE
F5: =BASE!B5 -> 52613816000194 | G5: =BASE!K5 -> 46023 | H5: =MONTH(G5) -> 1 | I5: =YEAR(G5) -> 2026 | J5: =IF(I5<$D$3,"EM ATRASO","PENSAR") -> PENSAR | K5: =IF(H5<$E$3,"EM ATRASO","EM DIA") -> EM DIA | L5: =IF(J5="EM ATRASO","EM ATRASO",K5) -> EM DIA | N5: =F5=BASE!B5 -> TRUE
F6: =BASE!B6 -> 53114412000119 | G6: =BASE!K6 -> 45931 | H6: =MONTH(G6) -> 10 | I6: =YEAR(G6) -> 2025 | J6: =IF(I6<$D$3,"EM ATRASO","PENSAR") -> EM ATRASO | K6: =IF(H6<$E$3,"EM ATRASO","EM DIA") -> EM DIA | L6: =IF(J6="EM ATRASO","EM ATRASO",K6) -> EM ATRASO | N6: =F6=BASE!B6 -> TRUE
F7: =BASE!B7 -> 65173227000184 | G7: =BASE!K7 -> 46054 | H7: =MONTH(G7) -> 2 | I7: =YEAR(G7) -> 2026 | J7: =IF(I7<$D$3,"EM ATRASO","PENSAR") -> PENSAR | K7: =IF(H7<$E$3,"EM ATRASO","EM DIA") -> EM DIA | L7: =IF(J7="EM ATRASO","EM ATRASO",K7) -> EM DIA | N7: =F7=BASE!B7 -> TRUE
F8: =BASE!B8 -> 57407089000122 | G8: =BASE!K8 -> 45931 | H8: =MONTH(G8) -> 10 | I8: =YEAR(G8) -> 2025 | J8: =IF(I8<$D$3,"EM ATRASO","PENSAR") -> EM ATRASO | K8: =IF(H8<$E$3,"EM ATRASO","EM DIA") -> EM DIA | L8: =IF(J8="EM ATRASO","EM ATRASO",K8) -> EM ATRASO | N8: =F8=BASE!B8 -> TRUE
F9: =BASE!B9 -> 9404697000130 | G9: =BASE!K9 -> 45931 | H9: =MONTH(G9) -> 10 | I9: =YEAR(G9) -> 2025 | J9: =IF(I9<$D$3,"EM ATRASO","PENSAR") -> EM ATRASO | K9: =IF(H9<$E$3,"EM ATRASO","EM DIA") -> EM DIA | L9: =IF(J9="EM ATRASO","EM ATRASO",K9) -> EM ATRASO | N9: =F9=BASE!B9 -> TRUE
F10: =BASE!B10 -> 43798918000130 | G10: =BASE!K10 -> 45931 | H10: =MONTH(G10) -> 10 | I10: =YEAR(G10) -> 2025 | J10: =IF(I10<$D$3,"EM ATRASO","PENSAR") -> EM ATRASO | K10: =IF(H10<$E$3,"EM ATRASO","EM DIA") -> EM DIA | L10: =IF(J10="EM ATRASO","EM ATRASO",K10) -> EM ATRASO | N10: =F10=BASE!B10 -> TRUE
F11: =BASE!B11 -> 54711482000117 | G11: =BASE!K11 -> 45931 | H11: =MONTH(G11) -> 10 | I11: =YEAR(G11) -> 2025 | J11: =IF(I11<$D$3,"EM ATRASO","PENSAR") -> EM ATRASO | K11: =IF(H11<$E$3,"EM ATRASO","EM DIA") -> EM DIA | L11: =IF(J11="EM ATRASO","EM ATRASO",K11) -> EM ATRASO | N11: =F11=BASE!B11 -> TRUE
F12: =BASE!B12 -> 42730764000182 | G12: =BASE!K12 -> 45931 | H12: =MONTH(G12) -> 10 | I12: =YEAR(G12) -> 2025 | J12: =IF(I12<$D$3,"EM ATRASO","PENSAR") -> EM ATRASO | K12: =IF(H12<$E$3,"EM ATRASO","EM DIA") -> EM DIA | L12: =IF(J12="EM ATRASO","EM ATRASO",K12) -> EM ATRASO | N12: =F12=BASE!B12 -> TRUE
F13: =BASE!B13 -> 64899759000130 | G13: =BASE!K13 -> 46054 | H13: =MONTH(G13) -> 2 | I13: =YEAR(G13) -> 2026 | J13: =IF(I13<$D$3,"EM ATRASO","PENSAR") -> PENSAR | K13: =IF(H13<$E$3,"EM ATRASO","EM DIA") -> EM DIA | L13: =IF(J13="EM ATRASO","EM ATRASO",K13) -> EM DIA | N13: =F13=BASE!B13 -> TRUE
F14: =BASE!B14 -> 24924847000120 | G14: =BASE!K14 -> 46023 | H14: =MONTH(G14) -> 1 | I14: =YEAR(G14) -> 2026 | J14: =IF(I14<$D$3,"EM ATRASO","PENSAR") -> PENSAR | K14: =IF(H14<$E$3,"EM ATRASO","EM DIA") -> EM DIA | L14: =IF(J14="EM ATRASO","EM ATRASO",K14) -> EM DIA | N14: =F14=BASE!B14 -> TRUE
F15: =BASE!B15 -> 35965694000186 | G15: =BASE!K15 -> 45778 | H15: =MONTH(G15) -> 5 | I15: =YEAR(G15) -> 2025 | J15: =IF(I15<$D$3,"EM ATRASO","PENSAR") -> EM ATRASO | K15: =IF(H15<$E$3,"EM ATRASO","EM DIA") -> EM DIA | L15: =IF(J15="EM ATRASO","EM ATRASO",K15) -> EM ATRASO | N15: =F15=BASE!B15 -> TRUE
... F63: =BASE!B63 -> 62760002000136 | G63: =BASE!K63 -> 45992 | H63: =MONTH(G63) -> 12 | I63: =YEAR(G63) -> 2025 | J63: =IF(I63<$D$3,"EM ATRASO","PENSAR") -> EM ATRASO | K63: =IF(H63<$E$3,"EM ATRASO","EM DIA") -> EM DIA | L63: =IF(J63="EM ATRASO","EM ATRASO",K63) -> EM ATRASO | N63: =F63=BASE!B63 -> TRUE
F64: 63.542.784/0001-08 | G64: =BASE!K64 -> 46082 | H64: =MONTH(G64) -> 3 | I64: =YEAR(G64) -> 2026 | J64: =IF(I64<$D$3,"EM ATRASO","PENSAR") -> PENSAR | K64: =IF(H64<$E$3,"EM ATRASO","EM DIA") -> EM DIA | L64: =IF(J64="EM ATRASO","EM ATRASO",K64) -> EM DIA | N64: =F64=BASE!B64 -> TRUE
F65: =BASE!B65 -> 13345041000161 | G65: =BASE!K65 -> 45931 | H65: =MONTH(G65) -> 10 | I65: =YEAR(G65) -> 2025 | J65: =IF(I65<$D$3,"EM ATRASO","PENSAR") -> EM ATRASO | K65: =IF(H65<$E$3,"EM ATRASO","EM DIA") -> EM DIA | L65: =IF(J65="EM ATRASO","EM ATRASO",K65) -> EM ATRASO | N65: =F65=BASE!B65 -> TRUE
F66: =BASE!B66 -> 13345041000242 | G66: =BASE!K66 -> 45931 | H66: =MONTH(G66) -> 10 | I66: =YEAR(G66) -> 2025 | J66: =IF(I66<$D$3,"EM ATRASO","PENSAR") -> EM ATRASO | K66: =IF(H66<$E$3,"EM ATRASO","EM DIA") -> EM DIA | L66: =IF(J66="EM ATRASO","EM ATRASO",K66) -> EM ATRASO | N66: =F66=BASE!B66 -> TRUE
F67: =BASE!B67 -> 36599674000100 | G67: =BASE!K67 -> 46023 | H67: =MONTH(G67) -> 1 | I67: =YEAR(G67) -> 2026 | J67: =IF(I67<$D$3,"EM ATRASO","PENSAR") -> PENSAR | K67: =IF(H67<$E$3,"EM ATRASO","EM DIA") -> EM DIA | L67: =IF(J67="EM ATRASO","EM ATRASO",K67) -> EM DIA | N67: =F67=BASE!B67 -> TRUE
F68: =BASE!B68 -> 48439778000128 | G68: =BASE!K68 -> 45931 | H68: =MONTH(G68) -> 10 | I68: =YEAR(G68) -> 2025 | J68: =IF(I68<$D$3,"EM ATRASO","PENSAR") -> EM ATRASO | K68: =IF(H68<$E$3,"EM ATRASO","EM DIA") -> EM DIA | L68: =IF(J68="EM ATRASO","EM ATRASO",K68) -> EM ATRASO | N68: =F68=BASE!B68 -> TRUE
F69: =BASE!B69 -> 63274325000182 | G69: =BASE!K69 -> 45950 | H69: =MONTH(G69) -> 10 | I69: =YEAR(G69) -> 2025 | J69: =IF(I69<$D$3,"EM ATRASO","PENSAR") -> EM ATRASO | K69: =IF(H69<$E$3,"EM ATRASO","EM DIA") -> EM DIA | L69: =IF(J69="EM ATRASO","EM ATRASO",K69) -> EM ATRASO | N69: =F69=BASE!B69 -> TRUE
F70: =BASE!B70 -> 61963820000173 | G70: =BASE!K70 -> 45839 | H70: =MONTH(G70) -> 7 | I70: =YEAR(G70) -> 2025 | J70: =IF(I70<$D$3,"EM ATRASO","PENSAR") -> EM ATRASO | K70: =IF(H70<$E$3,"EM ATRASO","EM DIA") -> EM DIA | L70: =IF(J70="EM ATRASO","EM ATRASO",K70) -> EM ATRASO | N70: =F70=BASE!B70 -> TRUE
F71: =BASE!B71 -> 35725797000179 | G71: =BASE!K71 -> 46023 | H71: =MONTH(G71) -> 1 | I71: =YEAR(G71) -> 2026 | J71: =IF(I71<$D$3,"EM ATRASO","PENSAR") -> PENSAR | K71: =IF(H71<$E$3,"EM ATRASO","EM DIA") -> EM DIA | L71: =IF(J71="EM ATRASO","EM ATRASO",K71) -> EM DIA | N71: =F71=BASE!B71 -> TRUE
F72: =BASE!B72 -> 18252709000140 | G72: =BASE!K72 -> 45931 | H72: =MONTH(G72) -> 10 | I72: =YEAR(G72) -> 2025 | J72: =IF(I72<$D$3,"EM ATRASO","PENSAR") -> EM ATRASO | K72: =IF(H72<$E$3,"EM ATRASO","EM DIA") -> EM DIA | L72: =IF(J72="EM ATRASO","EM ATRASO",K72) -> EM ATRASO | N72: =F72=BASE!B72 -> TRUE
F73: =BASE!B73 -> 36768275000117 | G73: =BASE!K73 -> 45931 | H73: =MONTH(G73) -> 10 | I73: =YEAR(G73) -> 2025 | J73: =IF(I73<$D$3,"EM ATRASO","PENSAR") -> EM ATRASO | K73: =IF(H73<$E$3,"EM ATRASO","EM DIA") -> EM DIA | L73: =IF(J73="EM ATRASO","EM ATRASO",K73) -> EM ATRASO | N73: =F73=BASE!B73 -> TRUE
F74: =BASE!B74 -> 53808182000198 | G74: =BASE!K74 -> 45931 | H74: =MONTH(G74) -> 10 | I74: =YEAR(G74) -> 2025 | J74: =IF(I74<$D$3,"EM ATRASO","PENSAR") -> EM ATRASO | K74: =IF(H74<$E$3,"EM ATRASO","EM DIA") -> EM DIA | L74: =IF(J74="EM ATRASO","EM ATRASO",K74) -> EM ATRASO | N74: =F74=BASE!B74 -> TRUE
F75: =BASE!B75 -> 56932805000128 | G75: =BASE!K75 -> 45932 | H75: =MONTH(G75) -> 10 | I75: =YEAR(G75) -> 2025 | J75: =IF(I75<$D$3,"EM ATRASO","PENSAR") -> EM ATRASO | K75: =IF(H75<$E$3,"EM ATRASO","EM DIA") -> EM DIA | L75: =IF(J75="EM ATRASO","EM ATRASO",K75) -> EM ATRASO | N75: =F75=BASE!B75 -> TRUE
F76: =BASE!B76 -> 28460728000115 | G76: =BASE!K76 -> 45931 | H76: =MONTH(G76) -> 10 | I76: =YEAR(G76) -> 2025 | J76: =IF(I76<$D$3,"EM ATRASO","PENSAR") -> EM ATRASO | K76: =IF(H76<$E$3,"EM ATRASO","EM DIA") -> EM DIA | L76: =IF(J76="EM ATRASO","EM ATRASO",K76) -> EM ATRASO | N76: =F76=BASE!B76 -> TRUE
... F208: =BASE!B208 -> 59648913000161 | G208: =BASE!K208 -> 45689 | H208: =MONTH(G208) -> 2 | I208: =YEAR(G208) -> 2025 | J208: =IF(I208<$D$3,"EM ATRASO","PENSAR") -> EM ATRASO | K208: =IF(H208<$E$3,"EM ATRASO","EM DIA") -> EM DIA | L208: =IF(J208="EM ATRASO","EM ATRASO",K208) -> EM ATRASO | N208: =F208=BASE!B208 -> TRUE
F209: =BASE!B209 -> 40669598000120 | G209: =BASE!K209 -> 46023 | H209: =MONTH(G209) -> 1 | I209: 2024 | J209: =IF(I209<$D$3,"EM ATRASO","PENSAR") -> EM ATRASO | K209: =IF(H209<$E$3,"EM ATRASO","EM DIA") -> EM DIA | L209: =IF(J209="EM ATRASO","EM ATRASO",K209) -> EM ATRASO | N209: =F209=BASE!B209 -> TRUE
F210: =BASE!B210 -> 38293457000104 | G210: =BASE!K210 -> 45931 | H210: =MONTH(G210) -> 10 | I210: =YEAR(G210) -> 2025 | J210: =IF(I210<$D$3,"EM ATRASO","PENSAR") -> EM ATRASO | K210: =IF(H210<$E$3,"EM ATRASO","EM DIA") -> EM DIA | L210: =IF(J210="EM ATRASO","EM ATRASO",K210) -> EM ATRASO | N210: =F210=BASE!B210 -> TRUE
F211: =BASE!B211 -> 42359555000174 | G211: =BASE!K211 -> 45901 | H211: =MONTH(G211) -> 9 | I211: =YEAR(G211) -> 2025 | J211: =IF(I211<$D$3,"EM ATRASO","PENSAR") -> EM ATRASO | K211: =IF(H211<$E$3,"EM ATRASO","EM DIA") -> EM DIA | L211: =IF(J211="EM ATRASO","EM ATRASO",K211) -> EM ATRASO | N211: =F211=BASE!B211 -> TRUE
F212: =BASE!B212 -> 60080888000141 | G212: =BASE!K212 -> 45717 | H212: =MONTH(G212) -> 3 | I212: =YEAR(G212) -> 2025 | J212: =IF(I212<$D$3,"EM ATRASO","PENSAR") -> EM ATRASO | K212: =IF(H212<$E$3,"EM ATRASO","EM DIA") -> EM DIA | L212: =IF(J212="EM ATRASO","EM ATRASO",K212) -> EM ATRASO | N212: =F212=BASE!B212 -> TRUE
F213: =BASE!B213 -> 31262718000180 | G213: =BASE!K213 -> 45931 | H213: =MONTH(G213) -> 10 | I213: =YEAR(G213) -> 2025 | J213: =IF(I213<$D$3,"EM ATRASO","PENSAR") -> EM ATRASO | K213: =IF(H213<$E$3,"EM ATRASO","EM DIA") -> EM DIA | L213: =IF(J213="EM ATRASO","EM ATRASO",K213) -> EM ATRASO | N213: =F213=BASE!B213 -> TRUE
F214: =BASE!B214 -> 63535609000185 | G214: =BASE!K214 -> 45962 | H214: =MONTH(G214) -> 11 | I214: =YEAR(G214) -> 2025 | J214: =IF(I214<$D$3,"EM ATRASO","PENSAR") -> EM ATRASO | K214: =IF(H214<$E$3,"EM ATRASO","EM DIA") -> EM DIA | L214: =IF(J214="EM ATRASO","EM ATRASO",K214) -> EM ATRASO | N214: =F214=BASE!B214 -> TRUE
F215: =BASE!B215 -> 54739907000104 | G215: =BASE!K215 -> 45839 | H215: =MONTH(G215) -> 7 | I215: =YEAR(G215) -> 2025 | J215: =IF(I215<$D$3,"EM ATRASO","PENSAR") -> EM ATRASO | K215: =IF(H215<$E$3,"EM ATRASO","EM DIA") -> EM DIA | L215: =IF(J215="EM ATRASO","EM ATRASO",K215) -> EM ATRASO | N215: =F215=BASE!B215 -> TRUE
F216: =BASE!B216 -> 34460684000126 | G216: =BASE!K216 -> 46054 | H216: =MONTH(G216) -> 2 | I216: =YEAR(G216) -> 2026 | J216: =IF(I216<$D$3,"EM ATRASO","PENSAR") -> PENSAR | K216: =IF(H216<$E$3,"EM ATRASO","EM DIA") -> EM DIA | L216: =IF(J216="EM ATRASO","EM ATRASO",K216) -> EM DIA | N216: =F216=BASE!B216 -> TRUE
F217: =BASE!B217 -> 19695538000196 | G217: =BASE!K217 -> 45992 | H217: =MONTH(G217) -> 12 | I217: =YEAR(G217) -> 2025 | J217: =IF(I217<$D$3,"EM ATRASO","PENSAR") -> EM ATRASO | K217: =IF(H217<$E$3,"EM ATRASO","EM DIA") -> EM DIA | L217: =IF(J217="EM ATRASO","EM ATRASO",K217) -> EM ATRASO | N217: =F217=BASE!B217 -> TRUE
F218: =BASE!B218 -> 35085344000125 | G218: =BASE!K218 -> 45627 | H218: =MONTH(G218) -> 12 | I218: =YEAR(G218) -> 2024 | J218: =IF(I218<$D$3,"EM ATRASO","PENSAR") -> EM ATRASO | K218: =IF(H218<$E$3,"EM ATRASO","EM DIA") -> EM DIA | L218: =IF(J218="EM ATRASO","EM ATRASO",K218) -> EM ATRASO | N218: =F218=BASE!B218 -> TRUE
F219: =BASE!B219 -> 55514828000150 | G219: =BASE!K219 -> 45870 | H219: =MONTH(G219) -> 8 | I219: =YEAR(G219) -> 2025 | J219: =IF(I219<$D$3,"EM ATRASO","PENSAR") -> EM ATRASO | K219: =IF(H219<$E$3,"EM ATRASO","EM DIA") -> EM DIA | L219: =IF(J219="EM ATRASO","EM ATRASO",K219) -> EM ATRASO | N219: =F219=BASE!B219 -> TRUE
F220: =BASE!B220 -> 31676426000193 | G220: =BASE!K220 -> 45931 | H220: =MONTH(G220) -> 10 | I220: =YEAR(G220) -> 2025 | J220: =IF(I220<$D$3,"EM ATRASO","PENSAR") -> EM ATRASO | K220: =IF(H220<$E$3,"EM ATRASO","EM DIA") -> EM DIA | L220: =IF(J220="EM ATRASO","EM ATRASO",K220) -> EM ATRASO | N220: =F220=BASE!B220 -> TRUE
F221: =BASE!B221 -> 44293319000128 | G221: =BASE!K221 -> 45992 | H221: =MONTH(G221) -> 12 | I221: =YEAR(G221) -> 2025 | J221: =IF(I221<$D$3,"EM ATRASO","PENSAR") -> EM ATRASO | K221: =IF(H221<$E$3,"EM ATRASO","EM DIA") -> EM DIA | L221: =IF(J221="EM ATRASO","EM ATRASO",K221) -> EM ATRASO | N221: =F221=BASE!B221 -> TRUE
... F244: =BASE!B244 -> 58054899000105 | G244: =BASE!K244 -> 45627 | H244: =MONTH(G244) -> 12 | I244: =YEAR(G244) -> 2024 | J244: =IF(I244<$D$3,"EM ATRASO","PENSAR") -> EM ATRASO | K244: =IF(H244<$E$3,"EM ATRASO","EM DIA") -> EM DIA | L244: =IF(J244="EM ATRASO","EM ATRASO",K244) -> EM ATRASO | N244: =F244=BASE!B244 -> TRUE
F245: =BASE!B245 -> 40713550000172 | G245: =BASE!K244 -> 45627 | H245: =MONTH(G245) -> 12 | I245: =YEAR(G245) -> 2024 | J245: =IF(I245<$D$3,"EM ATRASO","PENSAR") -> EM ATRASO | K245: =IF(H245<$E$3,"EM ATRASO","EM DIA") -> EM DIA | L245: =IF(J245="EM ATRASO","EM ATRASO",K245) -> EM ATRASO | N245: =F245=BASE!B245 -> TRUE
F246: =BASE!B246 -> 36557204000175 | G246: =BASE!K245 -> 45656 | H246: =MONTH(G246) -> 12 | I246: =YEAR(G246) -> 2024 | J246: =IF(I246<$D$3,"EM ATRASO","PENSAR") -> EM ATRASO | K246: =IF(H246<$E$3,"EM ATRASO","EM DIA") -> EM DIA | L246: =IF(J246="EM ATRASO","EM ATRASO",K246) -> EM ATRASO | N246: =F246=BASE!B246 -> TRUE
F247: =BASE!B247 -> 62361378000178 | G247: =BASE!K246 -> 45656 | H247: =MONTH(G247) -> 12 | I247: =YEAR(G247) -> 2024 | J247: =IF(I247<$D$3,"EM ATRASO","PENSAR") -> EM ATRASO | K247: =IF(H247<$E$3,"EM ATRASO","EM DIA") -> EM DIA | L247: =IF(J247="EM ATRASO","EM ATRASO",K247) -> EM ATRASO | N247: =F247=BASE!B247 -> TRUE
F248: =BASE!B248 -> 28218047000145 | G248: =BASE!K248 -> 46054 | H248: =MONTH(G248) -> 2 | I248: =YEAR(G248) -> 2026 | J248: =IF(I248<$D$3,"EM ATRASO","PENSAR") -> PENSAR | K248: =IF(H248<$E$3,"EM ATRASO","EM DIA") -> EM DIA | L248: =IF(J248="EM ATRASO","EM ATRASO",K248) -> EM DIA | N248: =F248=BASE!B248 -> TRUE
F249: =BASE!B249 -> 38287080000180 | G249: =BASE!K249 -> 46023 | H249: =MONTH(G249) -> 1 | I249: =YEAR(G249) -> 2026 | J249: =IF(I249<$D$3,"EM ATRASO","PENSAR") -> PENSAR | K249: =IF(H249<$E$3,"EM ATRASO","EM DIA") -> EM DIA | L249: =IF(J249="EM ATRASO","EM ATRASO",K249) -> EM DIA | N249: =F249=BASE!B249 -> TRUE
F250: =BASE!B250 -> 41231672000195 | G250: =BASE!K250 -> 45992 | H250: =MONTH(G250) -> 12 | I250: =YEAR(G250) -> 2025 | J250: =IF(I250<$D$3,"EM ATRASO","PENSAR") -> EM ATRASO | K250: =IF(H250<$E$3,"EM ATRASO","EM DIA") -> EM DIA | L250: =IF(J250="EM ATRASO","EM ATRASO",K250) -> EM ATRASO | N250: =F250=BASE!B250 -> TRUE
F251: =BASE!B251 -> 65.499.168/0001-39 | G251: =BASE!K251 -> 46054 | H251: =MONTH(G251) -> 2 | I251: =YEAR(G251) -> 2026 | J251: =IF(I251<$D$3,"EM ATRASO","PENSAR") -> PENSAR | K251: =IF(H251<$E$3,"EM ATRASO","EM DIA") -> EM DIA | L251: =IF(J251="EM ATRASO","EM ATRASO",K251) -> EM DIA | N251: =F251=BASE!B251 -> TRUE
F252: =BASE!B252 -> 65.592.643/0001-17 | G252: =BASE!K252 -> 46082 | H252: =MONTH(G252) -> 3 | I252: =YEAR(G252) -> 2026 | J252: =IF(I252<$D$3,"EM ATRASO","PENSAR") -> PENSAR | K252: =IF(H252<$E$3,"EM ATRASO","EM DIA") -> EM DIA | L252: =IF(J252="EM ATRASO","EM ATRASO",K252) -> EM DIA | N252: =F252=BASE!B252 -> TRUE
H253: =MONTH(G253) -> 12 | I253: =YEAR(G253) -> 1899 | J253: =IF(I253<$D$3,"EM ATRASO","PENSAR") -> EM ATRASO | K253: =IF(H253<$E$3,"EM ATRASO","EM DIA") -> EM DIA | L253: =IF(J253="EM ATRASO","EM ATRASO",K253) -> EM ATRASO | N253: =F253=BASE!B253 -> TRUE
H254: =MONTH(G254) -> 12 | I254: =YEAR(G254) -> 1899 | J254: =IF(I254<$D$3,"EM ATRASO","PENSAR") -> EM ATRASO | K254: =IF(H254<$E$3,"EM ATRASO","EM DIA") -> EM DIA | L254: =IF(J254="EM ATRASO","EM ATRASO",K254) -> EM ATRASO | N254: =F254=BASE!B254 -> TRUE
H255: =MONTH(G255) -> 12 | I255: =YEAR(G255) -> 1899 | J255: =IF(I255<$D$3,"EM ATRASO","PENSAR") -> EM ATRASO | K255: =IF(H255<$E$3,"EM ATRASO","EM DIA") -> EM DIA | L255: =IF(J255="EM ATRASO","EM ATRASO",K255) -> EM ATRASO | N255: =F255=BASE!B255 -> TRUE
H256: =MONTH(G256) -> 12 | I256: =YEAR(G256) -> 1899 | J256: =IF(I256<$D$3,"EM ATRASO","PENSAR") -> EM ATRASO | K256: =IF(H256<$E$3,"EM ATRASO","EM DIA") -> EM DIA | L256: =IF(J256="EM ATRASO","EM ATRASO",K256) -> EM ATRASO | N256: =F256=BASE!B256 -> TRUE
H257: =MONTH(G257) -> 12 | I257: =YEAR(G257) -> 1899 | J257: =IF(I257<$D$3,"EM ATRASO","PENSAR") -> EM ATRASO | K257: =IF(H257<$E$3,"EM ATRASO","EM DIA") -> EM DIA | L257: =IF(J257="EM ATRASO","EM ATRASO",K257) -> EM ATRASO | N257: =F257=BASE!B244 -> FALSE
H258: =MONTH(G258) -> 12 | I258: =YEAR(G258) -> 1899 | J258: =IF(I258<$D$3,"EM ATRASO","PENSAR") -> EM ATRASO | K258: =IF(H258<$E$3,"EM ATRASO","EM DIA") -> EM DIA | L258: =IF(J258="EM ATRASO","EM ATRASO",K258) -> EM ATRASO | N258: =F258=BASE!B245 -> FALSE
H259: =MONTH(G259) -> 12 | I259: =YEAR(G259) -> 1899 | J259: =IF(I259<$D$3,"EM ATRASO","PENSAR") -> EM ATRASO | K259: =IF(H259<$E$3,"EM ATRASO","EM DIA") -> EM DIA | L259: =IF(J259="EM ATRASO","EM ATRASO",K259) -> EM ATRASO | N259: =F259=BASE!B246 -> FALSE
H260: =MONTH(G260) -> 12 | I260: =YEAR(G260) -> 1899 | J260: =IF(I260<$D$3,"EM ATRASO","PENSAR") -> EM ATRASO | K260: =IF(H260<$E$3,"EM ATRASO","EM DIA") -> EM DIA | N260: =F260=BASE!B247 -> FALSE
H261: =MONTH(G261) -> 12 | I261: =YEAR(G261) -> 1899 | N261: =F261=BASE!B248 -> FALSE
H262: =MONTH(G262) -> 12 | I262: =YEAR(G262) -> 1899 | N262: =F262=BASE!B249 -> FALSE
H263: =MONTH(G263) -> 12 | I263: =YEAR(G263) -> 1899 | N263: =F263=BASE!B250 -> FALSE
H264: =MONTH(G264) -> 12 | N264: =F264=BASE!B251 -> FALSE
F265: =BASE!B252 -> 65.592.643/0001-17 | G265: =BASE!K252 -> 46082 | H265: =MONTH(G265) -> 3 | N265: =F265=BASE!B252 -> TRUE
F266: =BASE!B253 | G266: =BASE!K253 | H266: =MONTH(G266) -> 12 | N266: =F266=BASE!B253 -> TRUE
F267: =BASE!B254 | G267: =BASE!K254 | H267: =MONTH(G267) -> 12 | N267: =F267=BASE!B254 -> TRUE
F268: =BASE!B255 | G268: =BASE!K255 | H268: =MONTH(G268) -> 12 | N268: =F268=BASE!B255 -> TRUE
F269: =BASE!B256 | G269: =BASE!K256 | H269: =MONTH(G269) -> 12 | N269: =F269=BASE!B256 -> TRUE
F270: =BASE!B257 | G270: =BASE!K257 | N270: =F270=BASE!B257 -> TRUE
F271: =BASE!B258 | G271: =BASE!K258 | N271: =F271=BASE!B258 -> TRUE
F272: =BASE!B259 | G272: =BASE!K259 | N272: =F272=BASE!B259 -> TRUE
F273: =BASE!B260 | G273: =BASE!K260 | N273: =F273=BASE!B260 -> TRUE
F274: =BASE!B261 | G274: =BASE!K261 | N274: =F274=BASE!B261 -> TRUE
F275: =BASE!B262 | G275: =BASE!K262 | N275: =F275=BASE!B262 -> TRUE
F276: =BASE!B263 | G276: =BASE!K263 | N276: =F276=BASE!B263 -> TRUE
F277: =BASE!B264 | G277: =BASE!K264 | N277: =F277=BASE!B264 -> TRUE
F278: =BASE!B265 | G278: =BASE!K265 | N278: =F278=BASE!B265 -> TRUE
F279: =BASE!B266 | G279: =BASE!K266 | N279: =F279=BASE!B266 -> TRUE
F280: =BASE!B267 | G280: =BASE!K267 | N280: =F280=BASE!B267 -> TRUE
F281: =BASE!B268 | G281: =BASE!K268 | N281: =F281=BASE!B268 -> TRUE
... F290: =BASE!B277 | G290: =BASE!K277 | N290: =F290=BASE!B277 -> TRUE
F291: =BASE!B278 | G291: =BASE!K278
F292: =BASE!B279 | G292: =BASE!K279
F293: =BASE!B280 | G293: =BASE!K280
F294: =BASE!B281 | G294: =BASE!K281
F295: =BASE!B282 | G295: =BASE!K282
F296: =BASE!B283 | G296: =BASE!K283
F297: =BASE!B284 | G297: =BASE!K284
F298: =BASE!B285 | G298: =BASE!K285
F299: =BASE!B286 | G299: =BASE!K286
F300: =BASE!B287 | G300: =BASE!K287
F301: =BASE!B288 | G301: =BASE!K288
F302: =BASE!B289 | G302: =BASE!K289
... F337: =BASE!B324 | G337: =BASE!K324
F338: =BASE!B325
F339: =BASE!B326
F340: =BASE!B327
F341: =BASE!B328
F342: =BASE!B329
...

Sheet ECD E ECF 2025
B2: CNPJ | C2: EMPRESAS | D2: CÓDIGO SISTEMA | E2: STATUS | F2: RESPONSÁVEL | G2: REGIME TRIBUTÁRIO | H2: ECD | I2: DATA ENVIO ECD | J2: ECF | K2: DATA ENVIO ECF
A3: 1 | B3: 28523040000137 | C3: 180X NEGOCIOS DIGITAIS LTDA | D3: 555 | E3: ATIVA | F3: INGRID | G3: LUCRO PRESUMIDO | H3: PENDENTE | J3: PENDENTE
A4: =A3+1 -> 2 | B4: 63849413000165 | C4: 2RV ADMINISTRACAO E CONSULTORIA LTDA | D4: 259 | E4: ATIVA | F4: KELVIN | G4: SIMPLES NACIONAL | H4: PENDENTE | J4: PENDENTE
A5: =A4+1 -> 3 | B5: 52613816000194 | C5: 3.5 ESPORTE E SAÚDE LTDA (TAGUATINGA) | D5: 183 | E5: ATIVA | F5: INGRID | G5: SIMPLES NACIONAL | H5: PENDENTE | J5: PENDENTE
A6: =A5+1 -> 4 | B6: 53114412000119 | C6: 3.6 ESPORTE E SAÚDE LTDA | D6: 130 | E6: ATIVA | F6: KELVIN | G6: LUCRO PRESUMIDO | H6: PENDENTE | J6: PENDENTE
A7: =A6+1 -> 5 | B7: 65173227000184 | C7: ACADEMIA CEILANDIA DUE LTDA | D7: 272 | E7: ATIVA | F7: KELVIN | G7: SIMPLES NACIONAL | H7: NÃO OBRIGADA | J7: NÃO OBRIGADA
A8: =A7+1 -> 6 | B8: 57407089000122 | C8: ACADEMIA CEILANDIA ESPORTE SAUDE LTDA | D8: 195 | E8: ATIVA | F8: KELVIN | G8: LUCRO PRESUMIDO | H8: PENDENTE | J8: PENDENTE
A9: =A8+1 -> 7 | B9: 9404697000130 | C9: ACADEMIA PERSONAL FITNESS LTDA (LIVE 3.3) | D9: 134 | E9: ATIVA | F9: KELVIN | G9: SIMPLES NACIONAL | H9: NÃO OBRIGADA | J9: NÃO OBRIGADA
A10: =A9+1 -> 8 | B10: 43798918000130 | C10: AG COMERCIO E MERCEARIA LTDA | D10: 408 | E10: ATIVA | F10: KELVIN | G10: LUCRO REAL | H10: NÃO OBRIGADA | J10: NÃO OBRIGADA
A11: =A10+1 -> 9 | B11: 54711482000117 | C11: AGENCIA 33 MARKETING E NEGOCIOS DIGITAIS LTDA | D11: 148 | E11: ATIVA | F11: KELVIN | G11: SIMPLES NACIONAL | H11: NÃO OBRIGADA | J11: NÃO OBRIGADA
A12: =A11+1 -> 10 | B12: 42730764000182 | C12: AGRO VIRA LATA COMÉRCIO DE ARTIGOS PARA ANIMAIS E SERVIÇOES LTDA | D12: 389 | E12: ATIVA | F12: INGRID | G12: SIMPLES NACIONAL | H12: NÃO OBRIGADA | J12: NÃO OBRIGADA
A13: =A12+1 -> 11 | B13: 64899759000130 | C13: AHAVA ENERGIA SOLAR | D13: 270 | E13: ATIVA | F13: KELVIN | G13: LUCRO PRESUMIDO | H13: NÃO OBRIGADA | J13: NÃO OBRIGADA
A14: =A13+1 -> 12 | B14: 24924847000120 | C14: ALDEMIR CANDIDO DE RESENDE ME | D14: 263 | E14: ATIVA | F14: INGRID | G14: SIMPLES NACIONAL | H14: NÃO OBRIGADA | J14: NÃO OBRIGADA
A15: =A14+1 -> 13 | B15: 35965694000186 | C15: ALLEGRO COMÉRCIO DE ROUPAS | D15: 232 | E15: INATIVA | F15: KELVIN | G15: SIMPLES NACIONAL | H15: NÃO OBRIGADA | J15: NÃO OBRIGADA
... A64: =A63+1 -> 62 | B64: 62760002000136 | C64: EDUARDO CARDOSO SERVICOS MEDICOS LTD | D64: 249 | E64: ATIVA | F64: KELVIN | G64: SIMPLES NACIONAL | H64: NÃO OBRIGADA | J64: NÃO OBRIGADA
A65: =A64+1 -> 63 | B65: 63.542.784/0001-08 | C65: ELPORTO PIZZA 206 SUL LTDA | D65: 279 | E65: ATIVA | F65: KELVIN | G65: SIMPLES NACIONAL | H65: PENDENTE | J65: PENDENTE
A66: =A65+1 -> 64 | B66: 13345041000161 | C66: EME - COMERCIO DE MOVEIS LTDA | D66: 209 | E66: ATIVA | F66: KELVIN | G66: SIMPLES NACIONAL | H66: NÃO OBRIGADA | J66: NÃO OBRIGADA
A67: =A66+1 -> 65 | B67: 13345041000242 | C67: EME - COMERCIO DE MOVEIS LTDA (FILIAL) | D67: 212 | E67: ATIVA | F67: KELVIN | G67: SIMPLES NACIONAL | H67: NÃO OBRIGADA | J67: NÃO OBRIGADA
A68: =A67+1 -> 66 | B68: 36599674000100 | C68: EMPORIO DIVA COMERCIO DE PRODUTOS DE BELEZA EIRELI | D68: 11 | E68: ATIVA | F68: INGRID | G68: LUCRO PRESUMIDO | H68: NÃO OBRIGADA | J68: NÃO OBRIGADA
A69: =A68+1 -> 67 | B69: 52073052000191 | C69: EMPORIO DIVA TAGUATINGA COMERCIO | D69: 86 | E69: INATIVA | F69: KELVIN | G69: LUCRO PRESUMIDO | H69: PENDENTE | J69: PENDENTE
A70: =A69+1 -> 68 | B70: 48439778000128 | C70: ESCOLA E CRECHE GERAÇÃO APRENDER LTDA | D70: 35 | E70: ATIVA | F70: INGRID | G70: SIMPLES NACIONAL | H70: PENDENTE | J70: PENDENTE
A71: =A70+1 -> 69 | B71: 63274325000182 | C71: ESFERA CORRETORA DE SEGUROS LTDA | D71: 250 | E71: ATIVA | F71: INGRID | G71: LUCRO PRESUMIDO | H71: NÃO OBRIGADA | J71: NÃO OBRIGADA
A72: =A71+1 -> 70 | B72: 61963820000173 | C72: F. B. FREITAS DE SOUZA LTDA | D72: 239 | E72: ATIVA | F72: INGRID | G72: SIMPLES NACIONAL | H72: NÃO OBRIGADA | J72: NÃO OBRIGADA
A73: =A72+1 -> 71 | B73: 35725797000179 | C73: F.B. SANTOS GESTAO E ADMINISTRAÇÃO IMOBILIARIA | D73: 22 | E73: ATIVA | F73: INGRID | G73: LUCRO PRESUMIDO | H73: NÃO OBRIGADA | J73: NÃO OBRIGADA
A74: =A73+1 -> 72 | B74: 55329921000194 | C74: FAST LOCACOES LTDA | D74: 162 | E74: INATIVA | F74: INGRID | G74: SIMPLES NACIONAL | H74: NÃO OBRIGADA | J74: NÃO OBRIGADA
A75: =A74+1 -> 73 | B75: 18252709000140 | C75: FARIA COMERCIO DE BEBIDAS,CONVENIENCIA,EVENTOS E LOCACOES LTDA | D75: 25 | E75: ATIVA | F75: KELVIN | G75: SIMPLES NACIONAL | H75: NÃO OBRIGADA | J75: NÃO OBRIGADA
A76: =A75+1 -> 74 | B76: 36768275000117 | C76: FARIA DUE COMERCIO DE BEBIDAS E ALIMENTOS LTDA | D76: 21 | E76: ATIVA | F76: KELVIN | G76: SIMPLES NACIONAL | H76: PENDENTE | J76: PENDENTE
A77: =A76+1 -> 75 | B77: 53808182000198 | C77: FENESTRA INDUSTRIA, COMERCIO, FABRICACAO E INSTALACAO DE METAISE VIDROS LTDA | D77: 133 | E77: ATIVA | F77: KELVIN | G77: SIMPLES NACIONAL | H77: NÃO OBRIGADA | J77: NÃO OBRIGADA
... A90: =A89+1 -> 88 | B90: 17063002000122 | C90: GESTAO CONTADORES LTDA | D90: 1 | E90: ATIVA | F90: KELVIN | G90: SIMPLES NACIONAL | H90: NÃO OBRIGADA | J90: NÃO OBRIGADA
A91: =A90+1 -> 89 | B91: 64.464.630/0001-08 | C91: GESTAO ONLINE OUTSOURCING LTDA | D91: 260 | E91: ATIVA | F91: INGRID | G91: SIMPLES NACIONAL | H91: NÃO OBRIGADA | J91: NÃO OBRIGADA
A92: =A91+1 -> 90 | B92: 27072709000159 | C92: GK MEDICINE SERVICOS MEDICOS LTDA | D92: 513 | E92: ATIVA | F92: INGRID | G92: SIMPLES NACIONAL | H92: NÃO OBRIGADA | J92: NÃO OBRIGADA
A93: =A92+1 -> 91 | B93: 53726610000133 | C93: GM BRASIL COMERCIO DE PRODUTOS OPTICOS LTDA | D93: 129 | E93: ATIVA | F93: INGRID | G93: SIMPLES NACIONAL | H93: PENDENTE | J93: PENDENTE
A94: =A93+1 -> 92 | B94: 57670435000160 | C94: GPR SOFTWARE LTDA | D94: 196 | E94: ATIVA | F94: KELVIN | G94: LUCRO PRESUMIDO | H94: NÃO OBRIGADA | J94: NÃO OBRIGADA
A95: =A94+1 -> 93 | B95: 61166521000108 | C95: GRUPO IMS COMERCIO DE ALIMENTOS I LTDA (TEXAS BURGER) | D95: 233 | E95: INATIVA | F95: KELVIN | G95: SIMPLES NACIONAL | H95: NÃO OBRIGADA | J95: NÃO OBRIGADA
A96: =A95+1 -> 94 | B96: 61166503000126 | C96: GRUPO IMS COMERCIO DE ALIMENTOS II LTDA (TEXAS BURGER) | D96: 234 | E96: INATIVA | F96: INGRID | G96: SIMPLES NACIONAL | H96: NÃO OBRIGADA | J96: NÃO OBRIGADA
A97: =A96+1 -> 95 | B97: 54447300000142 | C97: GRUPO MACEDO (TEXAS BURGER) | D97: 144 | E97: INATIVA | F97: KELVIN | G97: SIMPLES NACIONAL | H97: NÃO OBRIGADA | J97: NÃO OBRIGADA
A98: =A97+1 -> 96 | B98: 54447287000121 | C98: GRUPO MACEDO II (BEST BEEF) | D98: 146 | E98: INATIVA | F98: KELVIN | G98: SIMPLES NACIONAL | H98: NÃO OBRIGADA | J98: NÃO OBRIGADA
A99: =A98+1 -> 97 | B99: 54447285000132 | C99: GRUPO MACEDO III (BURGER MANIA) | D99: 147 | E99: INATIVA | F99: KELVIN | G99: SIMPLES NACIONAL | H99: NÃO OBRIGADA | J99: NÃO OBRIGADA
A100: =A99+1 -> 98 | B100: 50900559000146 | C100: GS SCHILLING CONSULTORIA EM TECNOLOGIA LTDA | D100: 63 | E100: ATIVA | F100: INGRID | G100: SIMPLES NACIONAL | H100: NÃO OBRIGADA | J100: NÃO OBRIGADA
A101: =A100+1 -> 99 | B101: 64880825000120 | C101: IA TECH TECNOLOGIA DA INFORMACAO LTDA | D101: 269 | E101: ATIVA | F101: INGRID | G101: SIMPLES NACIONAL | H101: NÃO OBRIGADA | J101: NÃO OBRIGADA
A102: =A101+1 -> 100 | B102: 36631894000165 | C102: IGREJA MINISTÉRIO NOVA VIDA | D102: 152 | E102: ATIVA | F102: INGRID | G102: LUCRO PRESUMIDO | H102: NÃO OBRIGADA | J102: NÃO OBRIGADA
A103: =A102+1 -> 101 | B103: 55038481000116 | C103: IMPACT ENGENHARIA E ENERGIA SOLAR LTDA | D103: 159 | E103: ATIVA | F103: INGRID | G103: SIMPLES NACIONAL | H103: PENDENTE | J103: PENDENTE
... A132: =A131+1 -> 130 | B132: 46231380000176 | C132: LIS REFEIÇÕES COMÉRCIO DE ALIMENTOS LTDA | D132: 523 | E132: ATIVA | F132: KELVIN | G132: LUCRO PRESUMIDO | H132: NÃO OBRIGADA | J132: NÃO OBRIGADA
A133: =A132+1 -> 131 | B133: 64.610.816/0001-10 | C133: LIS REFEICOES E ALOJAMENTOS II LTDA | D133: 264 | E133: ATIVA | F133: KELVIN | G133: SIMPLES NACIONAL | H133: NÃO OBRIGADA | J133: NÃO OBRIGADA
A134: =A133+1 -> 132 | B134: 53134576000108 | C134: LIVE 3.4 PERSONAL LTDA (CRUZEIRO) | D134: 139 | E134: ATIVA | F134: INGRID | G134: LUCRO PRESUMIDO | H134: NÃO OBRIGADA | J134: NÃO OBRIGADA
A135: =A134+1 -> 133 | B135: 22554179000161 | C135: LIVE PERSONAL LTDA | D135: 136 | E135: ATIVA | F135: INGRID | G135: SIMPLES NACIONAL | H135: NÃO OBRIGADA | J135: NÃO OBRIGADA
A136: =A135+1 -> 134 | B136: 33895694000121 | C136: LL NARRATIVAS VISUAIS LTDA | D136: 248 | E136: ATIVA | F136: KELVIN | G136: SIMPLES NACIONAL | H136: NÃO OBRIGADA | J136: NÃO OBRIGADA
A137: =A136+1 -> 135 | B137: 31687088000195 | C137: LLIK COMERCIO DE ACESSORIOS E COSMETICOS LTDA | D137: 317 | E137: ATIVA | F137: KELVIN | G137: SIMPLES NACIONAL | H137: NÃO OBRIGADA | J137: NÃO OBRIGADA
A138: =A137+1 -> 136 | B138: 54184472000170 | C138: LLIK SECOND COMERCIO DE ACESSORIOS E COSMETICOS LTDA | D138: 203 | E138: ATIVA | F138: KELVIN | G138: SIMPLES NACIONAL | H138: NÃO OBRIGADA | J138: NÃO OBRIGADA
A139: =A138+1 -> 137 | B139: 14433426000143 | C139: LOCAR ENGENHARIA LTDA ME | D139: 48 | E139: ATIVA | F139: KELVIN | G139: LUCRO PRESUMIDO | H139: PENDENTE | J139: PENDENTE
A140: =A139+1 -> 138 | B140: 47358326000159 | C140: LUCALTO LTDA | D140: 73 | E140: ATIVA | F140: INGRID | G140: LUCRO PRESUMIDO | H140: PENDENTE | J140: PENDENTE
A141: =A140+1 -> 139 | B141: 24187519000199 | C141: M.A COMERCIO E DISTRIBUICAO DE ALIMENTOS | D141: 44 | E141: ATIVA | F141: INGRID | G141: LUCRO REAL | H141: PENDENTE | J141: PENDENTE
A142: =A141+1 -> 140 | B142: 60218324000122 | C142: M.A DUE COMERCIO E DISTRIBUICAO DE ALIMENTOS LTDA | D142: 226 | E142: ATIVA | F142: INGRID | G142: LUCRO REAL | H142: NÃO OBRIGADA | J142: NÃO OBRIGADA
A143: =A142+1 -> 141 | B143: 54151384000172 | C143: M.B GESTAO IMOBILIARIA LTDA | D143: 143 | E143: ATIVA | F143: KELVIN | G143: SIMPLES NACIONAL | H143: NÃO OBRIGADA | J143: NÃO OBRIGADA
A144: =A143+1 -> 142 | B144: 26525434000107 | C144: M&M COMERCIO DE ALIMENTOS LTDA | D144: 426 | E144: ATIVA | F144: INGRID | G144: SIMPLES NACIONAL | H144: PENDENTE | J144: PENDENTE
A145: =A144+1 -> 143 | B145: 6374213000160 | C145: M2 OPTICAL DO BRASIL LTDA | D145: 119 | E145: ATIVA | F145: INGRID | G145: SIMPLES NACIONAL | H145: NÃO OBRIGADA | J145: NÃO OBRIGADA
... A150: =A149+1 -> 148 | B150: 22582238000105 | C150: MARCOS AURELIO ROCHA NUNES | D150: 34 | E150: ATIVA | F150: KELVIN | G150: SIMPLES NACIONAL | H150: PENDENTE | J150: PENDENTE
A151: =A150+1 -> 149 | B151: 022.143.733-90 | C151: MARJORE TELES VIANA POMPEU | D151: 108 | E151: ATIVA | F151: KELVIN | G151: AUTÔNOMO | H151: NÃO OBRIGADA | J151: NÃO OBRIGADA
A152: =A151+1 -> 150 | B152: 8647859000107 | C152: MARYCRIZ PRESENTES & UTILIDADES DO LAR | D152: 267 | E152: ATIVA | F152: KELVIN | G152: SIMPLES NACIONAL | H152: PENDENTE | J152: PENDENTE
A153: =A152+1 -> 151 | B153: 56425581000168 | C153: MEATZ AGUAS CLARAS COMERCIO DE ALIMENTO | D153: 181 | E153: ATIVA | F153: INGRID | G153: SIMPLES NACIONAL | H153: NÃO OBRIGADA | J153: NÃO OBRIGADA
A154: =A153+1 -> 152 | B154: 7462754000102 | C154: MEATZ ASA NORTE BURGER COMÉRCIO DE ALIMENTOS LTDA | D154: 92 | E154: ATIVA | F154: KELVIN | G154: LUCRO PRESUMIDO | H154: PENDENTE | J154: PENDENTE
A155: =A154+1 -> 153 | B155: 33013866000196 | C155: MEATZ BSBURGER COMERCIO DE ALIMENTOS LTDA | D155: 117 | E155: ATIVA | F155: KELVIN | G155: LUCRO PRESUMIDO | H155: NÃO OBRIGADA | J155: NÃO OBRIGADA
A156: =A155+1 -> 154 | B156: 32648600000157 | C156: MEATZ BURGER CASTELO COMÉRCIO DE ALIMENTOS LTDA | D156: 378 | E156: ATIVA | F156: KELVIN | G156: LUCRO PRESUMIDO | H156: NÃO OBRIGADA | J156: NÃO OBRIGADA
A157: =A156+1 -> 155 | B157: 30046927000123 | C157: MEATZ BURITIS BURGER COMERCIO DE ALIMENTOS LTDA | D157: 379 | E157: ATIVA | F157: KELVIN | G157: SIMPLES NACIONAL | H157: NÃO OBRIGADA | J157: NÃO OBRIGADA
A158: =A157+1 -> 156 | B158: 28120242000138 | C158: MEATZ BURITIS HAMBURGUERIA ANTIGA P E C COMERCIO | D158: 77 | E158: ATIVA | F158: KELVIN | G158: LUCRO PRESUMIDO | H158: PENDENTE | J158: PENDENTE
A159: =A158+1 -> 157 | B159: 55657116000190 | C159: MEATZ CASTELO DUE COMÉRCIO | D159: 166 | E159: ATIVA | F159: KELVIN | G159: SIMPLES NACIONAL | H159: PENDENTE | J159: PENDENTE
A160: =A159+1 -> 158 | B160: 47133237000104 | C160: MEATZ CASTELO HAMBURGUERIA ANTIGA ASA NORTE DUE | D160: 551 | E160: ATIVA | F160: KELVIN | G160: LUCRO PRESUMIDO | H160: NÃO OBRIGADA | J160: NÃO OBRIGADA
A161: =A160+1 -> 159 | B161: 28347784000229 | C161: MEATZ CENTRO SUL COMERCIO DE ALIMENTOS LTDA - FILIAL | D161: 386 | E161: ATIVA | F161: KELVIN | G161: SIMPLES NACIONAL | H161: PENDENTE | J161: PENDENTE
A162: =A161+1 -> 160 | B162: 28347784000148 | C162: MEATZ CENTRO SUL COMERCIO DE ALIMENTOS LTDA - MATRIZ | D162: 380 | E162: ATIVA | F162: KELVIN | G162: SIMPLES NACIONAL | H162: NÃO OBRIGADA | J162: NÃO OBRIGADA
A163: =A162+1 -> 161 | B163: 24773977000100 | C163: MEATZ CENTRO SUL HAMBURGUERIA (ANTIGA AGUAS CLARAS) Delivery | D163: 50 | E163: ATIVA | F163: INGRID | G163: LUCRO PRESUMIDO | H163: NÃO OBRIGADA | J163: NÃO OBRIGADA
... A249: =A248+1 -> 247 | B249: 55033522000181 | C249: VERSATIL EXPRESS TRANSPORTES E CARGAS LTDA | D249: 158 | E249: ATIVA | F249: KELVIN | G249: SIMPLES NACIONAL | H249: NÃO OBRIGADA | J249: NÃO OBRIGADA
A250: =A249+1 -> 248 | B250: 65.452.307/0001-79 | C250: VERTEX 360 LTDA | D250: 276 | E250: ATIVA | F250: INGRID | G250: SIMPLES NACIONAL | H250: NÃO OBRIGADA | J250: NÃO OBRIGADA
A251: =A250+1 -> 249 | B251: 58054899000105 | C251: VG COMÉRCIO DE ACESSÓRIOS E BOLSAS LTDA | D251: 198 | E251: ATIVA | F251: KELVIN | G251: SIMPLES NACIONAL | H251: NÃO OBRIGADA | J251: NÃO OBRIGADA
A252: =A251+1 -> 250 | B252: 40713550000172 | C252: VIDREX COMERCIO DE VIDROS TEMPERADOS LTDA | D252: 206 | E252: ATIVA | F252: INGRID | G252: LUCRO PRESUMIDO | H252: NÃO OBRIGADA | J252: NÃO OBRIGADA
A253: =A252+1 -> 251 | B253: 36557204000175 | C253: VITRINE COMERCIO DE ARTIGOS OTICOS LTDA | D253: 12 | E253: ATIVA | F253: INGRID | G253: SIMPLES NACIONAL | H253: NÃO OBRIGADA | J253: NÃO OBRIGADA
A254: =A253+1 -> 252 | B254: 62361378000178 | C254: VM R.3 SAUDE LTDA | D254: 244 | E254: ATIVA | F254: KELVIN | G254: LUCRO PRESUMIDO | H254: NÃO OBRIGADA | J254: NÃO OBRIGADA
A255: =A254+1 -> 253 | B255: 28218047000145 | C255: WAME4 SOCIEDADE DE PARTICIPACOES LTDA | D255: 243 | E255: ATIVA | F255: KELVIN | G255: LUCRO PRESUMIDO | H255: NÃO OBRIGADA | J255: NÃO OBRIGADA
A256: =A255+1 -> 254 | B256: 38287080000180 | C256: WSS NEGOCIOS DIGITAIS LTDA | D256: 200 | E256: ATIVA | F256: KELVIN | G256: LUCRO PRESUMIDO | H256: NÃO OBRIGADA | J256: NÃO OBRIGADA
A257: =A256+1 -> 255 | B257: 41231672000195 | C257: WWC TECNOLOGIA LTDA | D257: 89 | E257: ATIVA | F257: KELVIN | G257: SIMPLES NACIONAL | H257: NÃO OBRIGADA | J257: NÃO OBRIGADA
A258: =A257+1 -> 256 | B258: 9205914000163 | C258: ZMC SANDRI GESTÃO EMPRESARIAL | D258: 356 | E258: ATIVA | F258: INGRID | G258: SIMPLES NACIONAL | H258: ENVIADA | J258: ENVIADA
A259: =A258+1 -> 257 | B259: 35193521000197 | C259: O PASTEL GOURMET LTDA | D259: 124 | E259: INATIVA | F259: KELVIN | G259: SIMPLES NACIONAL | H259: NÃO OBRIGADA | J259: NÃO OBRIGADA
A260: =A259+1 -> 258 | B260: 60136461000118 | C260: SHOPPING DOS OCULOS NOVO GAMA LTDA | D260: 225 | E260: INATIVA | F260: KELVIN | G260: SIMPLES NACIONAL | H260: NÃO OBRIGADA | J260: NÃO OBRIGADA
A261: =A260+1 -> 259 | B261: 60320842000152 | C261: STUDIO VISION OTICA LTDA | D261: 227 | E261: INATIVA | F261: KELVIN | G261: SIMPLES NACIONAL | H261: NÃO OBRIGADA | J261: NÃO OBRIGADA
A262: =A261+1 -> 260 | B262: 59466760000131 | C262: DRA. JESSICA JACOMELLI SERVIÇOS EM PSIQUIATRIA E MEDICINA INTERVENCIONISTA LTDA | D262: 219 | E262: INATIVA | F262: INGRID | G262: SIMPLES NACIONAL | H262: NÃO OBRIGADA | J262: NÃO OBRIGADA
A263: =A262+1 -> 261 | B263: 45377159000124 | C263: PAMONHA BRASIL ATACADISTA E COMERCIO DE ALIMENTOS LTDA | D263: 194 | E263: INATIVA | F263: INGRID | G263: SIMPLES NACIONAL | H263: NÃO OBRIGADA | J263: NÃO OBRIGADA

Sheet REINF 2025
B2: CNPJ | C2: FECHAMENTO | D2: EMPRESA | E2: REGIME | F2: RESPONSÁVEL | G2: ESCRITURAÇÃO ATÉ | H2: 1° TRIMESTRE | I2: 2° TRIMESTRE | J2: 3° TRIMESTRE | K2: 4° TRIMESTRE
A3: 1 | B3: 28523040000137 | C3: CAIXA | D3: 180X NEGOCIOS DIGITAIS LTDA | E3: LUCRO PRESUMIDO | F3: INGRID | G3: 45900 | H3: NÃO | I3: NÃO | J3: NÃO | K3: NÃO
A4: =A3+1 -> 2 | B4: 52613816000194 | C4: BANCO | D4: 3.5 ESPORTE E SAÚDE LTDA (TAGUATINGA) | E4: LUCRO PRESUMIDO | F4: INGRID | G4: 45992 | H4: PREJUIZO | I4: PREJUIZO | J4: PREJUIZO | K4: PREJUIZO
A5: =A4+1 -> 3 | B5: 53114412000119 | C5: BPO | D5: 3.6 ESPORTE E SAÚDE LTDA | E5: LUCRO PRESUMIDO | F5: KELVIN | G5: 45901 | H5: NÃO | I5: NÃO | J5: NÃO | K5: NÃO
A6: =A5+1 -> 4 | B6: 57407089000122 | C6: CAIXA | D6: ACADEMIA CEILANDIA ESPORTE SAUDE LTDA | E6: LUCRO PRESUMIDO | F6: KELVIN | G6: 45901 | H6: NÃO | I6: NÃO | J6: NÃO | K6: NÃO
A7: =A6+1 -> 5 | B7: 9404697000130 | C7: CAIXA | D7: ACADEMIA PERSONAL FITNESS LTDA (LIVE 3.3) | E7: SIMPLES NACIONAL | F7: KELVIN | G7: 45901 | H7: NÃO | I7: NÃO | J7: NÃO | K7: NÃO
A8: =A7+1 -> 6 | B8: 43798918000130 | C8: BANCO | D8: AG COMERCIO E MERCEARIA LTDA | E8: LUCRO REAL | F8: KELVIN | G8: 45901 | H8: NÃO | I8: NÃO | J8: NÃO | K8: NÃO
A9: =A8+1 -> 7 | B9: 54711482000117 | C9: CAIXA | D9: AGENCIA 33 MARKETING E NEGOCIOS DIGITAIS LTDA | E9: SIMPLES NACIONAL | F9: KELVIN | G9: 45931 | H9: NÃO | I9: NÃO | J9: NÃO | K9: NÃO
A10: =A9+1 -> 8 | B10: 42730764000182 | C10: CAIXA | D10: AGRO VIRA LATA COMÉRCIO DE ARTIGOS PARA ANIMAIS E SERVIÇOES LTDA | E10: SIMPLES NACIONAL | F10: INGRID | G10: 45627 | H10: NÃO | I10: NÃO | J10: NÃO | K10: NÃO
A11: =A10+1 -> 9 | B11: 35965694000186 | C11: NIBO | D11: ALLEGRO COMÉRCIO DE ROUPAS | E11: SIMPLES NACIONAL | F11: KELVIN | G11: 45778 | H11: NÃO | I11: NÃO | J11: NÃO | K11: NÃO
A12: =A11+1 -> 10 | B12: 28251192000128 | C12: CAIXA | D12: ALMED SERVICOS MEDICOS LTDA | E12: SIMPLES NACIONAL | F12: INGRID | G12: 45900 | H12: NÃO | I12: NÃO | J12: NÃO | K12: NÃO
A13: =A12+1 -> 11 | B13: 43106777000148 | C13: CAIXA | D13: ANDRE DA SILVA FERRAZ SOCIEDADE INVIDIDUAL DE ADVOCACIA | E13: SIMPLES NACIONAL | F13: INGRID | G13: 45900 | H13: NÃO | I13: NÃO | J13: NÃO | K13: NÃO
A14: =A13+1 -> 12 | B14: 51798642000119 | C14: ACOMPANHAR | D14: ANHANGUERA UNAÍ EDUCAÇÃO LTDA | E14: SIMPLES NACIONAL | F14: INGRID | G14: 45627 | H14: NÃO | I14: NÃO | J14: NÃO | K14: NÃO
A15: =A14+1 -> 13 | B15: 33154864000117 | C15: BANCO | D15: AO QUADRADO FABRICAÇAO PROPRIA DE PRODUTOS ALIMENTICIOS LTDA | E15: SIMPLES NACIONAL | F15: KELVIN | G15: 45901 | H15: NÃO | I15: NÃO | J15: NÃO | K15: NÃO
... A54: =A53+1 -> 52 | B54: 19662855000106 | C54: BPO | D54: EAPL COMERCIO DE APARELHOS AUDITIVOS (CENTRO AUDITIVO AUDIOFISA) | E54: LUCRO PRESUMIDO | F54: KELVIN | G54: 45627 | H54: NÃO | I54: NÃO | J54: NÃO | K54: NÃO
A55: =A54+1 -> 53 | B55: 19.662.855/0004-59 | C55: CAIXA | D55: EAPL COMERCIO DE APARELHOS AUDITIVOS LTDA (GAMA) (AUDIOFISA) | E55: LUCRO PRESUMIDO | F55: INGRID | G55: 45656 | H55: NÃO | I55: NÃO | J55: NÃO | K55: NÃO
A56: =A55+1 -> 54 | B56: 19.662.855/0005-30 | C56: CAIXA | D56: EAPL COMERCIO DE APARELHOS AUDITIVOS LTDA(ASA NORTE)(AUDIOFISA) | E56: LUCRO PRESUMIDO | F56: KELVIN | G56: 45656 | H56: NÃO | I56: NÃO | J56: NÃO | K56: NÃO
A57: =A56+1 -> 55 | B57: 62760002000136 | C57: ACOMPANHAR | D57: EDUARDO CARDOSO SERVICOS MEDICOS LTD | E57: SIMPLES NACIONAL | F57: KELVIN | G57: 45901 | H57: NÃO | I57: NÃO | J57: NÃO | K57: NÃO
A58: =A57+1 -> 56 | B58: 13345041000161 | C58: BPO | D58: EME - COMERCIO DE MOVEIS LTDA | E58: SIMPLES NACIONAL | F58: KELVIN | G58: 45870 | H58: NÃO | I58: NÃO | J58: NÃO | K58: NÃO
A59: =A58+1 -> 57 | B59: 13345041000242 | C59: BPO | D59: EME - COMERCIO DE MOVEIS LTDA (FILIAL) | E59: SIMPLES NACIONAL | F59: KELVIN | G59: 45870 | H59: NÃO | I59: NÃO | J59: NÃO | K59: NÃO
A60: =A59+1 -> 58 | B60: 36599674000100 | C60: CAIXA | D60: EMPORIO DIVA COMERCIO DE PRODUTOS DE BELEZA EIRELI | E60: LUCRO PRESUMIDO | F60: INGRID | G60: 45627 | H60: NÃO | I60: NÃO | J60: NÃO | K60: NÃO
A61: =A60+1 -> 59 | B61: 48439778000128 | C61: CAIXA | D61: ESCOLA E CRECHE GERAÇÃO APRENDER LTDA | E61: SIMPLES NACIONAL | F61: INGRID | G61: 45627 | H61: NÃO | I61: NÃO | J61: NÃO | K61: NÃO
A62: =A61+1 -> 60 | B62: 63.274.325/0001-82 | C62: ACOMPANHAR | D62: ESFERA CORRETORA DE SEGUROS LTDA | E62: SIMPLES NACIONAL | F62: INGRID | G62: 45950 | H62: NÃO | I62: NÃO | J62: NÃO | K62: NÃO
A63: =A62+1 -> 61 | B63: 61963820000173 | C63: ACOMPANHAR | D63: F. B. FREITAS DE SOUZA LTDA | E63: SIMPLES NACIONAL | F63: INGRID | G63: 45839 | H63: NÃO | I63: NÃO | J63: NÃO | K63: NÃO
A64: =A63+1 -> 62 | B64: 35725797000179 | C64: CAIXA | D64: F.B. SANTOS GESTAO E ADMINISTRAÇÃO IMOBILIARIA | E64: LUCRO PRESUMIDO | F64: INGRID | G64: 45627 | H64: NÃO | I64: NÃO | J64: NÃO | K64: NÃO
A65: =A64+1 -> 63 | B65: 18252709000140 | C65: CAIXA | D65: FARIA COMERCIO DE BEBIDAS,CONVENIENCIA,EVENTOS E LOCACOES LTDA | E65: SIMPLES NACIONAL | F65: KELVIN | G65: 45627 | H65: NÃO | I65: NÃO | J65: NÃO | K65: NÃO
A66: =A65+1 -> 64 | B66: 36768275000117 | C66: CAIXA | D66: FARIA DUE COMERCIO DE BEBIDAS E ALIMENTOS LTDA | E66: SIMPLES NACIONAL | F66: KELVIN | G66: 45627 | H66: NÃO | I66: NÃO | J66: NÃO | K66: NÃO
A67: =A66+1 -> 65 | B67: 53808182000198 | C67: CAIXA | D67: FENESTRA INDUSTRIA, COMERCIO, FABRICACAO E INSTALACAO DE METAISE VIDROS LTDA | E67: SIMPLES NACIONAL | F67: KELVIN | G67: 45627 | H67: NÃO | I67: NÃO | J67: NÃO | K67: NÃO
A68: =A67+1 -> 66 | B68: 56932805000128 | C68: NIBO | D68: FEO TECNOLOGIA LTDA | E68: LUCRO PRESUMIDO | F68: KELVIN | G68: 45992 | H68: SIM | I68: SIM | J68: SIM | K68: SIM
A69: =A68+1 -> 67 | B69: 28460728000115 | C69: CAIXA | D69: FERNANDO NAVES SOCIEDADE INDIVIDUAL DE ADVOCACIA | E69: SIMPLES NACIONAL | F69: KELVIN | G69: 45627 | H69: NÃO | I69: NÃO | J69: NÃO | K69: NÃO
A70: =A69+1 -> 68 | B70: 49779103000190 | C70: CAIXA | D70: FINANCIAL CONSULTORES ASSOCIADOS LTDA | E70: SIMPLES NACIONAL | F70: INGRID | G70: 45627 | H70: NÃO | I70: NÃO | J70: NÃO | K70: NÃO
A71: =A70+1 -> 69 | B71: 46265509000167 | C71: CAIXA | D71: FLAVIO MACEDO CORRETORA DE SEGUROS LTDA | E71: SIMPLES NACIONAL | F71: INGRID | G71: 45627 | H71: NÃO | I71: NÃO | J71: NÃO | K71: NÃO
A72: =A71+1 -> 70 | B72: 20282860000172 | C72: CAIXA | D72: FORNO MASTER INDUSTRIA E COMERCIO DE BISCOITOS LTDA | E72: SIMPLES NACIONAL | F72: INGRID | G72: 45627 | H72: NÃO | I72: NÃO | J72: NÃO | K72: NÃO
A73: =A72+1 -> 71 | B73: 22109712000186 | C73: BANCO | D73: FORTALEZA COMERCIO E DISTRIBUICAO DE ALIMENTOS LTDA | E73: LUCRO PRESUMIDO | F73: KELVIN | G73: 45627 | H73: NÃO | I73: NÃO | J73: NÃO | K73: NÃO
A74: =A73+1 -> 72 | B74: 28234202000117 | C74: CAIXA | D74: FRIO TECNICO'S - PRESTACAO DE SERVICOS DE INSTALACAO DE AR CONDICIONADO LTDA | E74: SIMPLES NACIONAL | F74: KELVIN | G74: 45870 | H74: NÃO | I74: NÃO | J74: NÃO | K74: NÃO
... A119: =A118+1 -> 117 | B119: 22554179000161 | C119: BPO | D119: LIVE PERSONAL LTDA | E119: SIMPLES NACIONAL | F119: INGRID | G119: 45900 | H119: NÃO | I119: NÃO | J119: NÃO | K119: NÃO
A120: =A119+1 -> 118 | B120: 33.895.694/0001-21 | C120: ACOMPANHAR | D120: LL NARRATIVAS VISUAIS LTDA | E120: SIMPLES NACIONAL | F120: KELVIN | G120: 45292 | H120: NÃO | I120: NÃO | J120: NÃO | K120: NÃO
A121: =A120+1 -> 119 | B121: 31687088000195 | C121: NIBO | D121: LLIK COMERCIO DE ACESSORIOS E COSMETICOS LTDA | E121: SIMPLES NACIONAL | F121: KELVIN | G121: 45839 | H121: SIM | I121: SIM | J121: SIM | K121: SIM
A122: =A121+1 -> 120 | B122: 54184472000170 | C122: NIBO | D122: LLIK SECOND COMERCIO DE ACESSORIOS E COSMETICOS LTDA | E122: SIMPLES NACIONAL | F122: KELVIN | G122: 45839 | H122: NÃO | I122: NÃO | J122: NÃO | K122: NÃO
A123: =A122+1 -> 121 | B123: 14433426000143 | C123: CAIXA | D123: LOCAR ENGENHARIA LTDA ME | E123: LUCRO PRESUMIDO | F123: KELVIN | G123: 45627 | H123: NÃO | I123: NÃO | J123: NÃO | K123: NÃO
A124: =A123+1 -> 122 | B124: 47358326000159 | C124: CAIXA | D124: LUCALTO LTDA | E124: LUCRO PRESUMIDO | F124: INGRID | G124: 45627 | H124: SIM | I124: SIM | J124: SIM | K124: SIM
A125: =A124+1 -> 123 | B125: 24187519000199 | C125: CAIXA | D125: M.A COMERCIO E DISTRIBUICAO DE ALIMENTOS | E125: LUCRO REAL | F125: INGRID | G125: 45627 | H125: NÃO | I125: NÃO | J125: NÃO | K125: NÃO
A126: =A125+1 -> 124 | B126: 60218324000122 | C126: BANCO | D126: M.A DUE COMERCIO E DISTRIBUICAO DE ALIMENTOS LTDA | E126: LUCRO REAL | F126: INGRID | G126: 45901 | H126: NÃO | I126: NÃO | J126: NÃO | K126: NÃO
A127: =A126+1 -> 125 | B127: 54151384000172 | C127: CAIXA | D127: M.B GESTAO IMOBILIARIA LTDA | E127: SIMPLES NACIONAL | F127: KELVIN | G127: 45627 | H127: NÃO | I127: NÃO | J127: NÃO | K127: NÃO
A128: =A127+1 -> 126 | B128: 26525434000107 | C128: CAIXA | D128: M&M COMERCIO DE ALIMENTOS LTDA | E128: SIMPLES NACIONAL | F128: INGRID | G128: 45627 | H128: NÃO | I128: NÃO | J128: NÃO | K128: NÃO
A129: =A128+1 -> 127 | B129: 6374213000160 | C129: CAIXA | D129: M2 OPTICAL DO BRASIL LTDA | E129: SIMPLES NACIONAL | F129: INGRID | G129: 45627 | H129: NÃO | I129: NÃO | J129: NÃO | K129: NÃO
A130: =A129+1 -> 128 | B130: 40566970000173 | C130: BANCO | D130: MAIS SERVICOS DE ENGENHARIA LTDA | E130: SIMPLES NACIONAL | F130: INGRID | G130: 45992 | H130: SIM | I130: SIM | J130: SIM | K130: SIM
A131: =A130+1 -> 129 | B131: 00.662.993/0001-33 | C131: NIBO | D131: MALHARIA ALLEGRO | E131: SIMPLES NACIONAL | F131: INGRID | G131: 45809 | H131: NÃO | I131: NÃO | J131: NÃO | K131: NÃO
A132: =A131+1 -> 130 | B132: 18312259000133 | C132: CAIXA | D132: MAN CENTRO DE DESENVOLVIMENTO PSICOMOTOR LTDA | E132: SIMPLES NACIONAL | F132: KELVIN | G132: 45627 | H132: NÃO | I132: NÃO | J132: NÃO | K132: NÃO
A133: =A132+1 -> 131 | B133: 22582238000105 | C133: CAIXA | D133: MARCOS AURELIO ROCHA NUNES | E133: SIMPLES NACIONAL | F133: KELVIN | G133: 45627 | H133: NÃO | I133: NÃO | J133: NÃO | K133: NÃO
A134: =A133+1 -> 132 | B134: 022.143.733-90 | C134: CARNÊ LEÃO | D134: MARJORE TELES VIANA POMPEU | E134: AUTÔNOMO | F134: KELVIN | G134: 45901 | H134: NÃO | I134: NÃO | J134: NÃO | K134: NÃO
A135: =A134+1 -> 133 | B135: 56425581000168 | C135: 8SYS | D135: MEATZ AGUAS CLARAS COMERCIO DE ALIMENTO | E135: SIMPLES NACIONAL | F135: INGRID | G135: 45809 | H135: PREJUIZO | I135: PREJUIZO | J135: PREJUIZO | K135: PREJUIZO
A136: =A135+1 -> 134 | B136: 7462754000102 | C136: 8SYS | D136: MEATZ ASA NORTE BURGER COMÉRCIO DE ALIMENTOS LTDA | E136: LUCRO PRESUMIDO | F136: KELVIN | G136: 45901 | H136: NÃO | I136: NÃO | J136: NÃO | K136: SIM
A137: =A136+1 -> 135 | B137: 33013866000196 | C137: 8SYS | D137: MEATZ BSBURGER COMERCIO DE ALIMENTOS LTDA | E137: LUCRO PRESUMIDO | F137: KELVIN | G137: 45901 | H137: SIM | I137: SIM | J137: SIM | K137: SIM
A138: =A137+1 -> 136 | B138: 28347784000229 | C138: 8SYS | D138: MEATZ BURGER SUL COMERCIO DE ALIMENTOS LTDA - FILIAL | E138: SIMPLES NACIONAL | F138: KELVIN | G138: 45839 | H138: NÃO | I138: NÃO | J138: NÃO | K138: NÃO
A139: =A138+1 -> 137 | B139: 30046927000123 | C139: 8SYS | D139: MEATZ BURITIS BURGER COMERCIO DE ALIMENTOS LTDA | E139: SIMPLES NACIONAL | F139: KELVIN | G139: 45839 | H139: NÃO | I139: NÃO | J139: NÃO | K139: NÃO
A140: =A139+1 -> 138 | B140: 28120242000138 | C140: 8SYS | D140: MEATZ BURITIS HAMBURGUERIA ANTIGA P E C COMERCIO | E140: LUCRO PRESUMIDO | F140: KELVIN | G140: 45809 | H140: NÃO | I140: NÃO | J140: NÃO | K140: SIM
A141: =A140+1 -> 139 | B141: 55657116000190 | C141: 8SYS | D141: MEATZ CASTELO DUE COMÉRCIO | E141: SIMPLES NACIONAL | F141: KELVIN | G141: 45839 | H141: NÃO | I141: NÃO | J141: NÃO | K141: NÃO
A142: =A141+1 -> 140 | B142: 47133237000104 | C142: 8SYS | D142: MEATZ CASTELO HAMBURGUERIA ANTIGA ASA NORTE DUE | E142: LUCRO PRESUMIDO | F142: KELVIN | G142: 45839 | H142: NÃO | I142: NÃO | J142: NÃO | K142: SIM
A143: =A142+1 -> 141 | B143: 28347784000148 | C143: 8SYS | D143: MEATZ CENTRO SUL COMERCIO DE ALIMENTOS LTDA - MATRIZ | E143: SIMPLES NACIONAL | F143: KELVIN | G143: 45839 | H143: NÃO | I143: NÃO | J143: NÃO | K143: NÃO
A144: =A143+1 -> 142 | B144: 24773977000100 | C144: 8SYS | D144: MEATZ CENTRO SUL HAMBURGUERIA (ANTIGA AGUAS CLARAS) Delivery | E144: LUCRO PRESUMIDO | F144: INGRID | G144: 45839 | H144: SIM | I144: SIM | J144: SIM | K144: SIM
A145: =A144+1 -> 143 | B145: 35027019000106 | C145: 8SYS | D145: MEATZ CIDADE NOVA COMERCIO DE ALIMENTOS LTDA | E145: SIMPLES NACIONAL | F145: KELVIN | G145: 45627 | H145: NÃO | I145: NÃO | J145: NÃO | K145: NÃO
A146: =A145+1 -> 144 | B146: 29936130000112 | C146: 8SYS | D146: MEATZ CIDADE NOVA HAMBURGUERIA (ANTIGA WPC COMERCIO) Delivery | E146: LUCRO PRESUMIDO | F146: INGRID | G146: 45839 | H146: SIM | I146: SIM | J146: SIM | K146: SIM
... A223: =A222+1 -> 221 | B223: 36557204000175 | C223: CAIXA | D223: VITRINE COMERCIO DE ARTIGOS OTICOS LTDA | E223: SIMPLES NACIONAL | F223: INGRID | G223: 45656 | H223: NÃO | I223: NÃO | J223: NÃO | K223: NÃO
A224: =A223+1 -> 222 | B224: 62.361.378/0001-78 | C224: ACOMPANHAR | D224: VM R.3 SAUDE LTDA | E224: LUCRO PRESUMIDO | F224: KELVIN | G224: 45870 | H224: NÃO | I224: NÃO | J224: NÃO | K224: NÃO
A225: =A224+1 -> 223 | B225: 28218047000145 | C225: ACOMPANHAR | D225: WAME4 SOCIEDADE DE PARTICIPACOES LTDA | E225: LUCRO PRESUMIDO | F225: KELVIN | G225: 45870 | H225: NÃO | I225: NÃO | J225: NÃO | K225: NÃO
A226: =A225+1 -> 224 | B226: 38287080000180 | C226: ACOMPANHAR | D226: WSS NEGOCIOS DIGITAIS LTDA | E226: LUCRO PRESUMIDO | F226: KELVIN | G226: 45656 | H226: NÃO | I226: NÃO | J226: NÃO | K226: NÃO
A227: =A226+1 -> 225 | B227: 41231672000195 | C227: BANCO | D227: WWC TECNOLOGIA LTDA | E227: SIMPLES NACIONAL | F227: KELVIN | G227: 45656 | H227: NÃO | I227: NÃO | J227: NÃO | K227: NÃO
A228: =A227+1 -> 226 | B228: 63403491000131 | C228: ACOMPANHAR | D228: SUPERCAR VEÍCULOS DF COMÉRCIO E LOCAÇÃO DE VEÍCULOS LTDA | E228: SIMPLES NACIONAL | F228: KELVIN | G228: 45931 | H228: NÃO | I228: NÃO | J228: NÃO | K228: NÃO
A229: =A228+1 -> 227 | B229: 52.584.427/0001-88 | C229: ACOMPANHAR | D229: GEOLINK TRANSFORMACAO DIGITAL LTDA | E229: SIMPLES NACIONAL | F229: INGRID | G229: 45962 | H229: NÃO | I229: NÃO | J229: NÃO | K229: NÃO

Sheet Página16
B2: CNPJ | C2: EMPRESAS | D2: CÓDIGO SISTEMA | E2: INTEGRAÇÃO FINANCEIRA | F2: REGIME TRIBUTÁRIO | G2: RESPONSÁVEL | H2: COMPETÊNCIA DE FECHAMENTO | I2: FECHAMENTOS EM 10.2025 | J2: FECHAMENTOS EM 11.2025 | K2: FECHAMENTOS EM 12.2025 | L2: FECHAMENTOS EM 01.2026 | M2: FECHAMENTOS EM 02.2026
A3: 1 | B3: 28523040000137 | C3: 180X NEGOCIOS DIGITAIS LTDA | D3: 555 | E3: CAIXA | F3: LUCRO PRESUMIDO | G3: INGRID | H3: 46023 | I3: 45931 | J3: 45962 | K3: 45992
A4: =A3+1 -> 2 | B4: 63849413000165 | C4: 2RV ADMINISTRACAO E CONSULTORIA LTDA | D4: 259 | E4: ACOMPANHAR | F4: SIMPLES NACIONAL | G4: KELVIN | H4: 45931 | L4: 46023
A5: =A4+1 -> 3 | B5: 52613816000194 | C5: 3.5 ESPORTE E SAÚDE LTDA (TAGUATINGA) | D5: 183 | E5: BANCO | F5: SIMPLES NACIONAL | G5: INGRID | H5: 46023 | I5: 45931
A6: =A5+1 -> 4 | B6: 53114412000119 | C6: 3.6 ESPORTE E SAÚDE LTDA | D6: 130 | E6: BPO | F6: LUCRO PRESUMIDO | G6: KELVIN | H6: 45931 | J6: 45962 | K6: 45992
A7: =A6+1 -> 5 | B7: 65173227000184 | C7: ACADEMIA CEILANDIA DUE LTDA | D7: 272 | E7: ACOMPANHAR | F7: SIMPLES NACIONAL | G7: KELVIN | H7: 46054
A8: =A7+1 -> 6 | B8: 57407089000122 | C8: ACADEMIA CEILANDIA ESPORTE SAUDE LTDA | D8: 195 | E8: CAIXA | F8: LUCRO PRESUMIDO | G8: KELVIN | H8: 45931 | J8: 45962 | K8: 45992
A9: =A8+1 -> 7 | B9: 9404697000130 | C9: ACADEMIA PERSONAL FITNESS LTDA (LIVE 3.3) | D9: 134 | E9: CAIXA | F9: SIMPLES NACIONAL | G9: KELVIN | H9: 45931 | J9: 45962 | K9: 45992
A10: =A9+1 -> 8 | B10: 43798918000130 | C10: AG COMERCIO E MERCEARIA LTDA | D10: 408 | E10: BANCO | F10: LUCRO REAL | G10: KELVIN | H10: 45931 | I10: 45931
A11: =A10+1 -> 9 | B11: 54711482000117 | C11: AGENCIA 33 MARKETING E NEGOCIOS DIGITAIS LTDA | D11: 148 | E11: CAIXA | F11: SIMPLES NACIONAL | G11: KELVIN | H11: 45931 | J11: 45962 | K11: 45992
A12: =A11+1 -> 10 | B12: 42730764000182 | C12: AGRO VIRA LATA COMÉRCIO DE ARTIGOS PARA ANIMAIS E SERVIÇOES LTDA | D12: 389 | E12: CAIXA | F12: SIMPLES NACIONAL | G12: INGRID | H12: 45931 | J12: 45962 | K12: 45992
A13: =A12+1 -> 11 | B13: 64899759000130 | C13: AHAVA ENERGIA SOLAR | D13: 270 | E13: NIBO | F13: LUCRO PRESUMIDO | G13: KELVIN | H13: 46054 | M13: 46054
A14: =A13+1 -> 12 | B14: 24924847000120 | C14: ALDEMIR CANDIDO DE RESENDE ME | D14: 263 | E14: ACOMPANHAR | F14: SIMPLES NACIONAL | G14: INGRID | H14: 46023 | L14: 46023 | M14: 46054
A15: =A14+1 -> 13 | B15: 35965694000186 | C15: ALLEGRO COMÉRCIO DE ROUPAS | D15: 232 | E15: NIBO | F15: SIMPLES NACIONAL | G15: KELVIN | H15: 45778
A16: =A15+1 -> 14 | B16: 28251192000128 | C16: ALMED SERVICOS MEDICOS LTDA | D16: 154 | E16: CAIXA | F16: SIMPLES NACIONAL | G16: INGRID | H16: 45901 | I16: 45931 | J16: 45962
A17: =A16+1 -> 15 | B17: 30826817000184 | C17: ALS SOLUÇÕES ESTRUTURAIS LTDA | D17: 268 | E17: ACOMPANHAR | F17: LUCRO PRESUMIDO | G17: INGRID | H17: 46054 | L17: 46054 | M17: 46054
A18: =A17+1 -> 16 | B18: 43106777000148 | C18: ANDRE DA SILVA FERRAZ SOCIEDADE INVIDIDUAL DE ADVOCACIA | D18: 391 | E18: CAIXA | F18: SIMPLES NACIONAL | G18: INGRID | H18: 45901 | I18: 45931 | J18: 45962
A19: =A18+1 -> 17 | B19: 33154864000117 | C19: AO QUADRADO FABRICAÇAO PROPRIA DE PRODUTOS ALIMENTICIOS LTDA | D19: 425 | E19: BANCO | F19: LUCRO REAL | G19: KELVIN | H19: 45992 | J19: 45962 | L19: 46023
A20: =A19+1 -> 18 | B20: 51055596000168 | C20: APS CONSULTORIA EM VENDAS E CRESCIMENTO LTDA | D20: 82 | E20: CAIXA | F20: SIMPLES NACIONAL | G20: INGRID | H20: 45930 | I20: 45931 | J20: 45962
A21: =A20+1 -> 19 | B21: 40192892000194 | C21: ARQ ENG CONSTRUCOES E COMERCIO LTDA | D21: 37 | E21: CAIXA | F21: SIMPLES NACIONAL | G21: KELVIN | H21: 45931 | J21: 45962 | K21: 45992
A22: =A21+1 -> 20 | B22: 686261000107 | C22: ASMRE ASSOC DOS SERV DO MIN DAS REL EXTERIORES | D22: 409 | E22: NIBO | F22: LUCRO PRESUMIDO | G22: KELVIN | H22: 45992 | K22: 45992 | M22: 46054
A23: =A22+1 -> 21 | B23: 32474592000170 | C23: AUDIOFISA GAMA COMÉRCIO DE APARELHOS AUDITIVOS LTDA ME | D23: 114 | E23: CAIXA | F23: SIMPLES NACIONAL | G23: INGRID | H23: 45931 | J23: 45962
A24: =A23+1 -> 22 | B24: 49890800000114 | C24: B2JF COMÉRCIO DE ALIMENTOS LTDA | D24: 10 | E24: CAIXA | F24: LUCRO PRESUMIDO | G24: KELVIN | H24: 45931 | J24: 45962 | K24: 45992
A25: =A24+1 -> 23 | B25: 62733499000101 | C25: BAHEA COZINHA BAIANA ASA NORTE LTDA | D25: 246 | E25: BANCO | F25: SIMPLES NACIONAL | G25: KELVIN | H25: 45901 | I25: 45931
A26: =A25+1 -> 24 | B26: 33464640000101 | C26: BAHEA COZINHA BAIANA LTDA | D26: 382 | E26: VOXEL | F26: LUCRO PRESUMIDO | G26: KELVIN | H26: 45931
A27: =A26+1 -> 25 | B27: 21090763000140 | C27: BANCA CREPE TO GO COMERCIO LTDA | D27: 13 | E27: CAIXA | F27: LUCRO PRESUMIDO | G27: INGRID | H27: 46023
A28: =A27+1 -> 26 | B28: 24711074000102 | C28: BARDO REPRESENTACAO E TRANSPORTES EIRELI | D28: 38 | E28: CAIXA | F28: LUCRO PRESUMIDO | G28: INGRID | H28: 46023 | I28: 45931 | J28: 45962
A29: =A28+1 -> 27 | B29: 58952972000166 | C29: BARUK COMERCIO E DISTRIBUIÇÃO DE ALIMENTOS LTDA | D29: 207 | E29: BANCO | F29: SIMPLES NACIONAL | G29: INGRID | H29: 45992 | I29: 45931 | M29: 46054
A30: =A29+1 -> 28 | B30: 50605321000198 | C30: BILLY BYTE SOLUÇÕES LTDA | D30: 76 | E30: NIBO | F30: LUCRO PRESUMIDO | G30: KELVIN | H30: 45992 | I30: 45931 | K30: 45992 | L30: 46023
A31: =A30+1 -> 29 | B31: 48484094000148 | C31: BRASIL VERDE COMÉRCIO VAREJISTA E ATACADISTA DE PAMONHAS LTDA | D31: 188 | E31: BPO | F31: SIMPLES NACIONAL | G31: KELVIN | H31: 45931 | J31: 45962 | K31: 45992
A32: =A31+1 -> 30 | B32: 5317981000119 | C32: BRASILIA TONER LTDA | D32: 87 | E32: CAIXA | F32: SIMPLES NACIONAL | G32: INGRID | H32: 45931 | J32: 45962
A33: =A32+1 -> 31 | B33: 55038535000143 | C33: BRM ENGENHARIA E TECNOLOGIA LTDA | D33: 160 | E33: CAIXA | F33: SIMPLES NACIONAL | G33: KELVIN | H33: 45962 | J33: 45962 | K33: 45992 | L33: 46023
A34: =A33+1 -> 32 | B34: 38141002000173 | C34: BROTHES BURGER COMERCIO DE ALIMENTOS LTDA | D34: 529 | E34: CAIXA | F34: SIMPLES NACIONAL | G34: INGRID | H34: 45901 | J34: 45962
A35: =A34+1 -> 33 | B35: 47500142000181 | C35: BRUMIX TREINAMENTO, DESENVOLVIMENTO E SERVICOS LTDA | D35: 564 | E35: CAIXA | F35: SIMPLES NACIONAL | G35: KELVIN | H35: 45962 | J35: 45962 | K35: 45992 | L35: 46023
A36: =A35+1 -> 34 | B36: 22614874000333 | C36: CADEIRAS DESIGN LTDA (FILIAL) | D36: 211 | E36: BPO | F36: SIMPLES NACIONAL | G36: KELVIN | H36: 45931 | J36: 45962 | K36: 45992
A37: =A36+1 -> 35 | B37: 22614874000171 | C37: CADEIRAS DESIGN LTDA (MATRIZ) | D37: 210 | E37: BPO | F37: SIMPLES NACIONAL | G37: KELVIN | H37: 45931 | J37: 45962 | K37: 45992
A38: =A37+1 -> 36 | B38: 29682133000177 | C38: CADEIRAS DESIGN SHOPPING ID LTDA | D38: 215 | E38: BPO | F38: SIMPLES NACIONAL | G38: KELVIN | H38: 45931 | J38: 45962 | K38: 45992
A39: =A38+1 -> 37 | B39: 28527486000130 | C39: CADEIRAS DESIGN.COM LTDA | D39: 214 | E39: BPO | F39: SIMPLES NACIONAL | G39: KELVIN | H39: 45931 | I39: 45931 | K39: 45992
A40: =A39+1 -> 38 | B40: 11111157000100 | C40: CASA DE FRUTAS A & E LTDA | D40: 241 | E40: CAIXA | F40: SIMPLES NACIONAL | G40: INGRID | H40: 45901 | I40: 45931
A41: =A40+1 -> 39 | B41: 63653031000161 | C41: CASA QUADRADA PARTICIPACOES | D41: 255 | E41: ACOMPANHAR | F41: LUCRO PRESUMIDO | G41: KELVIN | H41: 45962 | L41: 46023
A42: =A41+1 -> 40 | B42: 34698196000151 | C42: CENTRO DE MEDICINA DE FAMILIA DE BRASILIA LTDA | D42: 135 | E42: BANCO | F42: LUCRO PRESUMIDO | G42: INGRID | H42: 45992 | J42: 45962
A43: =A42+1 -> 41 | B43: 22855971000156 | C43: CENTRO DE NEFROLOGIA DO DISTRITO FEDERAL LTDA | D43: 104 | E43: NIBO | F43: LUCRO PRESUMIDO | G43: INGRID | H43: 46023 | I43: 45931 | J43: 45962 | L43: 46023
A44: =A43+1 -> 42 | B44: 33612605000192 | C44: CLIMA GESTAO DE PESSOAS LTDA | D44: 401 | E44: BANCO | F44: SIMPLES NACIONAL | G44: INGRID | H44: 46023 | J44: 45962
A45: =A44+1 -> 43 | B45: 55824679000125 | C45: CLINICA BIOPELLE SERVIÇOS MÉDICOS LTDA | D45: 170 | E45: CAIXA | F45: SIMPLES NACIONAL | G45: INGRID | H45: 45931 | J45: 45962
A46: =A45+1 -> 44 | B46: 41631955000124 | C46: CLINICA ODONTOLOGICA ALMEIDA LTDA (OPTIMA) | D46: 67 | E46: BANCO | F46: LUCRO PRESUMIDO | G46: KELVIN | H46: 45931 | J46: 45962 | K46: 45992
A47: =A46+1 -> 45 | B47: 39682852000141 | C47: COB OPTOMETRIA E SAUDE DOS OLHOS LTDA | D47: 27 | E47: CAIXA | F47: SIMPLES NACIONAL | G47: INGRID | H47: 45931 | I47: 45931 | J47: 45962
A48: =A47+1 -> 46 | B48: 59212038000170 | C48: CONGLOMERADO MACEDO COMERCIO DE ALIMENTOS IV LTDA | D48: 229 | E48: CAIXA | F48: SIMPLES NACIONAL | G48: INGRID | H48: 45809
A49: =A48+1 -> 47 | B49: 38212384000189 | C49: CONSULTORIA A LTDA | D49: 396 | E49: CAIXA | F49: SIMPLES NACIONAL | G49: INGRID | H49: 45901 | I49: 45931 | J49: 45962
A50: =A49+1 -> 48 | B50: 46905278000109 | C50: CRIS QUIRINO STUDIO ODONTOLOGICO LTDA | D50: 536 | E50: NIBO | F50: SIMPLES NACIONAL | G50: INGRID | H50: 45992 | J50: 45962
A51: =A50+1 -> 49 | B51: 34488093000167 | C51: CWJR REPRESENTACOES LTDA | D51: 216 | E51: ACOMPANHAR | F51: SIMPLES NACIONAL | G51: KELVIN | H51: 45931 | J51: 45962 | K51: 46023
A52: =A51+1 -> 50 | B52: 47667895000186 | C52: DF HAMBURGUERIA CASTELO LTDA | D52: 582 | E52: CAIXA | F52: SIMPLES NACIONAL | G52: KELVIN | H52: 45992 | J52: 45962 | K52: 45992
A53: =A52+1 -> 51 | B53: 29525176000149 | C53: DF HAMBURGUERIA LTDA | D53: 581 | E53: CAIXA | F53: SIMPLES NACIONAL | G53: KELVIN | H53: 45931 | J53: 45962 | K53: 45992
A54: =A53+1 -> 52 | B54: 30666082000179 | C54: DJ RESTAURANTE E RECEPCOES LTDA | D54: 99 | E54: CAIXA | F54: LUCRO PRESUMIDO | G54: INGRID | H54: 46023 | J54: 45962 | K54: 45992
A55: =A54+1 -> 53 | B55: 40385101000142 | C55: DL ESPETINHOS COMERCIO DE ALIMENTOS LTDA | D55: 406 | E55: CAIXA | F55: SIMPLES NACIONAL | G55: INGRID | H55: 45901 | J55: 45962
A56: =A55+1 -> 54 | B56: 62686180000164 | C56: DOUGLAS & MARIO SOLUCOES EM ALUGUEL LTDA | D56: 245 | E56: ACOMPANHAR | F56: LUCRO PRESUMIDO | G56: KELVIN | H56: 45931 | I56: 45931 | K56: 46023
A57: =A56+1 -> 55 | B57: 43192522000145 | C57: DOUGLAS MATOS SOCIEDADE INDIVIDUAL DE ADVOCACIA | D57: 525 | E57: CAIXA | F57: SIMPLES NACIONAL | G57: KELVIN | H57: 45931 | J57: 45962 | K57: 45992
A58: =A57+1 -> 56 | B58: 63652658000106 | C58: DUODECIMA PARTICIPACOES LTDA | D58: 256 | E58: ACOMPANHAR | F58: LUCRO PRESUMIDO | G58: INGRID | H58: 45962
A59: =A58+1 -> 57 | B59: 32474729000196 | C59: EAPL AGUAS CLARAS COMERCIO DE APARELHOS (AUDIOFISA COMERCIO) | D59: 115 | E59: CAIXA | F59: SIMPLES NACIONAL | G59: KELVIN | H59: 45931 | L59: 46023
A60: =A59+1 -> 58 | B60: 19662855000106 | C60: EAPL COMERCIO DE APARELHOS AUDITIVOS (CENTRO AUDITIVO AUDIOFISA) | D60: 54 | E60: BPO | F60: LUCRO PRESUMIDO | G60: KELVIN | H60: 45627
A61: =A60+1 -> 59 | B61: 19662855000459 | C61: EAPL COMERCIO DE APARELHOS AUDITIVOS LTDA (GAMA) (AUDIOFISA) | D61: 236 | E61: CAIXA | F61: LUCRO PRESUMIDO | G61: INGRID | H61: 46023
A62: =A61+1 -> 60 | B62: 19662855000530 | C62: EAPL COMERCIO DE APARELHOS AUDITIVOS LTDA(ASA NORTE)(AUDIOFISA) | D62: 235 | E62: CAIXA | F62: LUCRO PRESUMIDO | G62: KELVIN | H62: 45627
A63: =A62+1 -> 61 | B63: 62760002000136 | C63: EDUARDO CARDOSO SERVICOS MEDICOS LTD | D63: 249 | E63: NIBO | F63: SIMPLES NACIONAL | G63: KELVIN | H63: 45992 | I63: 45931 | K63: 45992
A64: =A63+1 -> 62 | B64: 63.542.784/0001-08 | C64: ELPORTO PIZZA 206 SUL LTDA | D64: 279 | E64: ACOMPANHAR | F64: SIMPLES NACIONAL | G64: KELVIN | H64: 46082
A65: =A64+1 -> 63 | B65: 13345041000161 | C65: EME - COMERCIO DE MOVEIS LTDA | D65: 209 | E65: BPO | F65: SIMPLES NACIONAL | G65: KELVIN | H65: 45931 | I65: 45931 | J65: 45962 | K65: 45992
A66: =A65+1 -> 64 | B66: 13345041000242 | C66: EME - COMERCIO DE MOVEIS LTDA (FILIAL) | D66: 212 | E66: BPO | F66: SIMPLES NACIONAL | G66: KELVIN | H66: 45931 | I66: 45931 | J66: 45962 | K66: 45992
A67: =A66+1 -> 65 | B67: 36599674000100 | C67: EMPORIO DIVA COMERCIO DE PRODUTOS DE BELEZA EIRELI | D67: 11 | E67: CAIXA | F67: LUCRO PRESUMIDO | G67: INGRID | H67: 46023
A68: =A67+1 -> 66 | B68: 48439778000128 | C68: ESCOLA E CRECHE GERAÇÃO APRENDER LTDA | D68: 35 | E68: CAIXA | F68: SIMPLES NACIONAL | G68: INGRID | H68: 45931 | J68: 45962
A69: =A68+1 -> 67 | B69: 63274325000182 | C69: ESFERA CORRETORA DE SEGUROS LTDA | D69: 250 | E69: ACOMPANHAR | F69: LUCRO PRESUMIDO | G69: INGRID | H69: 45950
A70: =A69+1 -> 68 | B70: 61963820000173 | C70: F. B. FREITAS DE SOUZA LTDA | D70: 239 | E70: ACOMPANHAR | F70: SIMPLES NACIONAL | G70: INGRID | H70: 45839
A71: =A70+1 -> 69 | B71: 35725797000179 | C71: F.B. SANTOS GESTAO E ADMINISTRAÇÃO IMOBILIARIA | D71: 22 | E71: CAIXA | F71: LUCRO PRESUMIDO | G71: INGRID | H71: 46023 | J71: 45962
A72: =A71+1 -> 70 | B72: 18252709000140 | C72: FARIA COMERCIO DE BEBIDAS,CONVENIENCIA,EVENTOS E LOCACOES LTDA | D72: 25 | E72: CAIXA | F72: SIMPLES NACIONAL | G72: KELVIN | H72: 45931 | J72: 45962 | K72: 45992
A73: =A72+1 -> 71 | B73: 36768275000117 | C73: FARIA DUE COMERCIO DE BEBIDAS E ALIMENTOS LTDA | D73: 21 | E73: CAIXA | F73: SIMPLES NACIONAL | G73: KELVIN | H73: 45931 | J73: 45962 | K73: 45992
A74: =A73+1 -> 72 | B74: 53808182000198 | C74: FENESTRA INDUSTRIA, COMERCIO, FABRICACAO E INSTALACAO DE METAISE VIDROS LTDA | D74: 133 | E74: BANCO | F74: SIMPLES NACIONAL | G74: KELVIN | H74: 45931 | J74: 45962 | K74: 45992
A75: =A74+1 -> 73 | B75: 56932805000128 | C75: FEO TECNOLOGIA LTDA | D75: 185 | E75: NIBO | F75: LUCRO PRESUMIDO | G75: KELVIN | H75: 45932 | I75: 45931 | K75: 46023 | L75: 46023
A76: =A75+1 -> 74 | B76: 28460728000115 | C76: FERNANDO NAVES SOCIEDADE INDIVIDUAL DE ADVOCACIA | D76: 343 | E76: CAIXA | F76: SIMPLES NACIONAL | G76: KELVIN | H76: 45931 | J76: 45962 | K76: 45992
A77: =A76+1 -> 75 | B77: 65258029000113 | C77: FILO BEAUTY STUDIO | D77: 273 | E77: ACOMPANHAR | F77: SIMPLES NACIONAL | G77: KELVIN | H77: 46054
A78: =A77+1 -> 76 | B78: 49779103000190 | C78: FINANCIAL CONSULTORES ASSOCIADOS LTDA | D78: 24 | E78: CAIXA | F78: SIMPLES NACIONAL | G78: INGRID | H78: 45931 | J78: 45962
A79: =A78+1 -> 77 | B79: 20282860000172 | C79: FORNO MASTER INDUSTRIA E COMERCIO DE BISCOITOS LTDA | D79: 23 | E79: CAIXA | F79: SIMPLES NACIONAL | G79: INGRID | H79: 45627
A80: =A79+1 -> 78 | B80: 22109712000186 | C80: FORTALEZA COMERCIO E DISTRIBUICAO DE ALIMENTOS LTDA | D80: 30 | E80: BANCO | F80: LUCRO PRESUMIDO | G80: KELVIN | H80: 45627
A81: =A80+1 -> 79 | B81: 28234202000117 | C81: FRIO TECNICO'S - PRESTACAO DE SERVICOS DE INSTALACAO DE AR CONDICIONADO LTDA | D81: 102 | E81: CAIXA | F81: SIMPLES NACIONAL | G81: KELVIN | H81: 45992 | I81: 45931 | J81: 45962 | K81: 45992
A82: =A81+1 -> 80 | B82: 34974447000183 | C82: GARCIA KPP COMERCIO DE ALIMENTOS EIRELI (DONA MARICOTA) | D82: 336 | E82: CAIXA | F82: LUCRO PRESUMIDO | G82: INGRID | H82: 45627
A83: =A82+1 -> 81 | B83: 28071236000138 | C83: GC SILVA COMERCIO DE BEBIDAS 191DF EIRELI - MATRIZ | D83: 75 | E83: CAIXA | F83: LUCRO REAL | G83: INGRID | H83: 45627
A84: =A83+1 -> 82 | B84: 28071236000219 | C84: GC SILVA COMERCIO DE BEBIDAS 191DF EIRELI - GO | D84: 149 | E84: CAIXA | F84: LUCRO REAL | G84: INGRID | H84: 45627
A85: =A84+1 -> 83 | B85: 63315107000149 | C85: GEOINFRA ENGENHARIA LTDA | D85: 251 | E85: ACOMPANHAR | F85: SIMPLES NACIONAL | G85: INGRID | H85: 45952
A86: =A85+1 -> 84 | B86: 52584427000188 | C86: GEOLINK TRANSFORMACAO DIGITAL LTDA | D86: 253 | E86: ACOMPANHAR | F86: SIMPLES NACIONAL | G86: INGRID | H86: 45962 | J86: 45962
A87: =A86+1 -> 85 | B87: 17063002000122 | C87: GESTAO CONTADORES LTDA | D87: 1 | E87: CAIXA | F87: SIMPLES NACIONAL | G87: KELVIN | H87: 45627
A88: =A87+1 -> 86 | B88: 64.464.630/0001-08 | C88: GESTAO ONLINE OUTSOURCING LTDA | D88: 260 | E88: CAIXA | F88: SIMPLES NACIONAL | G88: INGRID | H88: 46023 | L88: 46023
A89: =A88+1 -> 87 | B89: 27072709000159 | C89: GK MEDICINE SERVICOS MEDICOS LTDA | D89: 513 | E89: CAIXA | F89: SIMPLES NACIONAL | G89: INGRID | H89: 45931 | J89: 45962 | K89: 45992
A90: =A89+1 -> 88 | B90: 53726610000133 | C90: GM BRASIL COMERCIO DE PRODUTOS OPTICOS LTDA | D90: 129 | E90: CAIXA | F90: SIMPLES NACIONAL | G90: INGRID | H90: 45627
A91: =A90+1 -> 89 | B91: 57670435000160 | C91: GPR SOFTWARE LTDA | D91: 196 | E91: BANCO | F91: LUCRO PRESUMIDO | G91: KELVIN | H91: 46023 | I91: 45931 | L91: 46023
A92: =A91+1 -> 90 | B92: 61166521000108 | C92: GRUPO IMS COMERCIO DE ALIMENTOS I LTDA (TEXAS BURGER) | D92: 233 | E92: CAIXA | F92: SIMPLES NACIONAL | G92: KELVIN | H92: 45901
A93: =A92+1 -> 91 | B93: 61166503000126 | C93: GRUPO IMS COMERCIO DE ALIMENTOS II LTDA (TEXAS BURGER) | D93: 234 | E93: CAIXA | F93: SIMPLES NACIONAL | G93: INGRID | H93: 45809
A94: =A93+1 -> 92 | B94: 54447300000142 | C94: GRUPO MACEDO (TEXAS BURGER) | D94: 144 | E94: CAIXA | F94: SIMPLES NACIONAL | G94: KELVIN | H94: 45931 | J94: 45962 | K94: 45992
A95: =A94+1 -> 93 | B95: 54447287000121 | C95: GRUPO MACEDO II (BEST BEEF) | D95: 146 | E95: CAIXA | F95: SIMPLES NACIONAL | G95: KELVIN | H95: 45931 | J95: 45962 | K95: 45992 | L95: 46023
A96: =A95+1 -> 94 | B96: 54447285000132 | C96: GRUPO MACEDO III (BURGER MANIA) | D96: 147 | E96: CAIXA | F96: SIMPLES NACIONAL | G96: KELVIN | H96: 45931 | J96: 45962 | K96: 45992
A97: =A96+1 -> 95 | B97: 50900559000146 | C97: GS SCHILLING CONSULTORIA EM TECNOLOGIA LTDA | D97: 63 | E97: CAIXA | F97: SIMPLES NACIONAL | G97: INGRID | H97: 45931 | J97: 45962 | K97: 45992
A98: =A97+1 -> 96 | B98: 64880825000120 | C98: IA TECH TECNOLOGIA DA INFORMACAO LTDA | D98: 269 | E98: ACOMPANHAR | F98: SIMPLES NACIONAL | G98: INGRID | H98: 46054 | M98: 46054
A99: =A98+1 -> 97 | B99: 36631894000165 | C99: IGREJA MINISTÉRIO NOVA VIDA | D99: 152 | E99: CAIXA | F99: LUCRO PRESUMIDO | G99: INGRID | H99: 46023 | J99: 45962 | K99: 45992
A100: =A99+1 -> 98 | B100: 55038481000116 | C100: IMPACT ENGENHARIA E ENERGIA SOLAR LTDA | D100: 159 | E100: CAIXA | F100: SIMPLES NACIONAL | G100: INGRID | H100: 45931 | K100: 45992
A101: =A100+1 -> 99 | B101: 59084161000153 | C101: IMS COMÉRCIO DE ALIMENTOS III LTDA (CONGLOMERADO) | D101: 230 | E101: CAIXA | F101: SIMPLES NACIONAL | G101: INGRID | H101: 45930 | I101: 45931
...

Sheet IMPLEMENTAÇÕES
B2: CNPJ | C2: EMPRESAS | D2: DATA DE FECHAMENTO | E2: ENVIO BALANCETES COMPETENCIA | F2: ECD | G2: ONVIO | H2: NIBO | I2: FISCAL/FOLHA
A3: 1 | B3: 28523040000137 | C3: 180X NEGOCIOS DIGITAIS LTDA | D3: 45323 | E3: NÃO | F3: NÃO OBRIGADA | G3: NÃO | H3: NÃO | I3: NÃO
A4: =A3+1 -> 2 | B4: 52613816000194 | C4: 3.5 ESPORTE E SAÚDE LTDA (TAGUATINGA) | D4: 45323 | E4: NÃO | F4: NÃO OBRIGADA | G4: NÃO | H4: NÃO | I4: NÃO
A5: =A4+1 -> 3 | B5: 53114412000119 | C5: 3.6 ESPORTE E SAÚDE LTDA | D5: 45323 | E5: NÃO | F5: NÃO OBRIGADA | G5: NÃO | H5: NÃO | I5: NÃO
A6: =A5+1 -> 4 | B6: 57407089000122 | C6: ACADEMIA CEILANDIA ESPORTE SAUDE LTDA | D6: 45383 | G6: NÃO | H6: NÃO | I6: NÃO
A7: =A6+1 -> 5 | B7: 9404697000130 | C7: ACADEMIA PERSONAL FITNESS LTDA (LIVE 3.3) | D7: 45292 | E7: NÃO | F7: ENVIADA | G7: NÃO | H7: NÃO | I7: NÃO
A8: =A7+1 -> 6 | B8: 43798918000130 | C8: AG COMERCIO E MERCEARIA LTDA | D8: 45383 | G8: NÃO | H8: NÃO | I8: NÃO
A9: =A8+1 -> 7 | B9: 54711482000117 | C9: AGENCIA 33 MARKETING E NEGOCIOS DIGITAIS LTDA | D9: 45323 | E9: NÃO | F9: NÃO OBRIGADA | G9: NÃO | H9: NÃO | I9: NÃO
A10: =A9+1 -> 8 | B10: 42730764000182 | C10: AGRO VIRA LATA COMÉRCIO DE ARTIGOS PARA ANIMAIS E SERVIÇOES LTDA | D10: 45323 | E10: NÃO | F10: NÃO OBRIGADA | G10: NÃO | H10: NÃO | I10: NÃO
A11: =A10+1 -> 9 | B11: 35965694000186 | C11: ALLEGRO COMÉRCIO DE ROUPAS | D11: 45292 | E11: NÃO | F11: NÃO OBRIGADA | G11: NÃO | H11: SIM | I11: NÃO
A12: =A11+1 -> 10 | B12: 28251192000128 | C12: ALMED SERVICOS MEDICOS LTDA | D12: 45413 | E12: NÃO | F12: NÃO OBRIGADA | G12: NÃO | H12: NÃO | I12: NÃO
A13: =A12+1 -> 11 | B13: 43106777000148 | C13: ANDRE DA SILVA FERRAZ SOCIEDADE INVIDIDUAL DE ADVOCACIA | D13: 45323 | E13: SIM | F13: NÃO OBRIGADA | G13: NÃO | H13: NÃO | I13: NÃO
A14: =A13+1 -> 12 | B14: 51798642000119 | C14: ANHANGUERA UNAÍ EDUCAÇÃO LTDA | D14: 45323 | E14: NÃO | F14: NÃO OBRIGADA | G14: NÃO | H14: NÃO | I14: NÃO
A15: =A14+1 -> 13 | B15: 33154864000117 | C15: AO QUADRADO FABRICAÇAO PROPRIA DE PRODUTOS ALIMENTICIOS LTDA | D15: 45323 | E15: NÃO | F15: NÃO OBRIGADA | G15: NÃO | H15: NÃO | I15: NÃO
A16: =A15+1 -> 14 | B16: 51055596000168 | C16: APS CONSULTORIA EM VENDAS E CRESCIMENTO LTDA | D16: 45383 | E16: NÃO | F16: ENVIADA | G16: NÃO | H16: NÃO | I16: NÃO
A17: =A16+1 -> 15 | B17: 40192892000194 | C17: ARQ ENG CONSTRUCOES E COMERCIO LTDA | D17: 45383 | E17: SIM | F17: NÃO OBRIGADA | G17: NÃO | H17: NÃO | I17: NÃO
A18: =A17+1 -> 16 | B18: 686261000107 | C18: ASMRE ASSOC DOS SERV DO MIN DAS REL EXTERIORES | D18: 45413 | E18: SIM | F18: ENVIADA | G18: NÃO | H18: NÃO | I18: NÃO
A19: =A18+1 -> 17 | B19: 32474729000196 | C19: AUDIOFISA COMERCIO DE APARELHOS AUDITIVOS LTDA (EAPL COMERCIO) | D19: 45352 | E19: NÃO | F19: NÃO OBRIGADA | G19: NÃO | H19: NÃO | I19: NÃO
A20: =A19+1 -> 18 | B20: 32474592000170 | C20: AUDIOFISA GAMA COMÉRCIO DE APARELHOS AUDITIVOS LTDA ME | D20: 45352 | E20: NÃO | F20: NÃO OBRIGADA | G20: NÃO | H20: NÃO | I20: NÃO
A21: =A20+1 -> 19 | B21: 49890800000114 | C21: B2JF COMÉRCIO DE ALIMENTOS LTDA | G21: NÃO | H21: NÃO | I21: NÃO
A22: =A21+1 -> 20 | B22: 62733499000101 | C22: BAHEA COZINHA BAIANA ASA NORTE LTDA | D22: 45383 | E22: NÃO | F22: NÃO OBRIGADA | G22: NÃO | H22: NÃO | I22: NÃO
A23: =A22+1 -> 21 | B23: 33464640000101 | C23: BAHEA COZINHA BAIANA LTDA | D23: 45323 | E23: NÃO | F23: NÃO OBRIGADA | G23: NÃO | H23: NÃO | I23: NÃO
A24: =A23+1 -> 22 | B24: 21090763000140 | C24: BANCA CREPE TO GO COMERCIO LTDA | D24: 45323 | E24: NÃO | F24: NÃO OBRIGADA | G24: NÃO | H24: NÃO | I24: NÃO
A25: =A24+1 -> 23 | B25: 24711074000102 | C25: BARDO REPRESENTACAO E TRANSPORTES EIRELI | D25: 45383 | E25: NÃO | F25: NÃO OBRIGADA | G25: NÃO | H25: NÃO | I25: NÃO
A26: =A25+1 -> 24 | B26: 58952972000166 | C26: BARUK COMERCIO E DISTRIBUIÇÃO DE ALIMENTOS LTDA | D26: 45352 | E26: SIM | F26: NÃO OBRIGADA | G26: NÃO | H26: NÃO | I26: NÃO
A27: =A26+1 -> 25 | B27: 50605321000198 | C27: BILLY BYTE SOLUÇÕES LTDA | D27: 45383 | E27: SIM | F27: ENVIADA | G27: NÃO | H27: SIM | I27: NÃO
A28: =A27+1 -> 26 | B28: 48484094000148 | C28: BRASIL VERDE COMÉRCIO VAREJISTA E ATACADISTA DE PAMONHAS LTDA | D28: 45383 | E28: SIM | F28: ENVIADA | G28: NÃO | H28: NÃO | I28: NÃO
A29: =A28+1 -> 27 | B29: 5317981000119 | C29: BRASILIA TONER LTDA | G29: NÃO | H29: NÃO | I29: NÃO
A30: =A29+1 -> 28 | B30: 55038535000143 | C30: BRM ENGENHARIA E TECNOLOGIA LTDA | D30: 45323 | E30: SIM | F30: ENVIADA | G30: NÃO | H30: NÃO | I30: NÃO
A31: =A30+1 -> 29 | B31: 38141002000173 | C31: BROTHES BURGER COMERCIO DE ALIMENTOS LTDA | D31: 45383 | E31: NÃO | F31: ENVIADA | G31: NÃO | H31: NÃO | I31: NÃO
A32: =A31+1 -> 30 | B32: 47500142000181 | C32: BRUMIX TREINAMENTO, DESENVOLVIMENTO E SERVICOS LTDA | D32: 45383 | E32: NÃO | F32: NÃO OBRIGADA | G32: NÃO | H32: NÃO | I32: NÃO
A33: =A32+1 -> 31 | B33: 22614874000333 | C33: CADEIRAS DESIGN LTDA (FILIAL) | D33: 45017 | E33: NÃO | F33: NÃO OBRIGADA | G33: NÃO | H33: NÃO | I33: NÃO
A34: =A33+1 -> 32 | B34: 22614874000171 | C34: CADEIRAS DESIGN LTDA (MATRIZ) | D34: 45383 | E34: NÃO | F34: NÃO OBRIGADA | G34: NÃO | H34: NÃO | I34: NÃO
A35: =A34+1 -> 33 | B35: 29682133000177 | C35: CADEIRAS DESIGN SHOPPING ID LTDA | D35: 45413 | E35: NÃO | F35: NÃO OBRIGADA | G35: NÃO | H35: NÃO | I35: NÃO
A36: =A35+1 -> 34 | B36: 28527486000130 | C36: CADEIRAS DESIGN.COM LTDA | D36: 45352 | E36: NÃO | F36: NÃO OBRIGADA | G36: NÃO | H36: NÃO | I36: NÃO
A37: =A36+1 -> 35 | B37: 11111157000100 | C37: CASA DE FRUTAS A & E LTDA | D37: 45017 | E37: NÃO | F37: NÃO OBRIGADA | G37: NÃO | H37: NÃO | I37: NÃO
A38: =A37+1 -> 36 | B38: 34698196000151 | C38: CENTRO DE MEDICINA DE FAMILIA DE BRASILIA LTDA | D38: 45383 | E38: NÃO | F38: ENVIADA | G38: NÃO | H38: NÃO | I38: NÃO
A39: =A38+1 -> 37 | B39: 22855971000156 | C39: CENTRO DE NEFROLOGIA DO DISTRITO FEDERAL LTDA | D39: 45352 | E39: NÃO | F39: NÃO OBRIGADA | G39: NÃO | H39: SIM | I39: NÃO
A40: =A39+1 -> 38 | B40: 33612605000192 | C40: CLIMA GESTAO DE PESSOAS LTDA | D40: 45323 | E40: NÃO | F40: NÃO OBRIGADA | G40: NÃO | H40: NÃO | I40: NÃO
A41: =A40+1 -> 39 | B41: 55824679000125 | C41: CLINICA BIOPELLE SERVIÇOS MÉDICOS LTDA | D41: 45352 | E41: NÃO | F41: NÃO OBRIGADA | G41: NÃO | H41: NÃO | I41: NÃO
... A46: =A45+1 -> 44 | B46: 46905278000109 | C46: CRIS QUIRINO STUDIO ODONTOLOGICO LTDA | D46: 45108 | E46: NÃO | F46: NÃO OBRIGADA | G46: NÃO | H46: NÃO | I46: NÃO
A47: =A46+1 -> 45 | B47: 34488093000167 | C47: CWJR REPRESENTACOES LTDA | G47: NÃO | H47: NÃO | I47: NÃO
A48: =A47+1 -> 46 | B48: 29525176000149 | C48: DF HAMBURGUERIA LTDA | D48: SEM MOVIMENTO | E48: SEM MOVIMENTO | F48: SEM MOVIMENTO | G48: NÃO | H48: NÃO | I48: NÃO
A49: =A48+1 -> 47 | B49: 47667895000186 | C49: DF HAMBURGUERIA LTDA | D49: 45352 | E49: NÃO | F49: NÃO OBRIGADA | G49: NÃO | H49: NÃO | I49: NÃO
A50: =A49+1 -> 48 | B50: 30666082000179 | C50: DJ RESTAURANTE E RECEPCOES LTDA | G50: NÃO | H50: NÃO | I50: NÃO
A51: =A50+1 -> 49 | B51: 40385101000142 | C51: DL ESPETINHOS COMERCIO DE ALIMENTOS LTDA | G51: NÃO | H51: NÃO | I51: NÃO
A52: =A51+1 -> 50 | B52: 62686180000164 | C52: DOUGLAS & MARIO SOLUCOES EM ALUGUEL LTDA | G52: NÃO | H52: NÃO | I52: NÃO
A53: =A52+1 -> 51 | B53: 43192522000145 | C53: DOUGLAS MATOS SOCIEDADE INDIVIDUAL DE ADVOCACIA | D53: 45352 | E53: NÃO | F53: NÃO OBRIGADA | G53: NÃO | H53: NÃO | I53: NÃO
A54: =A53+1 -> 52 | B54: 19662855000106 | C54: EAPL COMERCIO DE APARELHOS AUDITIVOS (CENTRO AUDITIVO AUDIOFISA) | D54: 45352 | E54: NÃO | F54: NÃO OBRIGADA | G54: NÃO | H54: NÃO | I54: NÃO
A55: =A54+1 -> 53 | B55: 19.662.855/0004-59 | C55: EAPL COMERCIO DE APARELHOS AUDITIVOS LTDA (GAMA) (AUDIOFISA) | D55: SEM MOVIMENTO | E55: SEM MOVIMENTO | F55: SEM MOVIMENTO | G55: NÃO | H55: NÃO | I55: NÃO
A56: =A55+1 -> 54 | B56: 19.662.855/0005-30 | C56: EAPL COMERCIO DE APARELHOS AUDITIVOS LTDA(ASA NORTE)(AUDIOFISA) | D56: 45383 | E56: NÃO | F56: NÃO OBRIGADA | G56: NÃO | H56: NÃO | I56: NÃO
A57: =A56+1 -> 55 | B57: 62760002000136 | C57: EDUARDO CARDOSO SERVICOS MEDICOS LTD | D57: 45383 | E57: NÃO | F57: NÃO OBRIGADA | G57: NÃO | H57: NÃO | I57: NÃO
A58: =A57+1 -> 56 | B58: 13345041000161 | C58: EME - COMERCIO DE MOVEIS LTDA | D58: 45352 | E58: NÃO | F58: NÃO OBRIGADA | G58: NÃO | H58: NÃO | I58: NÃO
A59: =A58+1 -> 57 | B59: 13345041000242 | C59: EME - COMERCIO DE MOVEIS LTDA (FILIAL) | D59: 45352 | E59: NÃO | F59: NÃO OBRIGADA | G59: NÃO | H59: NÃO | I59: NÃO
A60: =A59+1 -> 58 | B60: 36599674000100 | C60: EMPORIO DIVA COMERCIO DE PRODUTOS DE BELEZA EIRELI | D60: 45261 | E60: NÃO | F60: NÃO OBRIGADA | G60: NÃO | H60: NÃO | I60: NÃO
A61: =A60+1 -> 59 | B61: 48439778000128 | C61: ESCOLA E CRECHE GERAÇÃO APRENDER LTDA | D61: SEM MOVIMENTO | E61: SEM MOVIMENTO | F61: SEM MOVIMENTO | G61: NÃO | H61: NÃO | I61: NÃO
A62: =A61+1 -> 60 | B62: 63.274.325/0001-82 | C62: ESFERA CORRETORA DE SEGUROS LTDA | D62: 45323 | E62: NÃO | F62: ENVIADA | G62: NÃO | H62: NÃO | I62: NÃO
A63: =A62+1 -> 61 | B63: 61963820000173 | C63: F. B. FREITAS DE SOUZA LTDA | D63: 45323 | E63: NÃO | F63: NÃO OBRIGADA | G63: NÃO | H63: NÃO | I63: NÃO
A64: =A63+1 -> 62 | B64: 35725797000179 | C64: F.B. SANTOS GESTAO E ADMINISTRAÇÃO IMOBILIARIA | D64: 45261 | E64: NÃO | F64: NÃO OBRIGADA | G64: NÃO | H64: NÃO | I64: NÃO
A65: =A64+1 -> 63 | B65: 18252709000140 | C65: FARIA COMERCIO DE BEBIDAS,CONVENIENCIA,EVENTOS E LOCACOES LTDA | D65: 45413 | E65: NÃO | F65: NÃO OBRIGADA | G65: NÃO | H65: NÃO | I65: NÃO
A66: =A65+1 -> 64 | B66: 36768275000117 | C66: FARIA DUE COMERCIO DE BEBIDAS E ALIMENTOS LTDA | D66: 45383 | E66: NÃO | F66: NÃO OBRIGADA | G66: NÃO | H66: NÃO | I66: NÃO
A67: =A66+1 -> 65 | B67: 53808182000198 | C67: FENESTRA INDUSTRIA, COMERCIO, FABRICACAO E INSTALACAO DE METAISE VIDROS LTDA | D67: 45383 | E67: NÃO | F67: NÃO OBRIGADA | G67: NÃO | H67: NÃO | I67: NÃO
A68: =A67+1 -> 66 | B68: 56932805000128 | C68: FEO TECNOLOGIA LTDA | D68: 45444 | G68: NÃO | H68: NÃO | I68: NÃO
A69: =A68+1 -> 67 | B69: 28460728000115 | C69: FERNANDO NAVES SOCIEDADE INDIVIDUAL DE ADVOCACIA | D69: 45352 | E69: NÃO | F69: NÃO OBRIGADA | G69: NÃO | H69: NÃO | I69: NÃO
A70: =A69+1 -> 68 | B70: 49779103000190 | C70: FINANCIAL CONSULTORES ASSOCIADOS LTDA | D70: 45352 | E70: NÃO | F70: NÃO OBRIGADA | G70: NÃO | H70: NÃO | I70: NÃO
A71: =A70+1 -> 69 | B71: 46265509000167 | C71: FLAVIO MACEDO CORRETORA DE SEGUROS LTDA | D71: SEM MOVIMENTO | E71: SEM MOVIMENTO | F71: SEM MOVIMENTO | G71: NÃO | H71: NÃO | I71: NÃO
A72: =A71+1 -> 70 | B72: 20282860000172 | C72: FORNO MASTER INDUSTRIA E COMERCIO DE BISCOITOS LTDA | D72: 45352 | E72: NÃO | F72: NÃO OBRIGADA | G72: NÃO | H72: NÃO | I72: NÃO
A73: =A72+1 -> 71 | B73: 22109712000186 | C73: FORTALEZA COMERCIO E DISTRIBUICAO DE ALIMENTOS LTDA | D73: 45352 | E73: NÃO | F73: NÃO OBRIGADA | G73: NÃO | H73: NÃO | I73: NÃO
A74: =A73+1 -> 72 | B74: 28234202000117 | C74: FRIO TECNICO'S - PRESTACAO DE SERVICOS DE INSTALACAO DE AR CONDICIONADO LTDA | D74: 45383 | E74: NÃO | F74: NÃO OBRIGADA | G74: NÃO | H74: NÃO | I74: NÃO
A75: =A74+1 -> 73 | B75: 34974447000183 | C75: GARCIA KPP COMERCIO DE ALIMENTOS EIRELI (DONA MARICOTA) | D75: 45352 | E75: NÃO | F75: NÃO OBRIGADA | G75: NÃO | H75: NÃO | I75: NÃO
A76: =A75+1 -> 74 | B76: 36812937000109 | C76: GB CEILANDIA DISTRIBUICAO DE BEBIDAS LTDA | D76: 45383 | E76: NÃO | F76: NÃO OBRIGADA | G76: NÃO | H76: NÃO | I76: NÃO
A77: =A76+1 -> 75 | B77: 28071236000138 | C77: GC SILVA COMERCIO DE BEBIDAS 191DF EIRELI - MATRIZ | D77: 45383 | E77: NÃO | F77: NÃO OBRIGADA | G77: NÃO | H77: NÃO | I77: NÃO
A78: =A77+1 -> 76 | B78: 28071236000219 | C78: GC SILVA COMERCIO DE BEBIDAS 191DF EIRELI - GO | D78: SEM MOVIMENTO | E78: SEM MOVIMENTO | F78: SEM MOVIMENTO | G78: NÃO | H78: NÃO | I78: NÃO
A79: =A78+1 -> 77 | B79: 63315107000149 | C79: GEOINFRA ENGENHARIA LTDA | D79: 45383 | E79: NÃO | F79: NÃO OBRIGADA | G79: NÃO | H79: NÃO | I79: NÃO
A80: =A79+1 -> 78 | B80: 17063002000122 | C80: GESTAO CONTADORES LTDA | D80: SEM MOVIMENTO | E80: SEM MOVIMENTO | F80: SEM MOVIMENTO | G80: NÃO | H80: NÃO | I80: NÃO
A81: =A80+1 -> 79 | B81: 27072709000159 | C81: GK MEDICINE SERVICOS MEDICOS LTDA | D81: SEM MOVIMENTO | E81: SEM MOVIMENTO | F81: SEM MOVIMENTO | G81: NÃO | H81: NÃO | I81: NÃO
A82: =A81+1 -> 80 | B82: 53726610000133 | C82: GM BRASIL COMERCIO DE PRODUTOS OPTICOS LTDA | D82: 45323 | E82: NÃO | F82: NÃO OBRIGADA | G82: NÃO | H82: NÃO | I82: NÃO
A83: =A82+1 -> 81 | B83: 57670435000160 | C83: GPR SOFTWARE LTDA | D83: 45323 | E83: NÃO | F83: NÃO OBRIGADA | G83: NÃO | H83: SIM | I83: NÃO
A84: =A83+1 -> 82 | B84: 61166521000108 | C84: GRUPO IMS COMERCIO DE ALIMENTOS I LTDA (TEXAS BURGER) | D84: 45383 | E84: NÃO | F84: NÃO OBRIGADA | G84: NÃO | H84: NÃO | I84: NÃO
A85: =A84+1 -> 83 | B85: 61166503000126 | C85: GRUPO IMS COMERCIO DE ALIMENTOS II LTDA (TEXAS BURGER) | D85: 45383 | E85: NÃO | F85: NÃO OBRIGADA | G85: NÃO | H85: NÃO | I85: NÃO
A86: =A85+1 -> 84 | B86: 54447300000142 | C86: GRUPO MACEDO (TEXAS BURGER) | D86: 45383 | E86: NÃO | F86: NÃO OBRIGADA | G86: NÃO | H86: NÃO | I86: NÃO
A87: =A86+1 -> 85 | B87: 54447287000121 | C87: GRUPO MACEDO II (BEST BEEF) | D87: 45352 | E87: NÃO | F87: NÃO OBRIGADA | G87: NÃO | H87: NÃO | I87: NÃO
A88: =A87+1 -> 86 | B88: 54447285000132 | C88: GRUPO MACEDO III (BURGER MANIA) | D88: 45352 | E88: SIM | F88: NÃO OBRIGADA | G88: NÃO | H88: NÃO | I88: NÃO
A89: =A88+1 -> 87 | B89: 50900559000146 | C89: GS SCHILLING CONSULTORIA EM TECNOLOGIA LTDA | G89: NÃO | H89: NÃO | I89: NÃO
A90: =A89+1 -> 88 | B90: 36631894000165 | C90: IGREJA MINISTÉRIO NOVA VIDA | D90: 45383 | E90: SIM | F90: ENVIADA | G90: NÃO | H90: NÃO | I90: NÃO
A91: =A90+1 -> 89 | B91: 55038481000116 | C91: IMPACT ENGENHARIA E ENERGIA SOLAR LTDA | D91: 45383 | E91: SIM | F91: ENVIADA | G91: NÃO | H91: NÃO | I91: NÃO
A92: =A91+1 -> 90 | B92: 59084161000153 | C92: IMS COMÉRCIO DE ALIMENTOS III LTDA (CONGLOMERADO) | D92: 45323 | E92: NÃO | F92: NÃO OBRIGADA | G92: NÃO | H92: NÃO | I92: NÃO
A93: =A92+1 -> 91 | B93: 52077329000154 | C93: INAD STUDIO DE DANÇA E PILATES LTDA | D93: 45413 | E93: NÃO | F93: NÃO OBRIGADA | G93: NÃO | H93: NÃO | I93: NÃO
A94: =A93+1 -> 92 | B94: 42335238000118 | C94: INFO OFFICE BRASIL SERVICOS DE INFORMATICA E TECNOLOGIA LTDA | D94: 45352 | E94: NÃO | F94: NÃO OBRIGADA | G94: NÃO | H94: NÃO | I94: NÃO
A95: =A94+1 -> 93 | B95: 53313120000105 | C95: INOVA CONTRATAÇÕES E TREINAMENTOS LTDA | D95: 45352 | E95: NÃO | F95: NÃO OBRIGADA | G95: NÃO | H95: NÃO | I95: NÃO
A96: =A95+1 -> 94 | B96: 46711604000147 | C96: ITOPIMPORTS COMERCIO ELETRONICO LTDA | D96: SEM MOVIMENTO | E96: SEM MOVIMENTO | F96: SEM MOVIMENTO | G96: NÃO | H96: NÃO | I96: NÃO
A97: =A96+1 -> 95 | B97: 33440538000176 | C97: J. CRISTO OPTICAL DO BRASIL EIRELI | D97: 45352 | E97: NÃO | F97: NÃO OBRIGADA | G97: NÃO | H97: NÃO | I97: NÃO
A98: =A97+1 -> 96 | B98: 59397694000195 | C98: JG CONVENIENCIA E TABACARIA LTDA MG | D98: SEM MOVIMENTO | E98: SEM MOVIMENTO | F98: SEM MOVIMENTO | G98: NÃO | H98: NÃO | I98: NÃO
A99: =A98+1 -> 97 | B99: 571616000112 | C99: JG LANCHES LTDA | D99: 45352 | E99: NÃO | F99: NÃO OBRIGADA | G99: NÃO | H99: NÃO | I99: NÃO
A100: =A99+1 -> 98 | B100: 43094426000164 | C100: JL ODONTOLOGIA PERSONALIZADA LTDA | D100: 45352 | E100: NÃO | F100: NÃO OBRIGADA | G100: NÃO | H100: NÃO | I100: NÃO
A101: =A100+1 -> 99 | B101: 59065282000158 | C101: JM COSMÉTICOS E ACESSÓRIOS LTDA | D101: 45444 | G101: NÃO | H101: NÃO | I101: NÃO
A102: =A101+1 -> 100 | B102: 44348652000197 | C102: JUNIOR CONSULTORIA EM TECNOLOGIA LTDA | D102: 45323 | E102: NÃO | F102: NÃO OBRIGADA | G102: NÃO | H102: NÃO | I102: NÃO
A103: =A102+1 -> 101 | B103: 52412559000122 | C103: KAKTOS CONSULTÓRIOS COLABORATIVOS LTDA | D103: SEM MOVIMENTO | E103: SEM MOVIMENTO | F103: SEM MOVIMENTO | G103: NÃO | H103: NÃO | I103: NÃO
A104: =A103+1 -> 102 | B104: 20021254000101 | C104: KAROLLINE A. DE MELO | D104: 45352 | E104: NÃO | F104: NÃO OBRIGADA | G104: NÃO | H104: NÃO | I104: NÃO
A105: =A104+1 -> 103 | B105: 11156374000117 | C105: KAYA RESTAURANTE LTDA | D105: 45323 | E105: NÃO | F105: NÃO OBRIGADA | G105: NÃO | H105: NÃO | I105: NÃO
...

Sheet ECD E ECF 2024
B2: CNPJ | C2: EMPRESAS | D2: ECD | E2: DATA ENVIO ECD | F2: ECF | G2: DATA ENVIO ECF
A3: 1 | B3: 28523040000137 | C3: 180X NEGOCIOS DIGITAIS LTDA (555) | D3: ENVIADA | E3: 45779 | F3: ENVIADA | G3: 45846
A4: 1 | B4: 53114412000119 | C4: 3.6 ESPORTE E SAÚDE LTDA (130) | D4: ENVIADA | E4: 45779 | F4: ENVIADA | G4: 45846
B5: 52613816000194 | C5: 3.5 ESPORTE E SAÚDE LTDA | D5: SEM MOVIMENTO | E5: - | F5: SEM MOVIMENTO | G5: -
A6: 1 | B6: 57.407.089/0001-22 | C6: ACADEMIA CEILANDIA ESPORTE SAUDE LTDA (195) | D6: ENVIADA | E6: 45782 | F6: ENVIADA | G6: 45846
A7: 1 | B7: 43798918000130 | C7: AG COMERCIO E MERCEARIA LTDA (408) | D7: ENVIADA | E7: 45758 | F7: ENVIADA | G7: 45848
B8: 7462754000102 | C8: ASA NORTE BURGER COMÉRCIO DE ALIMENTOS LTDA (92) | D8: ENVIADA | E8: 45789 | F8: ENVIADA | G8: 45848
A9: 1 | B9: 686261000107 | C9: ASMRE ASSOC DOS SERV DO MIN DAS REL EXTERIORES (409) | D9: ENVIADA | E9: 45699 | F9: ENVIADA | G9: 45848
A10: 1 | B10: 20720905000143 | C10: BENENUTRI COMERCIAL LTDA (DF) (4) | D10: ENVIADA | E10: 45748 | F10: ENVIADA | G10: 45849
A11: 1 | B11: 20720905000243 | C11: BENENUTRI COMERCIAL LTDA (GO) (7) | D11: ENVIADA | E11: 45748 | F11: ENVIADA | G11: 45849
A12: 1 | B12: 20.720.905/0003-05 | C12: BENENUTRI COMERCIAL LTDA (RS) (168) | D12: ENVIADA | E12: 45748 | F12: ENVIADA | G12: 45849
A13: 1 | B13: 50605321000198 | C13: BILLY BYTE SOLUÇÕES LTDA (76) | D13: ENVIADA | E13: 45698 | F13: ENVIADA | G13: 45848
A14: 1 | B14: 42863955000112 | C14: BN EXPRESS I COMÉRCIO E SERVIÇOS LTDA (DF) (400) | D14: ENVIADA | E14: 45686 | F14: ENVIADA | G14: 45846
A15: 1 | B15: 44891225000150 | C15: BN EXPRESS II COMÉRCIO E SERVIÇOS LTDA (DF) (427) | D15: ENVIADA | E15: 45749 | F15: ENVIADA | G15: 45849
A16: 1 | B16: 33013866000196 | C16: BSBURGER COMERCIO DE ALIMENTOS LTDA (117) | D16: ENVIADA | E16: 45786 | F16: ENVIADA | G16: 45848
A17: 1 | B17: 3469819600151 | C17: CENTRO DE MEDICINA DE FAMILIA DE BRASILIA LTDA (135) | D17: ENVIADA | E17: 45779 | F17: ENVIADA | G17: 45846
A18: 1 | B18: 22855971000156 | C18: CENTRO DE NEFROLOGIA DO DISTRITO FEDERAL LTDA (104) | D18: ENVIADA | E18: 45779 | F18: ENVIADA | G18: 45846
A19: 1 | B19: 41631955000124 | C19: CLINICA ODONTOLOGICA ALMEIDA LTDA (OPTIMA) (67) | D19: ENVIADA | E19: 45782 | F19: ENVIADA | G19: 45848
A20: 1 | B20: 36599674000100 | C20: EMPORIO DIVA COMERCIO DE PRODUTOS DE BELEZA EIRELI (11) | D20: ENVIADA | E20: 45800 | F20: ENVIADA | G20: 45846
A21: 1 | B21: 56.932.805-0001/28 | C21: FEO TECNOLOGIA LTDA (185) | D21: ENVIADA | E21: 45702 | F21: ENVIADA | G21: 45848
A22: 1 | B22: 57.670.435/0001-60 | C22: GPR SOFTWARE LTDA | D22: ENVIADA | E22: 45692 | F22: ENVIADA | G22: 45848
A23: 1 | B23: 29511026000186 | C23: IBEX COMERCIAL DE ALIMENTOS LTDA - DF (5) | D23: ENVIADA | E23: 45687 | F23: ENVIADA | G23: 45846
A24: 1 | B24: 29511026000267 | C24: IBEX COMERCIAL DE ALIMENTOS LTDA - GO (6) | D24: ENVIADA | E24: 45687 | F24: ENVIADA | G24: 45846
B25: 36631894000165 | C25: IGREJA MINISTÉRIO NOVA VIDA | D25: SEM MOVIMENTO | E25: - | F25: SEM MOVIMENTO | G25: -
A26: 1 | B26: 43094426000164 | C26: JL ODONTOLOGIA PERSONALIZADA LTDA (164) | D26: ENVIADA | E26: 45782 | F26: ENVIADA | G26: 45848
A27: 1 | B27: 51467621000110 | C27: KLINGER ENGENHARIA LTDA (70) | D27: ENVIADA | E27: 45699 | F27: ENVIADA | G27: 45849
A28: 1 | B28: 34084938000159 | C28: LA BAMBA INDUSTRIA DE SORVETES EIRELI (127) | D28: ENVIADA | E28: 45761 | F28: ENVIADA | G28: 45849
A29: 1 | B29: 53134576000108 | C29: LIVE 3.4 PERSONAL LTDA (139) | D29: ENVIADA | E29: 45782 | F29: ENVIADA | G29: 45848
A30: 1 | B30: 14433426000143 | C30: LOCAR ENGENHARIA LTDA ME (48) | D30: ENVIADA | E30: 45782 | F30: ENVIADA | G30: 45849
A31: 1 | B31: 55.936.097/0001-30 | C31: MEATZ BURGER BURITIS DUE COMERCIO DE ALIMENTOS (173) | D31: ENVIADA | E31: 45805 | F31: ENVIADA | G31: 45852
A32: 1 | B32: 32648600000157 | C32: MEATZ BURGER CASTELO COMERCIO DE ALIMENTOS LTDA (378) | D32: ENVIADA | E32: 45790 | F32: ENVIADA | G32: 45852
A33: 1 | B33: 55.397.331/0001-07 | C33: MEATZ BURGER CENTRO SUL DUE COMERCIO DE ALIMENTOS LTDA (163) | D33: ENVIADA | E33: 45805 | F33: ENVIADA | G33: 45852
A34: 1 | B34: 55.936.396/0001-75 | C34: MEATZ BURGER CIDADE NOVA DUE COMERCIO DE ALIMENTOS (172) | D34: ENVIADA | E34: 45805 | F34: ENVIADA | G34: 45852
A35: 1 | B35: 55.686.606/0001-14 | C35: MEATZ BURGER CONTAGEM DUE (167) | D35: ENVIADA | E35: 45805 | F35: ENVIADA | G35: 45852
A36: 1 | B36: 28120242000138 | C36: MEATZ BURITIS HAMBURGUERIA (77) ANTIGA P E C COMERCIO | D36: ENVIADA | E36: 45811 | F36: ENVIADA | G36: 45852
A37: 1 | B37: 47133237000104 | C37: MEATZ CASTELO HAMBURGUERIA (551) ANTIGA ASA NORTE DUE | D37: ENVIADA | E37: 45810 | F37: ENVIADA | G37: 45852
A38: 1 | B38: 39752648000150 | C38: MEATZ P & C DUE COMERCIO DE ALIMENTOS LTDA (56) | D38: ENVIADA | E38: 45777 | F38: ENVIADA | G38: 45852
B39: 24455157000170 | C39: MARIA EDILEUZA GUIMARÃES OLIVEIRA (47) | D39: SEM MOVIMENTO | F39: SEM MOVIMENTO | G39: -
A40: 1 | B40: 39.752.648/0002-30 | C40: MEATZ P & C DUE COMERCIO DE ALIMENTOS LTDA FILIAL (186) | D40: ENVIADA | E40: 45777 | F40: ENVIADA | G40: 45852
A41: 1 | B41: 358589000139 | C41: OBRA ORGANIZAÇÃO BRASILIENSE DE CONSTRUÇÃO LTDA (36) | D41: ENVIADA | E41: 45755 | F41: ENVIADA | G41: 45852
A42: 1 | B42: 16872154000103 | C42: OITENTA FILMES LTDA (566) | D42: ENVIADA | E42: 45757 | F42: ENVIADA | G42: 45852
B43: 27072709000159 | C43: GK MEDICINE SERVICOS MEDICOS LTDA (513) | D43: ENVIADA | E43: 45832 | F43: ENVIADA | G43: 45848
B44: 35725797000179 | C44: F.B SANTOS GESTÃO E ADMINISTRAÇÃO IMOBILIARIA (22) | D44: ENVIADA | E44: 45834 | F44: ENVIADA | G44: 45848
B45: 24314151000182 | C45: PEU CONSULTORIA EM PUBLICIDADE LTDA | D45: ENVIADA | E45: 45832 | F45: ENVIADA | G45: 45852
B46: 47130092000198 | C46: MEATZ CONTAGEM HAMBURGUERIA ANTIGA SW DUE | D46: ENVIADA | E46: 45832 | F46: ENVIADA | G46: 45847
B47: 38113906000195 | C47: MEATZ GYN BURGER COMERCIO DE ALIMENTOS LTDA | D47: ENVIADA | E47: 45832 | F47: ENVIADA | G47: 45847
B48: 57138578000126 | C48: GYN BURGER DUE COMERCIO DE ALIMENTOS LTDA | D48: ENVIADA | E48: 45834 | F48: ENVIADA | G48: 45847
B49: 29936130000112 | C49: MEATZ CIDADE NOVA HAMBURGUERIA (ANTIGA WPC COMERCIO) | D49: ENVIADA | E49: 45832 | F49: ENVIADA | G49: 45848
B50: 24773977000100 | C50: MEATZ CENTRO SUL HAMBURGUERIA (ANTIGA AGUAS CLARAS) | D50: ENVIADA | E50: 45832 | F50: ENVIADA | G50: 45847
B51: 24187519000199 | C51: M.A COMERCIO E DISTRIBUICAO DE ALIMENTOS | D51: SEM MOVIMENTO | F51: SEM MOVIMENTO | G51: -
B52: 9440175000194 | C52: E. DO CARMO DA SILVA - CHIQUE BIJOUX | D52: ENVIADA | E52: 45832 | F52: ENVIADA | G52: 45852
A53: 1 | B53: 22.160.231/0001-03 | C53: PAMONHA VERDE LTDA (187) | D53: ENVIADA | E53: 45810 | F53: ENVIADA | G53: 45852
A54: 1 | B54: 18135832000180 | C54: PAULO PEREIRA LAUREANO DA SILVA | D54: ENVIADA | E54: 45439 | F54: ENVIADA | G54: 45849
A55: 1 | B55: 9339178000136 | C55: QI AGENCIA, SERVICOS E INCENTIVOS A VENDAS LTDA (58) | D55: ENVIADA | E55: 45800 | F55: ENVIADA | G55: NOVO CONTADOR
A56: 1 | B56: 42359555000174 | C56: RESENHA CONVENIENCIA LTDA (530) | D56: ENVIADA | E56: 45758 | F56: ENVIADA | G56: 45852
A57: 1 | B57: 29946991000181 | C57: SW BURGER COMERCIO LTDA (SUDOESTE) (94) | D57: ENVIADA | E57: 45804 | F57: ENVIADA | G57: 45848
A58: 1 | B58: 40188984000109 | C58: WPC DUE COMERCIO DE ALIMENTOS LTDA (60) | D58: ENVIADA | E58: 45804 | F58: ENVIADA | G58: 45848
A59: 1 | B59: 38287080000180 | C59: WSS NEGOCIOS DIGITAIS LTDA (200) | D59: ENVIADA | E59: 45757 | F59: ENVIADA | G59: 45849
A60: 1 | B60: 41231672000195 | C60: WWC TECNOLOGIA LTDA (89) | D60: ENVIADA | E60: 45803 | F60: ENVIADA | G60: 45849
A61: 1 | B61: 9205914000163 | C61: ZMC SANDRI GESTAO EMPRESARIAL E REPRESENTACOES EIRELI (356) | D61: ENVIADA | E61: 45750 | F61: ENVIADA | G61: 45848

Sheet REINF 2025 BASE
B2: CNPJ | C2: FECHAMENTO | D2: EMPRESA | E2: REGIME | F2: RESPONSÁVEL | G2: ESCRITURAÇÃO ATÉ | H2: 1° TRIMESTRE | I2: 2° TRIMESTRE | J2: 3° TRIMESTRE | K2: 4° TRIMESTRE
B3: 51798642000119 | C3: BANCO | D3: ANHANGUERA UNAÍ EDUCAÇÃO LTDA (72) | E3: SIMPLES NACIONAL | F3: INGRID | G3: 45627 | H3: NÃO | I3: NÃO | J3: NÃO | K3: NÃO
B4: 33154864000117 | C4: BANCO | D4: AO QUADRADO FABRICAÇAO PROPRIA DE PRODUTOS ALIMENTICIOS LTDA (425) | E4: SIMPLES NACIONAL | F4: INGRID | G4: 45627 | H4: NÃO | I4: NÃO | J4: NÃO | K4: NÃO
B5: 58.952.972/0001-66 | C5: BANCO | D5: BARUK COMERCIO E DISTRIBUIÇÃO DE ALIMENTOS LTDA | E5: SIMPLES NACIONAL | F5: INGRID | G5: 45627 | H5: NÃO | I5: NÃO | J5: NÃO | K5: NÃO
B6: 42863955000112 | C6: BANCO | D6: BN EXPRESS I COMÉRCIO E SERVIÇOS LTDA (TO) (400) | E6: SIMPLES NACIONAL | F6: INGRID | G6: 45627 | H6: NÃO | I6: NÃO | J6: NÃO | K6: NÃO
B7: 22614874000333 | C7: BANCO | D7: CADEIRAS DESIGN LTDA (FILIAL) (211) | E7: SIMPLES NACIONAL | F7: INGRID | G7: 45627 | H7: NÃO | I7: NÃO | J7: NÃO | K7: NÃO
B8: 22614874000171 | C8: BANCO | D8: CADEIRAS DESIGN LTDA (MATRIZ) (210) | E8: SIMPLES NACIONAL | F8: INGRID | G8: 45627 | H8: NÃO | I8: NÃO | J8: NÃO | K8: NÃO
B9: 28.527.486/0001-30 | C9: BANCO | D9: CADEIRAS DESIGN.COM LTDA (214) | E9: SIMPLES NACIONAL | F9: INGRID | G9: 45627 | H9: NÃO | I9: NÃO | J9: NÃO | K9: NÃO
B10: 33612605000192 | C10: BANCO | D10: CLIMA GESTAO DE PESSOAS LTDA (401) | E10: SIMPLES NACIONAL | F10: INGRID | G10: 45627 | H10: NÃO | I10: NÃO | J10: NÃO | K10: NÃO
B11: 56.225.975/0001-72 | C11: BANCO | D11: MA ENGENHARIA E CONSULTORIA LTDA (174) | E11: SIMPLES NACIONAL | F11: INGRID | G11: 45627 | H11: NÃO | I11: NÃO | J11: NÃO | K11: NÃO
B12: 55.329.921/0001-94 | C12: BANCO | D12: FAST LOCAÇÕES LTDA (162) | E12: SIMPLES NACIONAL | F12: INGRID | G12: 45627 | H12: NÃO | I12: NÃO | J12: NÃO | K12: NÃO
B13: 59.319.900/0001-49 | C13: BPO | D13: LAGO HAMBURGUERIA COMERCIO DE ALIMENTOS LTDA (217) | E13: SIMPLES NACIONAL | F13: INGRID | G13: 45627 | H13: NÃO | I13: NÃO | J13: NÃO | K13: NÃO
B14: 19890822000113 | C14: BANCO | D14: LEASTRO CONSULTORIA LTDA (175) | E14: SIMPLES NACIONAL | F14: INGRID | G14: 45627 | H14: NÃO | I14: NÃO | J14: NÃO | K14: NÃO
B15: 55.824.679/0001-25 | C15: BANCO | D15: CLINICA BIOPELLE SERVIÇOS MÉDICOS LTDA (170) | E15: SIMPLES NACIONAL | F15: INGRID | G15: 45627 | H15: NÃO | I15: NÃO | J15: NÃO | K15: NÃO
B16: 40566970000173 | C16: BANCO | D16: MAIS SERVICOS DE ENGENHARIA LTDA (52) | E16: SIMPLES NACIONAL | F16: INGRID | G16: 45627 | H16: NÃO | I16: NÃO | J16: NÃO | K16: NÃO
B17: 35016496000176 | C17: BPO | D17: MEATZ BARRA BURGER COMÉRCIO DE ALIMENTOS EIRELI (383) | E17: SIMPLES NACIONAL | F17: INGRID | G17: 45627 | H17: NÃO | I17: NÃO | J17: NÃO | K17: NÃO
B18: 51904701000196 | C18: BPO | D18: MEATZ BOTAFOGO BURGER COMERCIAL DE ALIMENTOS LTDA (85) | E18: SIMPLES NACIONAL | F18: INGRID | G18: 45627 | H18: NÃO | I18: NÃO | J18: NÃO | K18: NÃO
B19: 56425581000168 | C19: BPO | D19: MEATZ BURGER AGUAS CLARAS COMERCIO DE ALIMENTO (181) | E19: SIMPLES NACIONAL | F19: INGRID | G19: 45627 | H19: NÃO | I19: NÃO | J19: NÃO | K19: NÃO
B20: 24773977000100 | C20: BPO | D20: MEATZ BURGER CENTRO SUL HAMBURGUERIA (50) (ANTIGA AGUAS CLARAS) | E20: SIMPLES NACIONAL | F20: INGRID | G20: 45627 | H20: NÃO | I20: NÃO | J20: NÃO | K20: NÃO
B21: 38831586000109 | C21: BPO | D21: MEATZ CEILANDIA BURGER COMERCIO DE ALIMENTOS LTDA (351) | E21: SIMPLES NACIONAL | F21: INGRID | G21: 45627 | H21: NÃO | I21: NÃO | J21: NÃO | K21: NÃO
B22: 47130092000198 | C22: BPO | D22: MEATZ CONTAGEM HAMBURGUERIA (549) ANTIGA SW DUE | E22: SIMPLES NACIONAL | F22: INGRID | G22: 45627 | H22: NÃO | I22: NÃO | J22: NÃO | K22: NÃO
B23: 38113906000195 | C23: BPO | D23: MEATZ GYN BURGER COMERCIO DE ALIMENTOS LTDA (51) | E23: SIMPLES NACIONAL | F23: INGRID | G23: 45627 | H23: NÃO | I23: NÃO | J23: NÃO | K23: NÃO
B24: 56.423.955/0001-06 | C24: BPO | D24: MEATZ SW COMERCIO DE ALIMENTOS LTDA (182) | E24: SIMPLES NACIONAL | F24: INGRID | G24: 45627 | H24: NÃO | I24: NÃO | J24: NÃO | K24: NÃO
B25: 52004246000135 | C25: BPO | D25: MEATZ TIJUCA BURGER COMERCIAL DE ALIMENTOS LTDA (83) | E25: SIMPLES NACIONAL | F25: INGRID | G25: 45627 | H25: NÃO | I25: NÃO | J25: NÃO | K25: NÃO
B26: 56504105000132 | C26: BPO | D26: MEATZ WPC BURGER COMERCIO DE ALIMENTOS EIRELI (GUARA) (179) | E26: SIMPLES NACIONAL | F26: INGRID | G26: 45627 | H26: NÃO | I26: NÃO | J26: NÃO | K26: NÃO
B27: 57.544.316/0001-61 | C27: BANCO | D27: P & D COMERCIO E SERVICOS LTDA (193) | E27: SIMPLES NACIONAL | F27: INGRID | G27: 45627 | H27: NÃO | I27: NÃO | J27: NÃO | K27: NÃO
B28: 59.765.765/0001-65 | C28: BANCO | D28: PANIFICADORA E CONFEITARIA PRIMAVERA LTDA (221) | E28: SIMPLES NACIONAL | F28: INGRID | G28: 45627 | H28: NÃO | I28: NÃO | J28: NÃO | K28: NÃO
B29: 40441837000190 | C29: BANCO | D29: PLINOVAIS SERVICOS MEDICOS LTDA (57) | E29: SIMPLES NACIONAL | F29: INGRID | G29: 45627 | H29: NÃO | I29: NÃO | J29: NÃO | K29: NÃO
B30: 41399883000131 | C30: BANCO | D30: PRECISAO SERVICOS DE ENGENHARIA LTDA (69) | E30: SIMPLES NACIONAL | F30: INGRID | G30: 45627 | H30: NÃO | I30: NÃO | J30: NÃO | K30: NÃO
B31: 47416372000167 | C31: BANCO | D31: QUADRATURE CONSULTORIA EM TECNOLOGIA LTDA (558) | E31: SIMPLES NACIONAL | F31: INGRID | G31: 45627 | H31: NÃO | I31: NÃO | J31: NÃO | K31: NÃO
B32: 40669598000120 | C32: BANCO | D32: REALIZE ENGENHARIA DF LTDA (204) | E32: SIMPLES NACIONAL | F32: INGRID | G32: 45627 | H32: NÃO | I32: NÃO | J32: NÃO | K32: NÃO
B33: 60.080.888/0001-41 | C33: BANCO | D33: RESTAURANTE BAHEA COZINHA BAIANA LTDA (224) | E33: SIMPLES NACIONAL | F33: INGRID | G33: 45627 | H33: NÃO | I33: NÃO | J33: NÃO | K33: NÃO
B34: 28523040000137 | C34: CAIXA | D34: 180X NEGOCIOS DIGITAIS LTDA (555) | E34: LUCRO PRESUMIDO | F34: INGRID | G34: 45444 | H34: NÃO | I34: NÃO | J34: NÃO | K34: NÃO
B35: 43798918000130 | C35: BANCO | D35: AG COMERCIO E MERCEARIA LTDA (408) | F35: KELVIN | G35: 45627 | H35: NÃO | I35: NÃO | J35: NÃO | K35: NÃO
B36: 686261000107 | C36: BANCO | D36: ASMRE ASSOC DOS SERV DO MIN DAS REL EXTERIORES (409) | F36: KELVIN | G36: 45627 | H36: NÃO | I36: NÃO | J36: NÃO | K36: NÃO
B37: 20720905000143 | C37: BANCO | D37: BENENUTRI COMERCIAL LTDA (DF) (4) | E37: LUCRO PRESUMIDO | F37: KELVIN | G37: 45901 | H37: SIM | I37: SIM | J37: SIM | K37: NÃO
B38: 20720905000224 | C38: BANCO | D38: BENENUTRI COMERCIAL LTDA (GO) (7) | E38: LUCRO PRESUMIDO | F38: KELVIN | G38: 45901 | H38: SIM | I38: SIM | J38: SIM | K38: NÃO
B39: 20.720.905/0003-05 | C39: BANCO | D39: BENENUTRI COMERCIAL LTDA (RS) (168) | E39: LUCRO PRESUMIDO | F39: KELVIN | G39: 45901 | H39: SIM | I39: SIM | J39: SIM | K39: NÃO
B40: 44891225000150 | C40: BANCO | D40: BN EXPRESS II COMÉRCIO E SERVIÇOS LTDA (DF) (427) | E40: LUCRO PRESUMIDO | F40: KELVIN | G40: 45901 | H40: SIM | I40: SIM | J40: SIM | K40: NÃO
B41: 50605321000198 | C41: CAIXA | D41: BILLY BYTE SOLUÇÕES LTDA (76) | E41: LUCRO PRESUMIDO | F41: KELVIN | G41: 45901 | H41: SIM | I41: SIM | J41: SIM | K41: NÃO
B42: 48.484.094/0001-48 | C42: BPO | D42: BRASIL VERDE COMÉRCIO VAREJISTA E ATACADISTA DE PAMONHAS LTDA (188) | F42: KELVIN | G42: 45627 | H42: NÃO | I42: NÃO | J42: NÃO | K42: NÃO
B43: 29682133000177 | C43: BPO | D43: CADEIRAS DESIGN SHOPPING ID LTDA (215) | F43: KELVIN | G43: 45627 | H43: NÃO | I43: NÃO | J43: NÃO | K43: NÃO
B44: 41631955000124 | C44: BANCO | D44: CLINICA ODONTOLOGICA ALMEIDA LTDA (OPTIMA) (67) | E44: LUCRO PRESUMIDO | F44: KELVIN | G44: 45901 | H44: SIM | I44: SIM | J44: SIM | K44: NÃO
B45: 34698196000151 | C45: BANCO | D45: CENTRO DE MEDICINA DE FAMILIA DE BRASILIA LTDA (135) | E45: LUCRO PRESUMIDO | F45: INGRID | G45: 45901 | H45: SIM | I45: SIM | J45: SIM | K45: NÃO
B46: 22855971000156 | C46: BANCO | D46: CENTRO DE NEFROLOGIA DO DISTRITO FEDERAL LTDA (104) | E46: LUCRO PRESUMIDO | F46: INGRID | G46: 45901 | H46: SIM | I46: SIM | J46: SIM | K46: NÃO
B47: 56932805000128 | C47: BANCO | D47: FEO TECNOLOGIA LTDA (185) | E47: LUCRO PRESUMIDO | F47: KELVIN | G47: 45901 | H47: SIM | I47: SIM | J47: SIM | K47: NÃO
B48: 29109712000186 | C48: BANCO | D48: FORTALEZA COMERCIO E DISTRIBUICAO DE ALIMENTOS LTDA (30) | F48: KELVIN | G48: 45627 | H48: NÃO | I48: NÃO | J48: NÃO | K48: NÃO
B49: 36599674000100 | C49: CAIXA | D49: EMPORIO DIVA COMERCIO DE PRODUTOS DE BELEZA EIRELI (11) | E49: LUCRO PRESUMIDO | F49: INGRID | G49: 45444 | H49: NÃO | I49: NÃO | J49: NÃO | K49: NÃO
B50: 27072709000159 | C50: CAIXA | D50: GK MEDICINE SERVICOS MEDICOS LTDA (513) | E50: LUCRO PRESUMIDO | F50: INGRID | G50: 45261 | H50: NÃO | I50: NÃO | J50: NÃO | K50: NÃO
B51: 36631894000165 | C51: CAIXA | D51: IGREJA MINISTÉRIO NOVA VIDA (152) | E51: LUCRO PRESUMIDO | F51: INGRID | G51: 45261 | H51: NÃO | I51: NÃO | J51: NÃO | K51: NÃO
B52: 53134576000108 | C52: CAIXA | D52: LIVE 3.4 PERSONAL LTDA (139) | E52: LUCRO PRESUMIDO | F52: INGRID | G52: 45413 | H52: NÃO | I52: NÃO | J52: NÃO | K52: NÃO
B53: 57670435000160 | C53: BANCO | D53: GPR SOFTWARE LTDA (196) | E53: LUCRO PRESUMIDO | F53: KELVIN | G53: 45901 | H53: SIM | I53: SIM | J53: SIM | K53: NÃO
B54: 51467621000110 | C54: BANCO | D54: KLINGER ENGENHARIA LTDA (70) | E54: SIMPLES NACIONAL | F54: KELVIN | G54: 45901 | H54: SIM | I54: SIM | J54: SIM | K54: NÃO
B55: 34084938000159 | C55: BANCO | D55: LA BAMBA INDUSTRIA DE SORVETES EIRELI (127) | F55: KELVIN | G55: 45627 | H55: NÃO | I55: NÃO | J55: NÃO | K55: NÃO
B56: 24187519000199 | C56: CAIXA | D56: M.A COMERCIO E DISTRIBUICAO DE ALIMENTOS (44) | E56: LUCRO PRESUMIDO | F56: INGRID | G56: 45261 | H56: NÃO | I56: NÃO | J56: NÃO | K56: NÃO
B57: 46231380000176 | C57: BPO | D57: LIS REFEIÇÕES COMÉRCIO DE ALIMENTOS LTDA (523) | F57: KELVIN | G57: 45627 | H57: NÃO | I57: NÃO | J57: NÃO | K57: NÃO
B58: 31687088000195 | C58: BANCO | D58: LLIK COMERCIO DE ACESSORIOS E COSMETICOS LTDA (317) | E58: SIMPLES NACIONAL | F58: KELVIN | G58: 45901 | H58: SIM | I58: SIM | J58: SIM | K58: NÃO
B59: 54184472000170 | C59: BANCO | D59: LLIK SECOND COMERCIO DE ACESSORIOS E COSMETICOS LTDA (203) | F59: KELVIN | G59: 45627 | H59: NÃO | I59: NÃO | J59: NÃO | K59: NÃO
B60: 7462754000102 | C60: BPO | D60: MEATZ ASA NORTE BURGER COMÉRCIO DE ALIMENTOS LTDA (92) | F60: KELVIN | G60: 45627 | H60: NÃO | I60: NÃO | J60: NÃO | K60: NÃO
B61: 36100604000157 | C61: CAIXA | D61: PARK BURGER COMERCIAL DE ALIMENTOS LTDA (15) | E61: LUCRO PRESUMIDO | F61: INGRID | G61: 45261 | H61: NÃO | I61: NÃO | J61: NÃO | K61: NÃO
B62: 33013866000196 | C62: BPO | D62: MEATZ BSBURGER COMERCIO DE ALIMENTOS LTDA (117) | E62: LUCRO PRESUMIDO | F62: KELVIN | G62: 45901 | H62: SIM | I62: SIM | J62: SIM | K62: NÃO
B63: 30046927000123 | C63: BPO | D63: MEATZ BURGER BURITIS COMERCIO DE ALIMENTOS LTDA (379) | F63: KELVIN | G63: 45627 | H63: NÃO | I63: NÃO | J63: NÃO | K63: NÃO
B64: 41399883000131 | C64: BANCO | D64: PRECISAO SERVICOS DE ENGENHARIA LTDA (69) | E64: SIMPLES NACIONAL | F64: INGRID | G64: 45627 | H64: NÃO | I64: NÃO | J64: SIM | K64: SIM
B65: 32648600000157 | C65: BPO | D65: MEATZ BURGER CASTELO COMERCIO DE ALIMENTOS LTDA (378) | F65: KELVIN | G65: 45627 | H65: NÃO | I65: NÃO | J65: NÃO | K65: NÃO
B66: 55.657.116/0001-90 | C66: BPO | D66: MEATZ BURGER CASTELO DUE (166) | F66: KELVIN | G66: 45627 | H66: NÃO | I66: NÃO | J66: NÃO | K66: NÃO
B67: 29946991000181 | C67: CAIXA | D67: SW BURGER COMERCIO LTDA (SUDOESTE) (94) | E67: LUCRO PRESUMIDO | F67: INGRID | G67: 45901 | H67: SIM | I67: SIM | J67: SIM | K67: NÃO
B68: 40188984000109 | C68: CAIXA | D68: WPC DUE COMERCIO DE ALIMENTOS LTDA (60) | E68: LUCRO PRESUMIDO | F68: INGRID | G68: 45901 | H68: SIM | I68: SIM | J68: SIM | K68: NÃO
B69: 28347784000229 | C69: BPO | D69: MEATZ BURGER CENTRO SUL COMERCIO DE ALIMENTOS LTDA - FILIAL (386) | F69: KELVIN | G69: 45627 | H69: NÃO | I69: NÃO | J69: NÃO | K69: NÃO
B70: 28347784000148 | C70: BPO | D70: MEATZ BURGER CENTRO SUL COMERCIO DE ALIMENTOS LTDA - MATRIZ (380) | F70: KELVIN | G70: 45627 | H70: NÃO | I70: NÃO | J70: NÃO | K70: NÃO
B71: 35027019000106 | C71: BPO | D71: MEATZ BURGER CIDADE NOVA COMERCIO DE ALIMENTOS LTDA (377) | F71: KELVIN | G71: 45627 | H71: NÃO | I71: NÃO | J71: NÃO | K71: NÃO
B72: 38225461000135 | C72: BPO | D72: MEATZ BURGER CONTAGEM COMERCIO DE ALIMENTOS LTDA (376) | F72: KELVIN | G72: 45627 | H72: NÃO | I72: NÃO | J72: NÃO | K72: NÃO
B73: 58139555000107 | C73: BPO | D73: MEATZ BURGER PAMPULHA COMERCIO DE ALIMENTOS LTDA (197) | F73: KELVIN | G73: 45627 | H73: NÃO | I73: NÃO | J73: NÃO | K73: NÃO
B74: 28120242000138 | C74: BPO | D74: MEATZ BURITIS HAMBURGUERIA (77) ANTIGA P E C COMERCIO | F74: KELVIN | G74: 45627 | H74: NÃO | I74: NÃO | J74: NÃO | K74: NÃO
B75: 47133237000104 | C75: BPO | D75: MEATZ CASTELO HAMBURGUERIA (551) ANTIGA ASA NORTE DUE | F75: KELVIN | G75: 45627 | H75: NÃO | I75: NÃO | J75: NÃO | K75: NÃO
B76: 37.472.128/0001-68 | C76: BPO | D76: MEATZ MWPC BURGER COMERCIO DE ALIMENTOS LTDA (176) | F76: KELVIN | G76: 45627 | H76: NÃO | I76: NÃO | J76: NÃO | K76: NÃO
B77: 56.418.678/0001-43 | C77: BPO | D77: MEATZ NORTE BURGER COMERCIO DE ALIMENTOS LTDA (180) | F77: KELVIN | G77: 45627 | H77: NÃO | I77: NÃO | J77: NÃO | K77: NÃO
B78: 55172071000163 | C78: BPO | D78: MEATZ P & C BURGER (161) ANTIGA LAGO BURGER | F78: KELVIN | G78: 45627 | H78: NÃO | I78: NÃO | J78: NÃO | K78: NÃO
B79: 39752648000150 | C79: BPO | D79: MEATZ P & C DUE COMERCIO DE ALIMENTOS LTDA (56) | E79: LUCRO PRESUMIDO | F79: KELVIN | G79: 45901 | H79: SIM | I79: SIM | J79: SIM | K79: NÃO
B80: 39.752.648/0002-30 | C80: BPO | D80: MEATZ P & C DUE COMERCIO DE ALIMENTOS LTDA FILIAL (186) | E80: LUCRO PRESUMIDO | F80: KELVIN | G80: 45901 | H80: SIM | I80: SIM | J80: SIM | K80: NÃO
B81: 41484228000181 | C81: BANCO | D81: MORAIS BRANCO PRODUTOS FARMACEUTICOS LTDA (353) | E81: SIMPLES NACIONAL | F81: KELVIN | G81: 45901 | H81: SIM | I81: SIM | J81: SIM | K81: NÃO
B82: 358589000139 | C82: BANCO | D82: OBRA ORGANIZAÇÃO BRASILIENSE DE CONSTRUÇÃO LTDA (36) | E82: LUCRO PRESUMIDO | F82: KELVIN | G82: 45901 | H82: SIM | I82: SIM | J82: SIM | K82: NÃO
B83: 16872154000103 | C83: BANCO | D83: OITENTA FILMES LTDA (566) | E83: LUCRO PRESUMIDO | F83: KELVIN | G83: 45901 | H83: SIM | I83: SIM | J83: SIM | K83: NÃO
B84: 22.160.231/0001-03 | C84: BPO | D84: PAMONHA VERDE LTDA (187) | E84: LUCRO PRESUMIDO | F84: KELVIN | G84: 45627 | H84: NÃO | I84: NÃO | J84: NÃO | K84: NÃO
B85: 56414768000166 | C85: BANCO | D85: PLURIBYTE SOLUTIONS (190) | E85: LUCRO PRESUMIDO | F85: KELVIN | G85: 45901 | H85: SIM | I85: SIM | J85: SIM | K85: NÃO
B86: 48.955.573/0001-03 | C86: CAIXA | D86: PORTAL DA PAMONHA LTDA (189) | E86: LUCRO PRESUMIDO | F86: KELVIN | G86: 45627 | H86: NÃO | I86: NÃO | J86: NÃO | K86: NÃO
B87: 42359555000174 | C87: BANCO | D87: RESENHA CONVENIENCIA LTDA (530) | E87: LUCRO REAL | F87: KELVIN | G87: 45627 | H87: NÃO | I87: NÃO | J87: NÃO | K87: NÃO
B88: 55033522000181 | C88: BANCO | D88: VERSATIL EXPRESS TRANSPORTES E CARGAS LTDA (158) | E88: SIMPLES NACIONAL | F88: KELVIN | G88: 45627 | H88: NÃO | I88: NÃO | J88: NÃO | K88: NÃO
B89: 41231672000195 | C89: BANCO | D89: WWC TECNOLOGIA LTDA (89) | E89: SIMPLES NACIONAL | F89: KELVIN | G89: 45627 | H89: NÃO | I89: NÃO | J89: NÃO | K89: NÃO
B90: 52613816000194 | C90: BANCO | D90: 3.5 ESPORTE E SAUDE LTDA | E90: LUCRO PRESUMIDO | F90: INGRID | G90: 45901 | H90: NÃO | I90: NÃO | J90: NÃO | K90: NÃO
B91: 38113906000195 | C91: BANCO | D91: MEATZ GYN BURGER COMERCIO DE ALIMENTOS LTDA | E91: LUCRO PRESUMIDO | F91: INGRID | G91: 45902 | H91: NÃO | I91: NÃO | J91: NÃO | K91: NÃO
B92: 24773977000100 | C92: BANCO | D92: MEATZ CENTRO SUL HAMBURGUERIA (ANTIGA AGUAS CLARAS) Delivery | E92: LUCRO PRESUMIDO | F92: INGRID | G92: 45839 | H92: NÃO | I92: NÃO | J92: NÃO | K92: NÃO
B93: 29936130000112 | C93: BANCO | D93: MEATZ CIDADE NOVA HAMBURGUERIA (ANTIGA WPC COMERCIO) Delivery | E93: LUCRO PRESUMIDO | F93: INGRID | G93: 45839 | H93: NÃO | I93: NÃO | J93: NÃO | K93: NÃO
B94: 47130092000198 | C94: BANCO | D94: MEATZ CONTAGEM HAMBURGUERIA ANTIGA SW DUE Delivery | E94: LUCRO PRESUMIDO | F94: INGRID | G94: 45839 | H94: NÃO | I94: NÃO | J94: NÃO | K94: NÃO

Sheet ECD E ECF 2023
B2: CNPJ | C2: EMPRESAS | D2: ECD | E2: DATA ENVIO ECD | F2: ECF | G2: DATA ENVIO ECF
A3: 1 | B3: 43798918000130 | C3: AG COMERCIO E MERCEARIA LTDA (408) | D3: ENVIADA | E3: 45413 | F3: ENVIADA | G3: -
A4: =A3+1 -> 2 | B4: 7462754000102 | C4: ASA NORTE BURGER COMÉRCIO DE ALIMENTOS LTDA (92) | D4: ENVIADA | E4: 45413 | F4: ENVIADA | G4: 45444
A5: =A4+1 -> 3 | B5: 686261000107 | C5: ASMRE ASSOC DOS SERV DO MIN DAS REL EXTERIORES (409) | D5: ENVIADA | E5: 45292 | F5: ENVIADA | G5: 45444
A6: =A5+1 -> 4 | B6: 20720905000143 | C6: BENENUTRI COMERCIAL LTDA (DF) (4) | D6: ENVIADA | E6: 45413 | F6: ENVIADA | G6: 45444
A7: =A6+1 -> 5 | B7: 20720905000243 | C7: BENENUTRI COMERCIAL LTDA (GO) (7) | D7: ENVIADA | E7: 45413 | F7: ENVIADA | G7: 45444
A8: =A7+1 -> 6 | B8: 50605321000198 | C8: BILLY BYTE SOLUÇÕES LTDA (76) | D8: ENVIADA | E8: 45413 | F8: ENVIADA | G8: 45444
A9: =A8+1 -> 7 | B9: 42863955000112 | C9: BN EXPRESS I COMÉRCIO E SERVIÇOS LTDA (DF) (427) | D9: ENVIADA | E9: 45414 | F9: ENVIADA | G9: 45444
A10: =A9+1 -> 8 | B10: 44891225000150 | C10: BN EXPRESS II COMÉRCIO E SERVIÇOS LTDA (DF) (427) | D10: ENVIADA | E10: 45383 | F10: ENVIADA | G10: 45444
A11: =A10+1 -> 9 | B11: 33013866000196 | C11: BSBURGER COMERCIO DE ALIMENTOS LTDA (117) | D11: ENVIADA | E11: 45413 | F11: ENVIADA | G11: 45444
A12: =A11+1 -> 10 | B12: 3469819600151 | C12: CENTRO DE MEDICINA DE FAMILIA DE BRASILIA LTDA (135) | D12: ENVIADA | E12: 45413 | F12: ENVIADA | G12: 45444
A13: =A12+1 -> 11 | B13: 22855971000156 | C13: CENTRO DE NEFROLOGIA DO DISTRITO FEDERAL LTDA (104) | D13: ENVIADA | E13: 45413 | F13: ENVIADA | G13: 45444
A14: =A13+1 -> 12 | B14: 52017539000157 | C14: CENTRO PREMIUM DE ESTETICA AVANCADA LTDA | D14: ENVIADA | E14: 45261 | F14: ENVIADA | G14: 45444
A15: =A14+1 -> 13 | B15: 36599674000100 | C15: EMPORIO DIVA COMERCIO DE PRODUTOS DE BELEZA EIRELI (11) | D15: ENVIADA | E15: 45413 | F15: ENVIADA | G15: 45444
... A17: =A16+1 -> 15 | B17: 29511026000267 | C17: IBEX COMERCIAL DE ALIMENTOS LTDA - GO (6) | D17: ENVIADA | E17: 45413 | F17: ENVIADA | G17: 45444
A18: =A17+1 -> 16 | B18: 36631894000165 | C18: IGREJA MINISTÉRIO NOVA VIDA (152) | D18: SEM MOVIMENTO | E18: SEM MOVIMENTO | F18: SEM MOVIMENTO | G18: SEM MOVIMENTO
A19: =A18+1 -> 17 | B19: 51467621000110 | C19: KLINGER ENGENHARIA LTDA (70) | D19: ENVIADA | E19: 45353 | F19: ENVIADA | G19: 45444
A20: =A19+1 -> 18 | B20: 34084938000159 | C20: LA BAMBA INDUSTRIA DE SORVETES EIRELI (127) | D20: ENVIADA | E20: 45292 | F20: ENVIADA | G20: -
A21: =A20+1 -> 19 | B21: 24187519000199 | C21: M.A COMERCIO E DISTRIBUICAO DE ALIMENTOS (44) | D21: SEM MOVIMENTO | E21: SEM MOVIMENTO | F21: SEM MOVIMENTO | G21: SEM MOVIMENTO
A22: =A21+1 -> 20 | B22: 24455157000170 | C22: MARIA EDILEUZA GUIMARAES OLIVEIRA | D22: ENVIADA | E22: 45413 | F22: ENVIADA | G22: 45444
A23: =A22+1 -> 21 | B23: 46149815000138 | C23: MOREIRA E FRANCO NEGOCIOS DIGITAIS | D23: ENVIADA | E23: 45413 | F23: ENVIADA | G23: 45444
A24: =A23+1 -> 22 | B24: 358589000139 | C24: OBRA ORGANIZAÇÃO BRASILIENSE DE CONSTRUÇÃO LTDA (36) | D24: ENVIADA | E24: 45413 | F24: ENVIADA | G24: 45444
A25: =A24+1 -> 23 | B25: 16872154000103 | C25: OITENTA FILMES LTDA (566) | D25: ENVIADA | E25: 45413 | F25: ENVIADA | G25: 45444
A26: =A25+1 -> 24 | B26: 39752648000150 | C26: P & C DUE COMERCIO DE ALIMENTOS LTDA (56) | D26: ENVIADA | E26: 45413 | F26: ENVIADA | G26: -
A27: =A26+1 -> 25 | B27: 18135832000180 | C27: PAULO PEREIRA LAUREANO DA SILVA | D27: ENVIADA | E27: 45413 | F27: ENVIADA | G27: 45444
A28: =A27+1 -> 26 | B28: 4291396000124 | C28: PROGAIA ENGENHARIA E MEIO AMBIENTE LTDA | D28: ENVIADA | E28: 45292 | F28: ENVIADA | G28: 45444
A29: =A28+1 -> 27 | B29: 9339178000136 | C29: QI AGENCIA, SERVICOS E INCENTIVOS A VENDAS LTDA (58) | D29: SEM MOVIMENTO | E29: SEM MOVIMENTO | F29: SEM MOVIMENTO | G29: SEM MOVIMENTO
A30: =A29+1 -> 28 | B30: 17266746000144 | C30: QI LOGISTICA PROMOCOES E EVENTOS EIRELI (59) | D30: SEM MOVIMENTO | E30: SEM MOVIMENTO | F30: SEM MOVIMENTO | G30: SEM MOVIMENTO
A31: =A30+1 -> 29 | B31: 42359555000174 | C31: RESENHA CONVENIENCIA LTDA (530) | D31: ENVIADA | E31: 45413 | F31: ENVIADA | G31: -
A32: =A31+1 -> 30 | B32: 29946991000181 | C32: SW BURGER COMERCIO LTDA (SUDOESTE) (94) | D32: ENVIADA | E32: 45413 | F32: ENVIADA | G32: -
A33: =A32+1 -> 31 | B33: 48683749000107 | C33: T&P NISHIYAMA INDUSTRIA DE ALIMENTOS LTDA | D33: ENVIADA | E33: 45414 | F33: ENVIADA | G33: -
A34: =A33+1 -> 32 | B34: 40188984000109 | C34: WPC DUE COMERCIO DE ALIMENTOS LTDA (60) | D34: ENVIADA | E34: 45413 | F34: ENVIADA | G34: 45444
A35: =A34+1 -> 33 | B35: 38287080000180 | C35: WSS NEGOCIOS DIGITAIS LTDA (200) | D35: ENVIADA | E35: 45383 | F35: ENVIADA | G35: 45444
A36: =A35+1 -> 34 | B36: 9205914000163 | C36: ZMC SANDRI GESTAO EMPRESARIAL E REPRESENTACOES EIRELI (356) | D36: ENVIADA | E36: 45352 | F36: ENVIADA | G36: 45444

Sheet INTEGRAÇÃO FOLHA
B2: CNPJ | C2: EMPRESAS | D2: INTEGRAÇÃO FOLHA | E2: ATIVIDADE | F2: RESPONSÁVEL | G2: INTEGRADO DE E ATÉ | H2: DATA DE FECHAMENTO | I2: ENVIO BALANCETES COMPETENCIA | J2: ECD
A3: =A2+1 -> 1 | B3: 53114412000119 | C3: 3.6 ESPORTE E SAÚDE LTDA (130) | D3: SIM | E3: SERVIÇOS | F3: KELVIN | G3: 01 a 05.2024 | H3: 45323 | I3: NÃO | J3: NÃO OBRIGADA
A4: =A3+1 -> 2 | B4: 9404697000130 | C4: ACADEMIA PERSONAL FITNESS LTDA (134) | D4: SIM | F4: KELVIN | G4: 01 a 05.2024 | H4: 45383
A5: =A4+1 -> 3 | B5: 54711482000117 | C5: AGENCIA 33 MARKETING E NEGOCIOS DIGITAIS LTDA (148) | D5: SIM | F5: KELVIN | G5: 01 a 05.2024 | H5: 45383
A6: =A5+1 -> 4 | B6: 42730674000182 | C6: AGRO VIRA LATA COMÉRCIO DE ARTIGOS PARA ANIMAIS E SERVIÇOES LTDA (389) | D6: SIM | E6: COMÉRCIO | F6: INGRID | G6: 01 a 05.2024 | H6: 45323 | I6: NÃO | J6: NÃO OBRIGADA
A7: =A6+1 -> 5 | B7: 28251192000128 | C7: ALMED SERVICOS MEDICOS LTDA (154) | D7: SIM | E7: SERVIÇOS | F7: INGRID | G7: 01 a 05.2024 | H7: 45323 | I7: NÃO | J7: NÃO OBRIGADA
A8: =A7+1 -> 6 | B8: 51798642000119 | C8: ANHANGUERA UNAÍ EDUCAÇÃO LTDA (72) | D8: SIM | E8: SERVIÇOS | F8: INGRID | G8: 01 a 05.2024 | H8: 45413 | I8: NÃO | J8: NÃO OBRIGADA
A9: =A8+1 -> 7 | B9: 33154864000117 | C9: AO QUADRADO FABRICAÇAO PROPRIA DE PRODUTOS ALIMENTICIOS LTDA (425) | D9: SIM | E9: COMÉRCIO/INDUSTRIA | F9: INGRID | G9: 01 a 05.2024 | H9: 45323 | I9: SIM | J9: NÃO OBRIGADA
A10: =A9+1 -> 8 | B10: 51055596000168 | C10: APS CONSULTORIA EM VENDAS E CRESCIMENTO LTDA (82) | D10: SIM | E10: SERVIÇOS | F10: INGRID | G10: 01 a 03.2024 | H10: 45323 | I10: NÃO | J10: NÃO OBRIGADA
A11: =A10+1 -> 9 | B11: 47133237000104 | C11: ASA NORTE DUE BURGER COMÉRCIO DE ALIMENTOS LTDA (551) | D11: SIM | E11: COMÉRCIO | F11: KELVIN | G11: 01 a 05.2024 | H11: 45383 | I11: SIM | J11: NÃO OBRIGADA
A12: =A11+1 -> 10 | B12: 686261000107 | C12: ASMRE ASSOC DOS SERV DO MIN DAS REL EXTERIORES (409) | D12: SIM | E12: TERCEIRO SETOR | F12: KELVIN | G12: 01 a 05.2024 | H12: 45413 | I12: SIM | J12: ENVIADA
A13: =A12+1 -> 11 | B13: 32474729000196 | C13: AUDIOFISA COMERCIO DE APARELHOS AUDITIVOS LTDA (115) | D13: SIM | E13: SERVIÇOS/COMÉRCIO | F13: KELVIN | G13: 01 a 05.2024 | H13: 45352 | I13: NÃO | J13: NÃO OBRIGADA
A14: =A13+1 -> 12 | B14: 49890800000114 | C14: B2JF COMÉRCIO DE ALIMENTOS LTDA (10) | D14: SIM | E14: COMÉRCIO | F14: KELVIN | G14: 01 a 05.2024 | H14: 45383 | I14: NÃO | J14: NÃO OBRIGADA
A15: =A14+1 -> 13 | B15: 51270240000147 | C15: BAHEA COZINHA BAIANA CONJUNTO NACIONAL LTDA (66) | D15: SIM | E15: COMÉRCIO | F15: KELVIN | G15: 01 a 05.2024 | H15: 45383 | I15: NÃO | J15: NÃO OBRIGADA
A16: =A15+1 -> 14 | B16: 33464640000101 | C16: BAHEA COZINHA BAIANA LTDA (382) | D16: SIM | E16: COMÉRCIO | F16: INGRID | G16: 01 a 05.2024 | H16: 45323 | I16: NÃO | J16: NÃO OBRIGADA
A17: =A16+1 -> 15 | B17: 21090763000140 | C17: BANCA CREPE TO GO COMERCIO LTDA (13) | D17: SIM | E17: COMÉRCIO | F17: INGRID | G17: 01 a 05.2024 | H17: 45323 | I17: NÃO | J17: NÃO OBRIGADA
... A37: =A36+1 -> 35 | B37: 40385101000142 | C37: DL ESPETINHOS COMERCIO DE ALIMENTOS LTDA (406) | D37: SIM | E37: COMÉRCIO | F37: INGRID | G37: 01 a 05.2024 | H37: 45352 | I37: NÃO | J37: NÃO OBRIGADA
A38: =A37+1 -> 36 | B38: 9440175000194 | C38: E. DO CARMO DA SILVA - CHIQUE BIJOUX (100) | D38: SIM | E38: COMÉRCIO | F38: KELVIN | G38: 01 a 05.2024 | H38: SEM MOVIMENTO | I38: SEM MOVIMENTO | J38: SEM MOVIMENTO
A39: =A38+1 -> 37 | B39: 36599674000100 | C39: EMPORIO DIVA COMERCIO DE PRODUTOS DE BELEZA EIRELI (11) | D39: SIM | E39: COMÉRCIO | F39: INGRID | G39: 01 a 05.2024 | H39: 45323 | I39: NÃO | J39: ENVIADA
A40: =A39+1 -> 38 | B40: 19252709000140 | C40: FARIA COMERCIO DE BEBIDAS,CONVENIENCIA,EVENTOS E LOCACOES LTDA (25) | D40: SIM | E40: COMÉRCIO | F40: KELVIN | G40: 01 a 05.2024 | H40: 45383 | I40: NÃO | J40: NÃO OBRIGADA
A41: =A40+1 -> 39 | B41: 36768275000117 | C41: FARIA DUE COMERCIO DE BEBIDAS E ALIMENTOS LTDA (21) | D41: SIM | E41: COMÉRCIO | F41: KELVIN | G41: 01 a 05.2024 | H41: 45383 | I41: NÃO | J41: NÃO OBRIGADA
A42: =A41+1 -> 40 | B42: 53808182000198 | C42: FENESTRA INDUSTRIA, COMERCIO, FABRICACAO E INSTALACAO DE METAISE VIDROS LTDA (133) | D42: SIM | E42: COMÉRCIO | F42: KELVIN | G42: 01 a 05.2024 | H42: 45352 | I42: NÃO | J42: NÃO OBRIGADA
A43: =A42+1 -> 41 | B43: 28460728000115 | C43: FERNANDO NAVES SOCIEDADE INDIVIDUAL DE ADVOCACIA (343) | D43: SIM | E43: SERVIÇOS | F43: KELVIN | G43: 01 a 05.2024 | H43: 45352 | I43: NÃO | J43: NÃO OBRIGADA
A44: =A43+1 -> 42 | B44: 29109712000186 | C44: FORTALEZA COMERCIO E DISTRIBUICAO DE ALIMENTOS LTDA (30) | D44: SIM | E44: COMÉRCIO/INDUSTRIA | F44: KELVIN | G44: 01 a 05.2024 | H44: 45383 | I44: NÃO | J44: NÃO OBRIGADA
A45: =A44+1 -> 43 | B45: 28234202000117 | C45: FRIO TECNICO'S - PRESTACAO DE SERVICOS DE INSTALACAO DE AR CONDICIONADO LTDA (102) | D45: SIM | E45: SERVIÇOS | F45: KELVIN | G45: 01 a 05.2024 | H45: 45352 | I45: NÃO | J45: NÃO OBRIGADA
A46: =A44+1 -> 43 | B46: 34974447000183 | C46: GARCIA KPP COMERCIO DE ALIMENTOS EIRELI (DONA MARICOTA) (336) | D46: SIM | E46: COMÉRCIO | F46: INGRID | G46: 01 a 05.2024 | H46: 45383 | I46: NÃO | J46: NÃO OBRIGADA
A47: =A45+1 -> 44 | B47: 50552948000128 | C47: GARDEN CAFÉ LTDA (65) | D47: SIM | E47: COMÉRCIO | F47: INGRID | G47: 01 a 05.2024 | H47: 45383 | I47: NÃO | J47: NÃO OBRIGADA
A48: =A47+1 -> 45 | B48: 17063002000122 | C48: GESTAO CONTADORES LTDA (1) | D48: SIM | E48: SERVIÇOS | F48: KELVIN | G48: 01 a 05.2024 | H48: SEM MOVIMENTO | I48: SEM MOVIMENTO | J48: SEM MOVIMENTO
A49: =A48+1 -> 46 | B49: 54447287000121 | C49: GRUPO MACEDO COM. ALIMENTOS II LTDA (146) | D49: SIM | E49: COMÉRCIO | F49: KELVIN | G49: 01 a 05.2024 | H49: 45383 | I49: NÃO | J49: NÃO OBRIGADA
A50: =A49+1 -> 47 | B50: 54447285000132 | C50: GRUPO MACEDO COM. ALIMENTOS III LTDA (147) | D50: SIM | E50: COMÉRCIO | F50: KELVIN | G50: 01 a 05.2024 | H50: 45383 | I50: NÃO | J50: NÃO OBRIGADA
A51: =A50+1 -> 48 | B51: 54447300000142 | C51: GRUPO MACEDO COM. ALIMENTOS LTDA (144) | D51: SIM | E51: COMÉRCIO | F51: KELVIN | G51: 01 a 05.2024 | H51: 45383 | I51: NÃO | J51: NÃO OBRIGADA
A52: =A51+1 -> 49 | B52: 38113906000195 | C52: GYN BURGER COMERCIO DE ALIMENTOS LTDA (51) | D52: SIM | E52: COMÉRCIO | F52: INGRID | G52: 01 a 05.2024 | H52: 45352 | I52: SIM | J52: NÃO OBRIGADA
A53: =A52+1 -> 50 | B53: 52077329000154 | C53: INAD STUDIO DE DANÇA E PILATES LTDA (97) | D53: SIM | E53: SERVIÇOS | F53: KELVIN | G53: 01 a 05.2024 | H53: 45352 | I53: NÃO | J53: NÃO OBRIGADA
A54: =A53+1 -> 51 | B54: 15615558000159 | C54: IRAMAR DOS SANTOS ALVARO (2) | D54: SIM | E54: COMÉRCIO | F54: KELVIN | G54: 01 a 05.2024 | H54: 45352 | I54: NÃO | J54: NÃO OBRIGADA
A55: =A54+1 -> 52 | B55: 33440538000176 | C55: J. CRISTO OPTICAL DO BRASIL EIRELI (33) | D55: SIM | E55: COMÉRCIO | F55: KELVIN | G55: 01 a 05.2024 | H55: 45352 | I55: NÃO | J55: NÃO OBRIGADA
A56: =A55+1 -> 53 | B56: 571616000112 | C56: JG LANCHES LTDA (128) | D56: SIM | E56: COMÉRCIO | F56: INGRID | G56: 01 a 05.2024 | H56: 45352 | I56: NÃO | J56: NÃO OBRIGADA
A57: =A56+1 -> 54 | B57: 43094426000164 | C57: JL ODONTOLOGIA PERSONALIZADA LTDA | D57: SIM | E57: COMÉRCIO | F57: KELVIN | G57: 01 a 05.2024 | H57: 45444
A58: =A57+1 -> 55 | B58: 20021254000101 | C58: KAROLLINE A. DE MELO (411) | D58: SIM | E58: SERVIÇOS | F58: INGRID | G58: 01 a 05.2024 | H58: 45352 | I58: NÃO | J58: NÃO OBRIGADA
A59: =A58+1 -> 56 | B59: 1156374000117 | C59: KAYA RESTAURANTE LTDA (201) | D59: SIM | E59: COMÉRCIO | F59: KELVIN | G59: 01 a 05.2024 | H59: 45323 | I59: NÃO | J59: NÃO OBRIGADA
A60: =A59+1 -> 57 | B60: 53411177000147 | C60: L.A LACERDA COMÉRCIO E BELEZA LTDA (123) | D60: SIM | E60: COMÉRCIO | F60: INGRID | G60: 01 a 05.2024 | H60: 45323 | I60: NÃO | J60: NÃO OBRIGADA
A61: =A60+1 -> 58 | B61: 49502482000177 | C61: L.L.F. DA SILVA LTDA (28) | D61: SIM | E61: SERVIÇOS | F61: INGRID | G61: 01 a 05.2024 | H61: 45352 | I61: NÃO | J61: NÃO OBRIGADA
A62: =A61+1 -> 59 | B62: 55172071000163 | C62: LAGO BURGER COMERCIO DE ALIMENTOS LTDA (161) | D62: SIM | E62: COMÉRCIO | F62: KELVIN | G62: 01 a 05.2024 | H62: 45413 | I62: NÃO | J62: NÃO OBRIGADA
A63: =A62+1 -> 60 | B63: 43730862000182 | C63: LD BRASIL COMERCIO DE PRODUTOS OPTICOS LTDA (504) | D63: SIM | E63: COMÉRCIO | F63: INGRID | G63: 01 a 05..2024 | H63: 45323 | I63: NÃO | J63: NÃO OBRIGADA
A64: =A63+1 -> 61 | B64: 46231380000176 | C64: LIS REFEIÇÕES COMÉRCIO DE ALIMENTOS LTDA (523) | D64: SIM | E64: COMÉRCIO | F64: KELVIN | G64: 01 a 05.2024 | H64: 45383 | I64: NÃO | J64: NÃO OBRIGADA
A65: =A64+1 -> 62 | B65: 47719603000101 | C65: LISI SANDRI ARQUITETURA E INTERIORES LTDA (562) | D65: SIM | E65: SERVIÇOS | F65: INGRID | G65: 01 a 05.2024 | H65: 45352 | I65: SIM | J65: NÃO OBRIGADA
A66: =A65+1 -> 63 | B66: 22554179000161 | C66: LIVE PERSONAL LTDA (136) | D66: SIM | F66: INGRID | G66: 01 a 05.2024 | H66: 45323
A67: =A66+1 -> 64 | B67: 31687088000195 | C67: LLIK COMERCIO DE ACESSORIOS E COSMETICOS LTDA (317) | D67: SIM | E67: COMÉRCIO | F67: KELVIN | G67: 01 a 05.2024 | H67: 45413 | I67: SIM | J67: NÃO OBRIGADA
A68: =A67+1 -> 65 | B68: 14433426000143 | C68: LOCAR ENGENHARIA LTDA ME | D68: SIM | E68: SERVIÇOS | F68: KELVIN | G68: 01 a 05.2024 | H68: 45383 | I68: NÃO | J68: NÃO OBRIGADA
A69: =A68+1 -> 66 | B69: 54151384000172 | C69: M.B GESTAO IMOBILIARIA LTDA (143) | D69: SIM | E69: SERVIÇOS/COMÉRCIO | F69: KELVIN | G69: 01 a 05.2024 | H69: 45383 | I69: NÃO | J69: NÃO OBRIGADA
A70: =A69+1 -> 67 | B70: 26525434000107 | C70: M&M COMERCIO DE ALIMENTOS LTDA (426) | D70: SIM | E70: COMÉRCIO | F70: INGRID | G70: 01 a 05.2024 | H70: 45352 | I70: NÃO | J70: NÃO OBRIGADA
A71: =A70+1 -> 68 | B71: 6374213000160 | C71: M2 OPTICAL DO BRASIL LTDA (119) | D71: SIM | E71: COMÉRCIO | F71: INGRID | G71: 01 a 05.2024 | H71: 45352 | I71: NÃO | J71: NÃO OBRIGADA
A72: =A71+1 -> 69 | B72: 42025646000173 | C72: M4 SERVICOS DE MANUTENCAO AUTOMOTIVA LTDA (371) | D72: SIM | E72: SERVIÇOS | F72: INGRID | G72: 01 a 05.2024 | H72: SEM MOVIMENTO | I72: SEM MOVIMENTO | J72: SEM MOVIMENTO
A73: =A72+1 -> 70 | B73: 40566970000173 | C73: MAIS SERVICOS DE ENGENHARIA LTDA (52) | D73: SIM | E73: SERVIÇOS | F73: INGRID | G73: 01 a 05.2024 | H73: 45352 | I73: NÃO | J73: NÃO OBRIGADA
A74: =A73+1 -> 71 | B74: 18312259000133 | C74: MAN CENTRO DE DESENVOLVIMENTO PSICOMOTOR LTDA (339) | D74: SIM | E74: SERVIÇOS | F74: INGRID | G74: 01 a 05.2024 | H74: 45323 | I74: NÃO | J74: NÃO OBRIGADA
A75: =A74+1 -> 72 | B75: 22582238000105 | C75: MARCOS AURELIO ROCHA NUNES (34) | D75: SIM | E75: SERVIÇOS | F75: KELVIN | G75: 01 a 05.2024 | H75: 45383 | I75: SIM | J75: NÃO OBRIGADA
A76: =A75+1 -> 73 | B76: 022.143.733-90 | C76: MARJORE TELES VIANA POMPEU | D76: SIM | E76: PESSOA FÍSICA | F76: KELVIN | G76: 01 a 05.2024 | H76: 45352 | I76: SIM | J76: NÃO OBRIGADA
A77: =A76+1 -> 74 | B77: 30046927000123 | C77: MEATZ BURGER BURITIS COMERCIO DE ALIMENTOS LTDA (379) | D77: SIM | E77: COMÉRCIO | F77: KELVIN | G77: 01 a 05.2024 | H77: 45383 | I77: SIM | J77: NÃO OBRIGADA
A78: =A77+1 -> 75 | B78: 32648600000157 | C78: MEATZ BURGER CASTELO COMERCIO DE ALIMENTOS LTDA (378) | D78: SIM | E78: COMÉRCIO | F78: KELVIN | G78: 01 a 05.2024 | H78: 45383 | I78: NÃO | J78: NÃO OBRIGADA
A79: =A78+1 -> 76 | B79: 28347784000229 | C79: MEATZ BURGER CENTRO SUL COMERCIO DE ALIMENTOS LTDA - FILIAL (386) | D79: SIM | E79: COMÉRCIO | F79: KELVIN | G79: 01 a 05.2024 | H79: 45383 | I79: NÃO | J79: NÃO OBRIGADA
A80: =A79+1 -> 77 | B80: 28347784000148 | C80: MEATZ BURGER CENTRO SUL COMERCIO DE ALIMENTOS LTDA - MATRIZ (380) | D80: SIM | E80: COMÉRCIO | F80: KELVIN | G80: 01 a 05.2024 | H80: 45383 | I80: NÃO | J80: NÃO OBRIGADA
A81: =A80+1 -> 78 | B81: 35027019000106 | C81: MEATZ BURGER CIDADE NOVA COMERCIO DE ALIMENTOS LTDA (377) | D81: SIM | E81: COMÉRCIO | F81: KELVIN | G81: 01 a 05.2024 | H81: 45383 | I81: NÃO | J81: NÃO OBRIGADA
A82: =A81+1 -> 79 | B82: 24733977000100 | C82: MEATZ BURGER COMERCIO DE ALIMENTOS EIRELI (50) | D82: SIM | E82: COMÉRCIO | F82: INGRID | G82: 01 a 05.2024 | H82: 45323 | I82: NÃO | J82: NÃO OBRIGADA
A83: =A82+1 -> 80 | B83: 38225461000135 | C83: MEATZ BURGER CONTAGEM COMERCIO DE ALIMENTOS LTDA (376) | D83: SIM | E83: COMÉRCIO | F83: KELVIN | G83: 01 a 05.2024 | H83: 45383 | I83: NÃO | J83: NÃO OBRIGADA
A84: =A83+1 -> 81 | B84: 27984050000107 | C84: METTA COMUNICAÇÃO E TREINAMENTOS (74) | D84: SIM | E84: SERVIÇOS | F84: INGRID | G84: 01 a 05.2024 | H84: 45017 | I84: NÃO | J84: NÃO OBRIGADA
A85: =A84+1 -> 82 | B85: 23701285000193 | C85: MH TRANSPORTES LTDA GO (40) | D85: SIM | E85: SERVIÇOS | F85: INGRID | G85: 01 a 05.2024 | H85: 45352 | I85: NÃO | J85: NÃO OBRIGADA
A86: =A85+1 -> 83 | B86: 31370812000152 | C86: MJH COMERCIO DE ARTIGOS OPTICOS LTDA (16) | D86: SIM | E86: COMÉRCIO | F86: INGRID | G86: 01 a 05.2024 | H86: 45352 | I86: NÃO | J86: NÃO OBRIGADA
A87: =A86+1 -> 84 | B87: 43938268000181 | C87: MMP COMÉRCIO DE ALIMENTOS - LM (507) | D87: SIM | E87: COMÉRCIO | F87: INGRID | G87: 01 a 05.2024 | H87: 45352 | I87: NÃO | J87: NÃO OBRIGADA
A88: =A87+1 -> 85 | B88: 41484228000181 | C88: MORAIS BRANCO PRODUTOS FARMACEUTICOS LTDA (353) | D88: SIM | E88: COMÉRCIO | F88: KELVIN | G88: 01 a 05.2024 | H88: 45383 | I88: SIM | J88: NÃO OBRIGADA
... A119: =A118+1 -> 116 | B119: 42017600000102 | C119: ZECA SMASH BURGER LTDA (43) | D119: SIM | E119: COMÉRCIO | F119: KELVIN | G119: 01 a 05.2024 | H119: 45352 | I119: NÃO | J119: NÃO OBRIGADA
